{
  "courseId": "100105",
  "courseName": "外科学",
  "chapterId": "100105027",
  "chapterName": "第二十七章 胸部损伤",
  "questionCount": 19,
  "expectedCount": 19,
  "questions": [
    {
      "questionTypeOption": null,
      "questionBankId": "2002338651446579848",
      "number": "2011N145B",
      "questionId": "1001050270001",
      "year": "2011",
      "questionBankCategoryId": "1001",
      "columnId": null,
      "courseId": "100105",
      "courseName": "外科学",
      "chapterId": "100105027",
      "chapterName": "第二十七章 胸部损伤",
      "questionBankType": "B",
      "topic": "下述疾病中，急需手术探查的是",
      "topicImage": null,
      "content": "[\"{\\\"answer\\\":\\\"C\\\",\\\"choose\\\":\\\"A\\\",\\\"right\\\":\\\"false\\\",\\\"content\\\":\\\"开放性气胸\\\"}\",\"{\\\"answer\\\":\\\"C\\\",\\\"choose\\\":\\\"B\\\",\\\"right\\\":\\\"false\\\",\\\"content\\\":\\\"闭合性气胸\\\"}\",\"{\\\"answer\\\":\\\"C\\\",\\\"choose\\\":\\\"C\\\",\\\"right\\\":\\\"true\\\",\\\"content\\\":\\\"进行性血气胸\\\"}\",\"{\\\"answer\\\":\\\"C\\\",\\\"choose\\\":\\\"D\\\",\\\"right\\\":\\\"false\\\",\\\"content\\\":\\\"张力性气胸\\\"}\"]",
      "answer": "C",
      "source": null,
      "examCenterRestore": "《外科学》（第10版）指出：  \n- **进行性血胸**：持续大量出血所致胸膜腔积血称为进行性血胸，其特征为引流量持续增加、血红蛋白进行性降低，保守治疗无法纠正休克，需及时行开胸探查手术以控制出血源。  \n- **开放性气胸**：急救处理需立即闭合胸壁伤口，转变为闭合性气胸，并行胸腔闭式引流，无需紧急手术探查。  \n- **闭合性气胸**：积气量少者可自行吸收，大量积气时行胸腔穿刺或闭式引流，一般不需手术探查。  \n- **张力性气胸**：需立即穿刺减压并安置闭式引流，若引流无效或合并复杂损伤才考虑手术。",
      "examCenterRestoreImage": null,
      "basicAnalysis": "A：开放性气胸急救需闭合伤口并闭式引流，非急需手术探查，该选项错误。<br> B：闭合性气胸以保守治疗为主（观察或引流），无需手术探查，该选项错误。<br> C <span style=\"color: #59BCA2; font-weight: bold;\"> [正确选项]</span>：进行性血气胸（进行性血胸）因持续活动性出血，保守治疗无效，需紧急手术探查止血，该选项正确。<br> D：张力性气胸首选穿刺减压和闭式引流，仅在引流失败时考虑手术，非急需探查，该选项错误。<br>",
      "basicAnalysisImage": null,
      "itemizeAnalysis": null,
      "itemizeAnalysisImage": null,
      "videoAnalysis": null,
      "schoolName": null,
      "score": "1.5",
      "scoreDescribe": null,
      "id": null,
      "comparisonSummary": "| **疾病类型**       | **紧急处理**                     | **是否需要手术探查** | **关键病理机制**                     |  \n|--------------------|----------------------------------|---------------------|--------------------------------------|  \n| **进行性血气胸**   | 抗休克治疗，立即手术探查         | 是                  | 持续出血致循环衰竭，保守治疗无效     |  \n| **开放性气胸**     | 闭合伤口+闭式引流                | 否                  | 纵隔扑动影响呼吸循环，引流可稳定病情 |  \n| **闭合性气胸**     | 观察或穿刺引流                   | 否                  | 积气缓慢吸收，肺复张后症状缓解       |  \n| **张力性气胸**     | 穿刺减压+闭式引流                | 否（引流无效时考虑）| 高压气体积累压迫纵隔，需快速减压     |  \n**核心要点**：  \n   **手术探查指征**：进行性血胸因出血无法自止，需手术控制；其他气胸类型优先非手术处理。  \n   **临床鉴别**：进行性血胸表现为引流量>200ml/h持续3小时、血红蛋白进行性下降；张力性气胸以呼吸困难、皮下气肿为特征。",
      "mindMap": "**解释**：  \n   **初筛重点**：优先排除进行性出血（引流量持续增加、休克难以纠正），确诊后需紧急手术。  \n   **非手术处理**：开放性/张力性气胸通过引流稳定病情；闭合性气胸以观察为主。  \n   **手术时机**：进行性血胸延迟手术可致失血性休克死亡；张力性气胸仅在引流失败后手术。",
      "mindMapImage": "https://image.muzhiyikao.com/mermaid_images/68aeec32/5334.png",
      "comparisonImages": null,
      "tags": null,
      "sort": null,
      "examRate": null,
      "userQuestionBankId": null,
      "userId": null,
      "isAnswer": 0,
      "userAnswer": null,
      "isRight": null,
      "isChop": 0,
      "isCollect": 0,
      "isLike": 0,
      "isNote": 0,
      "isComment": 0,
      "commentCount": null,
      "isContinue": 1,
      "sortNumber": 1,
      "knowledgeImage": null,
      "difficulty": 1,
      "collectTotal": 0,
      "answerTotal": 0,
      "rightTotal": 0,
      "rightRate": "0.0",
      "myAnswerCount": 0,
      "myRightCount": 0,
      "myRightRate": "0"
    },
    {
      "questionTypeOption": null,
      "questionBankId": "2002338651446579849",
      "number": "2014N84A",
      "questionId": "1001050270002",
      "year": "2014",
      "questionBankCategoryId": "1001",
      "columnId": null,
      "courseId": "100105",
      "courseName": "外科学",
      "chapterId": "100105027",
      "chapterName": "第二十七章 胸部损伤",
      "questionBankType": "A1",
      "topic": "下列胸部损伤中须考虑手术探查的是",
      "topicImage": null,
      "content": "[\"{\\\"answer\\\":\\\"A\\\",\\\"choose\\\":\\\"A\\\",\\\"right\\\":\\\"true\\\",\\\"content\\\":\\\"胸腹联合伤\\\"}\",\"{\\\"answer\\\":\\\"A\\\",\\\"choose\\\":\\\"B\\\",\\\"right\\\":\\\"false\\\",\\\"content\\\":\\\"胸部爆震伤\\\"}\",\"{\\\"answer\\\":\\\"A\\\",\\\"choose\\\":\\\"C\\\",\\\"right\\\":\\\"false\\\",\\\"content\\\":\\\"胸骨损伤\\\"}\",\"{\\\"answer\\\":\\\"A\\\",\\\"choose\\\":\\\"D\\\",\\\"right\\\":\\\"false\\\",\\\"content\\\":\\\"创伤性窒息\\\"}\"]",
      "answer": "A",
      "source": null,
      "examCenterRestore": "《外科学》（第10版）指出：  \n- **胸腹联合伤**：穿透性膈肌损伤需急诊手术治疗，根据伤情选择经胸、经腹或胸腹联合切口探查胸腹腔器官并修补损伤。  \n- **胸部爆震伤**：救治以维护呼吸循环功能为主，包括保持呼吸道通畅、给氧、辅助呼吸等，无需手术探查。  \n- **胸骨损伤**：类似肋骨骨折处理，无移位者保守治疗（休息、止痛），有移位者手法或手术复位，非必须手术探查。  \n- **创伤性窒息**：严密观察下对症处理，出血点自行吸收，无需手术探查；仅合并其他损伤时针对性处理。",
      "examCenterRestoreImage": null,
      "basicAnalysis": "A <span style=\"color: #59BCA2; font-weight: bold;\"> [正确选项]</span>：胸腹联合伤因可能伤及膈肌及腹腔脏器（如肝、脾），需急诊手术探查以控制出血和修复损伤，该选项正确。<br> B：胸部爆震伤以支持治疗为主（如氧疗、抗休克），无手术探查指征，该选项错误。<br> C：胸骨损伤一般保守治疗，移位严重时需复位但非紧急手术探查，该选项错误。<br> D：创伤性窒息以观察和对症处理为主，无手术探查必要性，该选项错误。<br>",
      "basicAnalysisImage": null,
      "itemizeAnalysis": null,
      "itemizeAnalysisImage": null,
      "videoAnalysis": null,
      "schoolName": null,
      "score": "1.5",
      "scoreDescribe": null,
      "id": null,
      "comparisonSummary": "| **损伤类型**       | **手术探查必要性** | **核心处理原则**                                  | **临床特征**                              |  \n|--------------------|--------------------|-------------------------------------------------|------------------------------------------|  \n| **胸腹联合伤**     | 是                 | 急诊手术探查（经胸/腹切口），修补膈肌及脏器损伤     | 胸腹部穿透伤，可能伴失血性休克、气胸      |  \n| **胸部爆震伤**     | 否                 | 维护呼吸循环功能（给氧、辅助通气、抗休克）          | 肺挫伤致低氧血症，无进行性出血            |  \n| **胸骨损伤**       | 否（一般）         | 无移位者休息止痛，移位者复位固定                  | 局部疼痛，罕见危及生命的并发症            |  \n| **创伤性窒息**     | 否                 | 严密观察，对症处理（出血点自行吸收）              | 上半身皮肤黏膜瘀斑，无内脏破裂征象        |  \n\n**关键点**：  \n   **手术探查指征**：仅当损伤可能导致进行性出血、脏器穿孔或膈肌破裂（如胸腹联合伤）时需手术。  \n   **非手术管理**：其他损伤以保守治疗为主，手术仅用于特定并发症（如胸骨严重移位）。",
      "mindMap": "**解释**：  \n   **初筛重点**：穿透伤或暴力致膈肌损伤（胸腹联合伤）是唯一需紧急手术的损伤。  \n   **决策依据**：爆震伤、胸骨损伤和创伤性窒息均无进行性内脏破坏，手术反而增加风险。  \n   **手术目标**：胸腹联合伤探查需彻底止血、修补膈肌及处理合并伤（如肝脾破裂）。",
      "mindMapImage": "https://image.muzhiyikao.com/mermaid_images/68aeec32/5335.png",
      "comparisonImages": null,
      "tags": null,
      "sort": null,
      "examRate": null,
      "userQuestionBankId": null,
      "userId": null,
      "isAnswer": 0,
      "userAnswer": null,
      "isRight": null,
      "isChop": 0,
      "isCollect": 0,
      "isLike": 0,
      "isNote": 0,
      "isComment": 0,
      "commentCount": null,
      "isContinue": null,
      "sortNumber": 2,
      "knowledgeImage": null,
      "difficulty": 1,
      "collectTotal": 0,
      "answerTotal": 0,
      "rightTotal": 0,
      "rightRate": "0.0",
      "myAnswerCount": 0,
      "myRightCount": 0,
      "myRightRate": "0"
    },
    {
      "questionTypeOption": null,
      "questionBankId": "2002338651446579850",
      "number": "2020N63A",
      "questionId": "1001050270003",
      "year": "2020",
      "questionBankCategoryId": "1001",
      "columnId": null,
      "courseId": "100105",
      "courseName": "外科学",
      "chapterId": "100105027",
      "chapterName": "第二十七章 胸部损伤",
      "questionBankType": "A1",
      "topic": "下列胸部创伤性疾病中，一般采用非手术治疗的是",
      "topicImage": null,
      "content": "[\"{\\\"answer\\\":\\\"A\\\",\\\"choose\\\":\\\"A\\\",\\\"right\\\":\\\"true\\\",\\\"content\\\":\\\"创伤性窒息\\\"}\",\"{\\\"answer\\\":\\\"A\\\",\\\"choose\\\":\\\"B\\\",\\\"right\\\":\\\"false\\\",\\\"content\\\":\\\"血胸\\\"}\",\"{\\\"answer\\\":\\\"A\\\",\\\"choose\\\":\\\"C\\\",\\\"right\\\":\\\"false\\\",\\\"content\\\":\\\"张力性气胸\\\"}\",\"{\\\"answer\\\":\\\"A\\\",\\\"choose\\\":\\\"D\\\",\\\"right\\\":\\\"false\\\",\\\"content\\\":\\\"开放性气胸\\\"}\"]",
      "answer": "A",
      "source": null,
      "examCenterRestore": "《外科学》（第10版）指出：先天性肌性斜颈的治疗强调早发现早治疗，非手术治疗适用于1岁以内的婴儿，目的在于促进局部肿块消散，防止胸锁乳突肌挛缩。具体方法包括局部热敷、按摩和手法牵拉，需教会家长每日坚持操作，多数患儿可自愈。手术治疗（如胸锁乳突肌松解术）仅适用于1岁以上患儿。",
      "examCenterRestoreImage": null,
      "basicAnalysis": "A：胸锁乳突肌切除术属于手术治疗，适用于1岁以上患儿，该婴儿仅20天，非首选，该选项错误。<br> B：给予肌松药物在教材中未提及作为治疗选项，且无循证医学支持，该选项错误。<br> C：胸锁乳突肌松解术是手术方法，适用于1岁以上患儿，该婴儿年龄不符，该选项错误。<br> D <span style=\"color: #59BCA2; font-weight: bold;\"> [正确选项]</span>：局部热敷、按摩是非手术治疗的核心方法，适用于新生儿期，可促进肿块消散，防止挛缩，该选项正确。<br>",
      "basicAnalysisImage": null,
      "itemizeAnalysis": null,
      "itemizeAnalysisImage": null,
      "videoAnalysis": null,
      "schoolName": null,
      "score": "2",
      "scoreDescribe": null,
      "id": null,
      "comparisonSummary": "| **治疗方式**       | **适用年龄** | **核心方法**              | **目的与效果**                              | **教材依据**              |  \n|---------------------|--------------|---------------------------|---------------------------------------------|---------------------------|  \n| **非手术治疗 (D)** | 1岁以内      | 热敷、按摩、手法牵拉      | 促进肿块消散，90%患儿2年内自愈              | 《外科学》（第10版） |  \n| **手术治疗**       | 1岁以上      | 胸锁乳突肌松解/切除术     | 矫正畸形，但无法逆转继发面部或颈椎畸形      | 《外科学》（第10版） |  \n| **关键原则**       | —            | 早干预、家长参与          | 预防继发畸形，避免手术                      | —                         |",
      "mindMap": "**解释**：  \n   **诊断核心**：颈部无痛性肿物+头部偏斜+下颌活动受限，符合先天性肌性斜颈典型表现。  \n   **年龄关键**：婴儿期（<1岁）首选非手术干预，手术仅用于>1岁患儿。  \n   **治疗逻辑**：热敷按摩促进局部血循环，加速肿块吸收；手法牵拉防止肌肉挛缩。",
      "mindMapImage": "https://image.muzhiyikao.com/mermaid_images/68aeec32/5336.png",
      "comparisonImages": null,
      "tags": null,
      "sort": null,
      "examRate": null,
      "userQuestionBankId": null,
      "userId": null,
      "isAnswer": 0,
      "userAnswer": null,
      "isRight": null,
      "isChop": 0,
      "isCollect": 0,
      "isLike": 0,
      "isNote": 0,
      "isComment": 0,
      "commentCount": null,
      "isContinue": null,
      "sortNumber": 3,
      "knowledgeImage": null,
      "difficulty": 1,
      "collectTotal": 0,
      "answerTotal": 0,
      "rightTotal": 0,
      "rightRate": "0.0",
      "myAnswerCount": 0,
      "myRightCount": 0,
      "myRightRate": "0"
    },
    {
      "questionTypeOption": null,
      "questionBankId": "2002338651446579851",
      "number": "2024N62A",
      "questionId": "1001050270004",
      "year": "2024",
      "questionBankCategoryId": "1001",
      "columnId": null,
      "courseId": "100105",
      "courseName": "外科学",
      "chapterId": "100105027",
      "chapterName": "第二十七章 胸部损伤",
      "questionBankType": "A1",
      "topic": "张力性气胸时，首选的急救措施是",
      "topicImage": null,
      "content": "[\"{\\\"answer\\\":\\\"B\\\",\\\"choose\\\":\\\"A\\\",\\\"right\\\":\\\"false\\\",\\\"content\\\":\\\"剖胸探查\\\"}\",\"{\\\"answer\\\":\\\"B\\\",\\\"choose\\\":\\\"B\\\",\\\"right\\\":\\\"true\\\",\\\"content\\\":\\\"胸膜腔穿刺减压\\\"}\",\"{\\\"answer\\\":\\\"B\\\",\\\"choose\\\":\\\"C\\\",\\\"right\\\":\\\"false\\\",\\\"content\\\":\\\"气管插管\\\"}\",\"{\\\"answer\\\":\\\"B\\\",\\\"choose\\\":\\\"D\\\",\\\"right\\\":\\\"false\\\",\\\"content\\\":\\\"气管切开\\\"}\"]",
      "answer": "B",
      "source": null,
      "examCenterRestore": "《外科学》（第10版）指出：  \n- **张力性气胸**：是可迅速致死的危急重症，急救需立即使用粗针头穿刺胸膜腔减压，并外接单向活瓣装置（如剪口手套或塑料袋），使高压气体排出而外界空气不能进入。  \n- **其他选项对比**：  \n  - 剖胸探查：适用于进行性血胸、心脏大血管损伤等，非张力性气胸的首选。  \n  - 气管插管：用于建立人工气道辅助呼吸，不直接解决胸腔高压。  \n  - 气管切开：针对气道梗阻（如喉头水肿），与气胸处理无关。",
      "examCenterRestoreImage": null,
      "basicAnalysis": "A：剖胸探查——适用于特定指征如进行性血胸或内脏损伤，张力性气胸急救无需开胸，该选项错误<br> B <span style=\"color: #59BCA2; font-weight: bold;\"> [正确选项]</span>：胸膜腔穿刺减压——教材明确为首选急救措施，可迅速降低胸腔内压，挽救生命，该选项正确<br> C：气管插管——属于辅助呼吸措施，用于改善通气，但无法解除胸腔高压，该选项错误<br> D：气管切开——用于解除上呼吸道梗阻，与张力性气胸病理机制无关，该选项错误<br>",
      "basicAnalysisImage": null,
      "itemizeAnalysis": null,
      "itemizeAnalysisImage": null,
      "videoAnalysis": null,
      "schoolName": null,
      "score": "2",
      "scoreDescribe": null,
      "id": null,
      "comparisonSummary": "| **气胸类型**       | **病理机制**                  | **首选急救措施**          | **后续处理**              |  \n|--------------------|-------------------------------|---------------------------|---------------------------|  \n| **张力性气胸**     | 活瓣机制致胸腔高压            | 胸膜腔穿刺减压            | 胸腔闭式引流              |  \n| **开放性气胸**     | 胸壁伤口致空气自由进出        | 封闭伤口变闭合性          | 清创缝合+闭式引流         |  \n| **闭合性气胸**     | 肺裂口闭合，积气稳定          | 穿刺抽气或观察            | 少量积气可自行吸收        |  \n| **进行性血胸**     | 持续出血致胸腔积血            | 补充血容量+开胸探查       | 控制出血源                |",
      "mindMap": "**关键逻辑**：  \n   **急救核心**：穿刺减压可快速逆转纵隔移位和呼吸循环衰竭（教材强调“迅速致死”特性）。  \n   **禁忌延迟**：气管插管/切开可能延误胸腔减压，加重病情（教材指出需优先处理胸腔高压）。  \n   **后续衔接**：穿刺后需尽快转为闭式引流，避免复发（教材描述后续安置引流管）。",
      "mindMapImage": "https://image.muzhiyikao.com/mermaid_images/68aeec32/5337.png",
      "comparisonImages": null,
      "tags": null,
      "sort": null,
      "examRate": null,
      "userQuestionBankId": null,
      "userId": null,
      "isAnswer": 0,
      "userAnswer": null,
      "isRight": null,
      "isChop": 0,
      "isCollect": 0,
      "isLike": 0,
      "isNote": 0,
      "isComment": 0,
      "commentCount": null,
      "isContinue": null,
      "sortNumber": 4,
      "knowledgeImage": null,
      "difficulty": 1,
      "collectTotal": 0,
      "answerTotal": 0,
      "rightTotal": 0,
      "rightRate": "0.0",
      "myAnswerCount": 0,
      "myRightCount": 0,
      "myRightRate": "0"
    },
    {
      "questionTypeOption": null,
      "questionBankId": "2002338651446579852",
      "number": "2022N62A",
      "questionId": "1001050270005",
      "year": "2022",
      "questionBankCategoryId": "1001",
      "columnId": null,
      "courseId": "100105",
      "courseName": "外科学",
      "chapterId": "100105027",
      "chapterName": "第二十七章 胸部损伤",
      "questionBankType": "A1",
      "topic": "下列关于创伤性窒息的病理生理改变，错误的是",
      "topicImage": null,
      "content": "[\"{\\\"answer\\\":\\\"B\\\",\\\"choose\\\":\\\"A\\\",\\\"right\\\":\\\"false\\\",\\\"content\\\":\\\"瞬间声门紧闭\\\"}\",\"{\\\"answer\\\":\\\"B\\\",\\\"choose\\\":\\\"B\\\",\\\"right\\\":\\\"true\\\",\\\"content\\\":\\\"小支气管和肺泡破裂\\\"}\",\"{\\\"answer\\\":\\\"B\\\",\\\"choose\\\":\\\"C\\\",\\\"right\\\":\\\"false\\\",\\\"content\\\":\\\"胸内压骤升\\\"}\",\"{\\\"answer\\\":\\\"B\\\",\\\"choose\\\":\\\"D\\\",\\\"right\\\":\\\"false\\\",\\\"content\\\":\\\"上腔静脉系统血逆流\\\"}\"]",
      "answer": "B",
      "source": null,
      "examCenterRestore": "《外科学》（第10版）指出：  \n- **创伤性窒息**：是钝性暴力作用于胸部所致的上半身广泛皮肤、黏膜、末梢毛细血管淤血及出血性损害。当胸部与上腹部受到暴力挤压时，病人声门紧闭，胸内压骤然剧增，右心房血液经无静脉瓣的上腔静脉系统逆流，造成上半身末梢静脉及毛细血管过度充盈扩张并破裂出血。",
      "examCenterRestoreImage": null,
      "basicAnalysis": "A：瞬间声门紧闭——教材明确描述暴力挤压时声门反射性关闭，该选项正确。<br> B <span style=\"color: #59BCA2; font-weight: bold;\"> [正确选项]</span>：小支气管和肺泡破裂——教材未提及小支气管或肺泡破裂，创伤性窒息的核心机制是静脉系统逆流和毛细血管破裂，而非肺泡损伤（肺泡破裂常见于气胸或肺挫伤），该选项描述错误。<br> C：胸内压骤升——教材强调胸内压“骤然剧增”，该选项正确。<br> D：上腔静脉系统血逆流——教材指出血液经无静脉瓣的上腔静脉逆流，该选项正确。<br>",
      "basicAnalysisImage": null,
      "itemizeAnalysis": null,
      "itemizeAnalysisImage": null,
      "videoAnalysis": null,
      "schoolName": null,
      "score": "2",
      "scoreDescribe": null,
      "id": null,
      "comparisonSummary": "| **病理生理改变**       | **描述**                                  | **临床意义**                          |  \n|------------------------|------------------------------------------|---------------------------------------|  \n| **声门紧闭**           | 暴力挤压时声门反射性关闭                 | 防止空气吸入，加剧胸内压升高          |  \n| **胸内压骤升**         | 胸腔压力急剧增高（可达数百mmHg）         | 外力传导至血管系统                   |  \n| **上腔静脉逆流**       | 血液逆流入无静脉瓣的上腔静脉系统         | 导致上半身毛细血管高压               |  \n| **毛细血管破裂**       | 头颈部皮肤、黏膜点状出血                 | 典型体征为“瘀斑面具征”               |  \n| **无肺泡破裂**         | 小支气管和肺泡破裂非本病特征（B错误）    | 常见于肺挫伤或气胸机制               |",
      "mindMap": "**关键逻辑**：  \n   **核心机制**：暴力挤压→声门关闭→胸内压剧增→静脉逆流→毛细血管破裂。  \n   **错误选项辨析**：小支气管和肺泡破裂是肺实质损伤的表现（如肺挫伤），与创伤性窒息的静脉系统逆流机制无关。  \n   **并发症**：颅内静脉高压可致暂时性意识障碍或视力损害，但非直接肺泡损伤所致。",
      "mindMapImage": "https://image.muzhiyikao.com/mermaid_images/68aeec32/5338.png",
      "comparisonImages": null,
      "tags": null,
      "sort": null,
      "examRate": null,
      "userQuestionBankId": null,
      "userId": null,
      "isAnswer": 0,
      "userAnswer": null,
      "isRight": null,
      "isChop": 0,
      "isCollect": 0,
      "isLike": 0,
      "isNote": 0,
      "isComment": 0,
      "commentCount": null,
      "isContinue": null,
      "sortNumber": 5,
      "knowledgeImage": null,
      "difficulty": 1,
      "collectTotal": 0,
      "answerTotal": 0,
      "rightTotal": 0,
      "rightRate": "0.0",
      "myAnswerCount": 0,
      "myRightCount": 0,
      "myRightRate": "0"
    },
    {
      "questionTypeOption": null,
      "questionBankId": "2002338651446579853",
      "number": "2007N126B",
      "questionId": "1001050270006",
      "year": "2007",
      "questionBankCategoryId": "1001",
      "columnId": null,
      "courseId": "100105",
      "courseName": "外科学",
      "chapterId": "100105027",
      "chapterName": "第二十七章 胸部损伤",
      "questionBankType": "B",
      "topic": "多发肋骨骨折的表现是",
      "topicImage": null,
      "content": "[\"{\\\"answer\\\":\\\"A\\\",\\\"choose\\\":\\\"A\\\",\\\"right\\\":\\\"true\\\",\\\"content\\\":\\\"胸壁反常呼吸\\\"}\",\"{\\\"answer\\\":\\\"A\\\",\\\"choose\\\":\\\"B\\\",\\\"right\\\":\\\"false\\\",\\\"content\\\":\\\"呼吸时纵隔扑动\\\"}\",\"{\\\"answer\\\":\\\"A\\\",\\\"choose\\\":\\\"C\\\",\\\"right\\\":\\\"false\\\",\\\"content\\\":\\\"气促胸闷、咯血\\\"}\",\"{\\\"answer\\\":\\\"A\\\",\\\"choose\\\":\\\"D\\\",\\\"right\\\":\\\"false\\\",\\\"content\\\":\\\"极度呼吸困难、发绀\\\"}\"]",
      "answer": "A",
      "source": null,
      "examCenterRestore": "《外科学》（第10版）指出：  \n- **多根多处肋骨骨折**：定义为在2根或2根以上相邻肋骨各自发生2处或2处以上骨折，导致局部胸壁失去肋骨支撑而软化，在自主呼吸时出现反常运动（即吸气时软化区胸壁内陷，呼气时外突），称为连枷胸（flail chest）。  \n- **纵隔扑动**：连枷胸的反常呼吸运动可造成两侧胸腔压力不均衡，导致纵隔随呼吸周期摆动（吸气时移向健侧，呼气时移向伤侧），影响肺通气和腔静脉回流。",
      "examCenterRestoreImage": null,
      "basicAnalysis": "A <span style=\"color: #59BCA2; font-weight: bold;\"> [正确选项]</span>：胸壁反常呼吸（连枷胸）是多发肋骨骨折的直接表现，因胸壁软化区失去支撑，在呼吸时出现内陷和外突的反常运动，该选项正确。<br> B <span style=\"color: #59BCA2; font-weight: bold;\"> [正确选项]</span>：呼吸时纵隔扑动是连枷胸的继发表现，由胸腔压力失衡引起，可导致低通气和呼吸衰竭，该选项正确。<br> C：气促胸闷、咯血多见于肺栓塞、肺结核或支气管扩张等疾病，非多发肋骨骨折的典型表现（咯血仅当合并肺裂伤时可能出现，但非直接关联），该选项错误。<br> D：极度呼吸困难、发绀更常见于张力性气胸或严重呼吸道梗阻，多发肋骨骨折虽可致呼吸困难，但“极度”描述更符合张力性气胸的特征，该选项错误。<br>",
      "basicAnalysisImage": null,
      "itemizeAnalysis": null,
      "itemizeAnalysisImage": null,
      "videoAnalysis": null,
      "schoolName": null,
      "score": "1.6",
      "scoreDescribe": null,
      "id": null,
      "comparisonSummary": "| **表现类型**       | **机制**                                      | **临床意义**                              | **相关疾病鉴别**                  |  \n|--------------------|---------------------------------------------|------------------------------------------|----------------------------------|  \n| **胸壁反常呼吸**   | 胸壁软化区失去支撑，吸气时内陷、呼气时外突      | 连枷胸的核心特征，导致通气障碍            | 特异性见于多根多处肋骨骨折        |  \n| **呼吸时纵隔扑动** | 胸腔压力失衡致纵隔周期性摆动                  | 影响肺通气和静脉回流，可致低氧血症        | 连枷胸的并发症，需与开放性气胸鉴别 |  \n| **气促胸闷、咯血** | 肺血管栓塞或实质损伤                          | 提示肺栓塞、肺癌或感染性疾病              | 非肋骨骨折直接表现                |  \n| **极度呼吸困难、发绀** | 高压气体压迫或呼吸道梗阻                      | 见于张力性气胸、大气道阻塞                | 肋骨骨折可伴呼吸困难，但非“极度”  |  \n\n**核心要点**：  \n   **多发肋骨骨折的核心表现**：反常呼吸（连枷胸）和纵隔扑动均源于胸壁结构破坏，需通过胸部CT或X线确诊。  \n   **鉴别关键**：  \n   肺栓塞（C选项）以突发胸痛、咯血为特征，CT肺动脉造影可确诊。  \n   张力性气胸（D选项）表现为气管偏移、皮下气肿，需紧急穿刺减压。",
      "mindMap": "**解释**：  \n   **初诊导向**：多发肋骨骨折首要表现为反常呼吸（连枷胸），触诊可及骨摩擦音，影像学（CT/X线）确认骨折范围。  \n   **继发影响**：反常呼吸→胸腔压力变化→纵隔扑动→通气/血流比例失调→低氧血症。  \n   **紧急处理**：优先镇痛（硬膜外或肋间神经阻滞）、呼吸支持（氧疗或机械通气），若合并血气胸需引流。  \n   **手术指征**：连枷胸伴呼吸衰竭时需肋骨固定术。",
      "mindMapImage": "https://image.muzhiyikao.com/mermaid_images/68aeec32/5339.png",
      "comparisonImages": null,
      "tags": null,
      "sort": null,
      "examRate": null,
      "userQuestionBankId": null,
      "userId": null,
      "isAnswer": 0,
      "userAnswer": null,
      "isRight": null,
      "isChop": 0,
      "isCollect": 0,
      "isLike": 0,
      "isNote": 0,
      "isComment": 0,
      "commentCount": null,
      "isContinue": null,
      "sortNumber": 6,
      "knowledgeImage": null,
      "difficulty": 1,
      "collectTotal": 0,
      "answerTotal": 0,
      "rightTotal": 0,
      "rightRate": "0.0",
      "myAnswerCount": 0,
      "myRightCount": 0,
      "myRightRate": "0"
    },
    {
      "questionTypeOption": null,
      "questionBankId": "2002338651446579854",
      "number": "2018N61A",
      "questionId": "1001050270007",
      "year": "2018",
      "questionBankCategoryId": "1001",
      "columnId": null,
      "courseId": "100105",
      "courseName": "外科学",
      "chapterId": "100105027",
      "chapterName": "第二十七章 胸部损伤",
      "questionBankType": "A1",
      "topic": "出现反常呼吸运动的胸部损伤是",
      "topicImage": null,
      "content": "[\"{\\\"answer\\\":\\\"C\\\",\\\"choose\\\":\\\"A\\\",\\\"right\\\":\\\"false\\\",\\\"content\\\":\\\"闭合性气胸\\\"}\",\"{\\\"answer\\\":\\\"C\\\",\\\"choose\\\":\\\"B\\\",\\\"right\\\":\\\"false\\\",\\\"content\\\":\\\"张力性气胸\\\"}\",\"{\\\"answer\\\":\\\"C\\\",\\\"choose\\\":\\\"C\\\",\\\"right\\\":\\\"true\\\",\\\"content\\\":\\\"多根多处肋骨骨折\\\"}\",\"{\\\"answer\\\":\\\"C\\\",\\\"choose\\\":\\\"D\\\",\\\"right\\\":\\\"false\\\",\\\"content\\\":\\\"开放性气胸\\\"}\"]",
      "answer": "C",
      "source": null,
      "examCenterRestore": "《外科学》（第10版）指出：多根多处肋骨骨折（≥2根相邻肋骨各≥2处骨折）导致局部胸壁失去肋骨支撑而软化，形成连枷胸（flail chest），表现为吸气时软化区胸壁内陷、呼气时外突的反常呼吸运动。其他损伤如闭合性气胸、张力性气胸、开放性气胸均无此特征。",
      "examCenterRestoreImage": null,
      "basicAnalysis": "A：闭合性气胸表现为胸膜腔积气、肺萎陷，无胸壁反常运动，该选项错误。<br> B：张力性气胸以高压性气胸为特征，可致纵隔移位和皮下气肿，但无胸壁软化区反常呼吸，该选项错误。<br> C <span style=\"color: #59BCA2; font-weight: bold;\"> [正确选项]</span>：多根多处肋骨骨折导致胸壁软化区失去支撑，引发反常呼吸运动（吸气内陷、呼气外突），该选项正确。<br> D：开放性气胸表现为纵隔扑动（吸气移向健侧、呼气移向伤侧），但无胸壁结构异常引起的反常呼吸，该选项错误。<br>",
      "basicAnalysisImage": null,
      "itemizeAnalysis": null,
      "itemizeAnalysisImage": null,
      "videoAnalysis": null,
      "schoolName": null,
      "score": "2",
      "scoreDescribe": null,
      "id": null,
      "comparisonSummary": "| **损伤类型**         | **是否出现反常呼吸** | **核心机制**                          | **典型临床特征**                          |  \n|----------------------|----------------------|---------------------------------------|-------------------------------------------|  \n| **多根多处肋骨骨折** | 是                   | 胸壁软化区失去支撑，呼吸时内陷/外突   | 局部压痛、胸壁畸形、低氧血症              |  \n| **闭合性气胸**       | 否                   | 肺萎陷，胸内压增加                    | 呼吸困难，叩诊鼓音，气管健侧移位          |  \n| **张力性气胸**       | 否                   | 活瓣机制致胸内高压，纵隔移位          | 极度呼吸困难，皮下气肿，循环衰竭          |  \n| **开放性气胸**       | 否                   | 空气自由进出，纵隔扑动                | 吸吮性伤口，纵隔摆动，呼吸循环障碍        |",
      "mindMap": "**解释**：  \n   **核心逻辑**：反常呼吸运动是连枷胸（多根多处肋骨骨折）的特异性表现，由胸壁软化区失去骨性支撑引起。  \n   **鉴别要点**：  \n   纵隔扑动（开放性气胸）是纵隔结构摆动，非胸壁局部运动。  \n   张力性气胸以胸内高压为特征，可伴皮下气肿但无胸壁软化。  \n   **临床处理**：连枷胸需优先稳定胸壁（如硬膜外镇痛、机械通气“内固定”），其他损伤需针对性处置（如闭式引流）。",
      "mindMapImage": "https://image.muzhiyikao.com/mermaid_images/68aeec32/5340.png",
      "comparisonImages": null,
      "tags": null,
      "sort": null,
      "examRate": null,
      "userQuestionBankId": null,
      "userId": null,
      "isAnswer": 0,
      "userAnswer": null,
      "isRight": null,
      "isChop": 0,
      "isCollect": 0,
      "isLike": 0,
      "isNote": 0,
      "isComment": 0,
      "commentCount": null,
      "isContinue": null,
      "sortNumber": 7,
      "knowledgeImage": null,
      "difficulty": 1,
      "collectTotal": 0,
      "answerTotal": 0,
      "rightTotal": 0,
      "rightRate": "0.0",
      "myAnswerCount": 0,
      "myRightCount": 0,
      "myRightRate": "0"
    },
    {
      "questionTypeOption": null,
      "questionBankId": "2002338651446579855",
      "number": "2015N175X",
      "questionId": "1001050270008",
      "year": "2015",
      "questionBankCategoryId": "1001",
      "columnId": null,
      "courseId": "100105",
      "courseName": "外科学",
      "chapterId": "100105027",
      "chapterName": "第二十七章 胸部损伤",
      "questionBankType": "X",
      "topic": "女性，28岁。车祸伤及右胸1小时。查体：P96次/分，R24次/分，BP140/95mmHg。右前胸未见反常呼吸运动，局部肿胀、压痛明显，右肺呼吸音降低，X线胸片示右侧8、9肋骨后端骨折，正确的处理有",
      "topicImage": null,
      "content": "[\"{\\\"answer\\\":\\\"ABD\\\",\\\"choose\\\":\\\"A\\\",\\\"right\\\":\\\"true\\\",\\\"content\\\":\\\"腹部B超\\\"}\",\"{\\\"answer\\\":\\\"ABD\\\",\\\"choose\\\":\\\"B\\\",\\\"right\\\":\\\"true\\\",\\\"content\\\":\\\"镇静止痛\\\"}\",\"{\\\"answer\\\":\\\"ABD\\\",\\\"choose\\\":\\\"C\\\",\\\"right\\\":\\\"false\\\",\\\"content\\\":\\\"牵引固定\\\"}\",\"{\\\"answer\\\":\\\"ABD\\\",\\\"choose\\\":\\\"D\\\",\\\"right\\\":\\\"true\\\",\\\"content\\\":\\\"胸带固定\\\"}\"]",
      "answer": "ABD",
      "source": null,
      "examCenterRestore": "《外科学》（第10版）指出：  \n- **肋骨骨折合并腹部损伤风险**：第8~10肋骨骨折位于肋弓区域，邻近膈肌和腹腔脏器，需警惕合并肝、脾或膈肌损伤，应行腹部影像学检查排查。  \n- **疼痛管理**：有效镇痛是肋骨骨折的核心处理原则，可改善呼吸功能、减少肺部并发症，常用药物包括非甾体抗炎药或阿片类药物。  \n- **固定方法**：闭合性单处肋骨骨折（如本例未见连枷胸）首选胸带固定，以减少断端活动、缓解疼痛；牵引固定仅适用于连枷胸（多根多处骨折伴反常呼吸）。",
      "examCenterRestoreImage": null,
      "basicAnalysis": "A <span style=\"color: #59BCA2; font-weight: bold;\"> [正确选项]</span>：第8~9肋骨后端骨折邻近膈肌和腹腔（如肝、脾），腹部B超可排查潜在脏器损伤或出血，该选项正确。<br> B <span style=\"color: #59BCA2; font-weight: bold;\"> [正确选项]</span>：镇静止痛是肋骨骨折的基础处理，可缓解疼痛、改善呼吸深度，避免继发肺不张，该选项正确。<br> C：牵引固定适用于连枷胸（多根多处骨折伴胸壁软化），本例未见反常呼吸运动，属单处骨折，无需牵引，该选项错误。<br> D <span style=\"color: #59BCA2; font-weight: bold;\"> [正确选项]</span>：胸带固定能稳定骨折断端、减轻疼痛，适用于闭合性单处肋骨骨折，该选项正确。<br>",
      "basicAnalysisImage": null,
      "itemizeAnalysis": null,
      "itemizeAnalysisImage": null,
      "videoAnalysis": null,
      "schoolName": null,
      "score": "2",
      "scoreDescribe": null,
      "id": null,
      "comparisonSummary": "| **处理措施**       | **适用场景**                  | **机制/目的**                          | **禁忌证/注意事项**                  |  \n|--------------------|-------------------------------|----------------------------------------|--------------------------------------|  \n| **腹部B超**        | 低位肋骨骨折（第8~12肋）      | 排查肝、脾、膈肌损伤及腹腔出血         | 无创检查，优先于CT以减少辐射暴露     |  \n| **镇静止痛**       | 所有肋骨骨折                  | 减轻疼痛、改善通气、预防肺不张         | 避免过度镇静抑制呼吸                 |  \n| **牵引固定**       | 连枷胸（多根多处骨折）        | 限制胸壁浮动、维持胸廓稳定性           | 单处骨折禁用，可能增加并发症风险     |  \n| **胸带固定**       | 闭合性单处肋骨骨折            | 减少断端移动、缓解疼痛、促进愈合       | 需定期调整松紧度，避免皮肤压疮      |",
      "mindMap": "**解释**：  \n   **初始评估**：生命体征平稳排除紧急干预（如张力性气胸）。  \n   **关键鉴别**：反常呼吸缺失提示非连枷胸，无需牵引固定（C选项错误）。  \n   **核心处理**：  \n   **镇痛（B）**：优先选择非甾体抗炎药，避免呼吸抑制。  \n   **固定（D）**：胸带限制断端活动，降低疼痛敏感性。  \n   **并发症排查（A）**：第8~9肋骨折易累及膈下区域，B超筛查隐匿损伤。  \n   **动态监测**：观察呼吸音变化、腹痛表现，警惕迟发性血胸或腹腔出血。",
      "mindMapImage": "https://image.muzhiyikao.com/mermaid_images/68aeec32/5341.png",
      "comparisonImages": null,
      "tags": null,
      "sort": null,
      "examRate": null,
      "userQuestionBankId": null,
      "userId": null,
      "isAnswer": 0,
      "userAnswer": null,
      "isRight": null,
      "isChop": 0,
      "isCollect": 0,
      "isLike": 0,
      "isNote": 0,
      "isComment": 0,
      "commentCount": null,
      "isContinue": null,
      "sortNumber": 8,
      "knowledgeImage": null,
      "difficulty": 1,
      "collectTotal": 0,
      "answerTotal": 0,
      "rightTotal": 0,
      "rightRate": "0.0",
      "myAnswerCount": 0,
      "myRightCount": 0,
      "myRightRate": "0"
    },
    {
      "questionTypeOption": null,
      "questionBankId": "2002338651446579856",
      "number": "2023N61A",
      "questionId": "1001050270009",
      "year": "2023",
      "questionBankCategoryId": "1001",
      "columnId": null,
      "courseId": "100105",
      "courseName": "外科学",
      "chapterId": "100105027",
      "chapterName": "第二十七章 胸部损伤",
      "questionBankType": "A2",
      "topic": "男性，23岁。因胸部钝挫伤2小时来诊。自诉呼吸困难。听诊右侧肺呼吸音消失，胸片提示右侧大量胸腔积液。为明确诊断，最有价值的检查是",
      "topicImage": null,
      "content": "[\"{\\\"answer\\\":\\\"C\\\",\\\"choose\\\":\\\"A\\\",\\\"right\\\":\\\"false\\\",\\\"content\\\":\\\"胸部CT\\\"}\",\"{\\\"answer\\\":\\\"C\\\",\\\"choose\\\":\\\"B\\\",\\\"right\\\":\\\"false\\\",\\\"content\\\":\\\"胸部超声\\\"}\",\"{\\\"answer\\\":\\\"C\\\",\\\"choose\\\":\\\"C\\\",\\\"right\\\":\\\"true\\\",\\\"content\\\":\\\"胸腔穿刺\\\"}\",\"{\\\"answer\\\":\\\"C\\\",\\\"choose\\\":\\\"D\\\",\\\"right\\\":\\\"false\\\",\\\"content\\\":\\\"胸部MRI\\\"}\"]",
      "answer": "C",
      "source": null,
      "examCenterRestore": "《外科学》（第10版）指出：  \n- **胸腔穿刺术**：是诊断胸腔积液性质的金标准，通过穿刺抽液可直接观察积液性状（如血液、脓液等），涂片镜检或培养可明确病因（如血胸、感染性积液）。对于创伤后胸腔积液，抽出不凝血可确诊血胸，是快速、直接的确诊方法。  \n- **其他检查对比**：  \n  - 胸部CT：用于评估胸内损伤范围（如肺挫伤、骨折），但无法直接确定积液性质。  \n  - 胸部超声：可定位积液并引导穿刺，但仅能间接提示积液存在，不能确诊成分。  \n  - 胸部MRI：主要用于软组织或血管损伤评估，在急性创伤性积液诊断中价值有限。",
      "examCenterRestoreImage": null,
      "basicAnalysis": "A：胸部CT——可显示胸腔积液量和伴随损伤（如肋骨骨折、肺挫伤），但无法直接分析积液性质（如是否为血性），需结合穿刺确诊，该选项错误<br> B：胸部超声——能实时评估积液位置和量，常用于引导穿刺定位，但无法通过影像直接区分积液类型（如血胸与脓胸），该选项错误<br> C <span style=\"color: #59BCA2; font-weight: bold;\"> [正确选项]</span>：胸腔穿刺——通过抽液可直接观察积液性状（如不凝血提示血胸），并进行实验室分析（如细胞计数、细菌培养），是确诊积液性质最直接、可靠的方法，该选项正确<br> D：胸部MRI——对软组织分辨率高，适用于慢性或复杂损伤（如神经、血管损伤），但耗时较长、成本高，且对急性积液性质诊断无优势，该选项错误<br>",
      "basicAnalysisImage": null,
      "itemizeAnalysis": null,
      "itemizeAnalysisImage": null,
      "videoAnalysis": null,
      "schoolName": null,
      "score": "2",
      "scoreDescribe": null,
      "id": null,
      "comparisonSummary": "| **检查方法**       | **核心用途**                          | **诊断价值**                          | **局限性**                          |  \n|--------------------|---------------------------------------|---------------------------------------|-------------------------------------|  \n| **胸腔穿刺 (C)**   | 直接抽取积液分析性状和成分            | 确诊积液性质（如血胸、脓胸）的金标准  | 有创操作，需严格无菌避免感染        |  \n| **胸部CT**         | 评估胸内整体损伤（骨折、器官破裂）    | 显示积液量及伴随病变，辅助定位穿刺    | 辐射暴露，无法直接定性积液          |  \n| **胸部超声**       | 实时引导穿刺定位，评估积液动态变化    | 无创、便捷，适合床旁急查              | 依赖操作者经验，不能替代积液分析    |  \n| **胸部MRI**        | 软组织、血管或神经损伤的精细成像      | 对慢性损伤、骨髓病变敏感              | 急性创伤中应用少，成本高且耗时长  |",
      "mindMap": "**关键逻辑**：  \n   **优先级**：胸腔穿刺是唯一能直接确诊积液性质的方法（教材强调其金标准地位）。  \n   **创伤导向**：急性外伤中，血胸最常见（占胸腔积液70%以上），穿刺不凝血是特异性标志。  \n   **辅助角色**：CT/超声用于全面伤情评估，但需在穿刺确诊后指导进一步治疗。",
      "mindMapImage": "https://image.muzhiyikao.com/mermaid_images/68aeec32/5342.png",
      "comparisonImages": null,
      "tags": null,
      "sort": null,
      "examRate": null,
      "userQuestionBankId": null,
      "userId": null,
      "isAnswer": 0,
      "userAnswer": null,
      "isRight": null,
      "isChop": 0,
      "isCollect": 0,
      "isLike": 0,
      "isNote": 0,
      "isComment": 0,
      "commentCount": null,
      "isContinue": null,
      "sortNumber": 9,
      "knowledgeImage": null,
      "difficulty": 1,
      "collectTotal": 0,
      "answerTotal": 0,
      "rightTotal": 0,
      "rightRate": "0.0",
      "myAnswerCount": 0,
      "myRightCount": 0,
      "myRightRate": "0"
    },
    {
      "questionTypeOption": null,
      "questionBankId": "2002338651446579857",
      "number": "1988N39A",
      "questionId": "1001050270010",
      "year": "1988",
      "questionBankCategoryId": "1001",
      "columnId": null,
      "courseId": "100105",
      "courseName": "外科学",
      "chapterId": "100105027",
      "chapterName": "第二十七章 胸部损伤",
      "questionBankType": "A1",
      "topic": "开放性气胸急救处理时应立即",
      "topicImage": null,
      "content": "[\"{\\\"answer\\\":\\\"D\\\",\\\"choose\\\":\\\"A\\\",\\\"right\\\":\\\"false\\\",\\\"content\\\":\\\"胸穿\\\"}\",\"{\\\"answer\\\":\\\"D\\\",\\\"choose\\\":\\\"B\\\",\\\"right\\\":\\\"false\\\",\\\"content\\\":\\\"闭式引流\\\"}\",\"{\\\"answer\\\":\\\"D\\\",\\\"choose\\\":\\\"C\\\",\\\"right\\\":\\\"false\\\",\\\"content\\\":\\\"加压吸氧\\\"}\",\"{\\\"answer\\\":\\\"D\\\",\\\"choose\\\":\\\"D\\\",\\\"right\\\":\\\"true\\\",\\\"content\\\":\\\"封闭胸部创口\\\"}\"]",
      "answer": "D",
      "source": null,
      "examCenterRestore": "《外科学》（第10版）指出：开放性气胸的急救处理要点是立即闭合胸壁伤口，将开放性气胸变为闭合性气胸，赢得挽救生命的时间。具体方法为使用无菌敷料（如凡士林纱布、棉垫）或清洁器材（如塑料袋、衣物）在伤员用力呼气末封盖吸吮性伤口，并加压包扎，随后迅速转送至医院进一步处理。",
      "examCenterRestoreImage": null,
      "basicAnalysis": "A：胸穿适用于闭合性气胸或血胸的积液抽吸，非开放性气胸的急救措施，该选项错误。<br> B：闭式引流是开放性气胸送达医院后的确定性治疗手段，非现场急救首选，该选项错误。<br> C：加压吸氧无法解决胸膜腔与外界相通导致的纵隔扑动和呼吸循环障碍，甚至可能加重气胸，该选项错误。<br> D <span style=\"color: #59BCA2; font-weight: bold;\"> [正确选项]</span>：封闭胸部创口可立即阻止空气自由进出胸膜腔，消除纵隔扑动，恢复胸腔负压，为后续救治争取时间，该选项正确。<br>",
      "basicAnalysisImage": null,
      "itemizeAnalysis": null,
      "itemizeAnalysisImage": null,
      "videoAnalysis": null,
      "schoolName": null,
      "score": "1",
      "scoreDescribe": null,
      "id": null,
      "comparisonSummary": "| **气胸类型**       | **急救处理核心**                  | **病理机制**                                  | **后续治疗**                              |  \n|--------------------|-----------------------------------|---------------------------------------------|------------------------------------------|  \n| **开放性气胸**     | 立即封闭伤口                     | 空气自由进出致纵隔扑动、呼吸循环衰竭          | 院内清创缝合+闭式引流                    |  \n| **张力性气胸**     | 穿刺减压+闭式引流                | 活瓣机制致胸内压持续升高，压迫纵隔及健侧肺    | 持续引流，无效时手术探查                 |  \n| **闭合性气胸**     | 观察或穿刺引流                   | 肺裂口闭合，积气缓慢吸收                    | 少量积气自行吸收，大量积气需引流         |  \n**关键点**：  \n   **开放性气胸致命机制**：纵隔扑动导致腔静脉回流受阻和双侧肺通气障碍，封闭伤口是阻断此过程的关键。  \n   **封闭操作要点**：需在伤员呼气末封盖伤口，避免吸气时负压吸入敷料。",
      "mindMap": "**解释**：  \n   **初筛重点**：识别吸吮性伤口（伴随呼吸气流声）是诊断开放性气胸的关键。  \n   **急救优先级**：封闭伤口需在院前立即完成，早于任何影像学检查或高级生命支持。  \n   **后续衔接**：封闭后仍需尽快转运，因可能合并内脏损伤或发展为张力性气胸。",
      "mindMapImage": "https://image.muzhiyikao.com/mermaid_images/68aeec32/5343.png",
      "comparisonImages": null,
      "tags": null,
      "sort": null,
      "examRate": null,
      "userQuestionBankId": null,
      "userId": null,
      "isAnswer": 0,
      "userAnswer": null,
      "isRight": null,
      "isChop": 0,
      "isCollect": 0,
      "isLike": 0,
      "isNote": 0,
      "isComment": 0,
      "commentCount": null,
      "isContinue": null,
      "sortNumber": 10,
      "knowledgeImage": null,
      "difficulty": 1,
      "collectTotal": 0,
      "answerTotal": 0,
      "rightTotal": 0,
      "rightRate": "0.0",
      "myAnswerCount": 0,
      "myRightCount": 0,
      "myRightRate": "0"
    },
    {
      "questionTypeOption": null,
      "questionBankId": "2002338651446579858",
      "number": "2011N146B",
      "questionId": "1001050270011",
      "year": "2011",
      "questionBankCategoryId": "1001",
      "columnId": null,
      "courseId": "100105",
      "courseName": "外科学",
      "chapterId": "100105027",
      "chapterName": "第二十七章 胸部损伤",
      "questionBankType": "B",
      "topic": "下述病例中，可引起纵隔扑动的是",
      "topicImage": null,
      "content": "[\"{\\\"answer\\\":\\\"A\\\",\\\"choose\\\":\\\"A\\\",\\\"right\\\":\\\"true\\\",\\\"content\\\":\\\"开放性气胸\\\"}\",\"{\\\"answer\\\":\\\"A\\\",\\\"choose\\\":\\\"B\\\",\\\"right\\\":\\\"false\\\",\\\"content\\\":\\\"闭合性气胸\\\"}\",\"{\\\"answer\\\":\\\"A\\\",\\\"choose\\\":\\\"C\\\",\\\"right\\\":\\\"false\\\",\\\"content\\\":\\\"进行性血气胸\\\"}\",\"{\\\"answer\\\":\\\"A\\\",\\\"choose\\\":\\\"D\\\",\\\"right\\\":\\\"false\\\",\\\"content\\\":\\\"张力性气胸\\\"}\"]",
      "answer": "A",
      "source": null,
      "examCenterRestore": "《外科学》（第10版）指出：开放性气胸时，外界空气经胸壁伤口自由进出胸膜腔，导致两侧胸膜腔压力不均衡的周期性变化，使纵隔在吸气时移向健侧、呼气时移向伤侧，称为纵隔扑动（mediastinal flutter）。闭合性气胸积气稳定，纵隔单向移位；张力性气胸以高压积气致纵隔持续偏移为主；进行性血气胸核心表现为失血性休克，无周期性压力变化。",
      "examCenterRestoreImage": null,
      "basicAnalysis": "A <span style=\"color: #59BCA2; font-weight: bold;\"> [正确选项]</span>：开放性气胸因呼吸时气体自由进出，引起两侧胸腔压力周期性失衡，导致纵隔扑动，该选项正确。<br> B：闭合性气胸积气缓慢吸收，纵隔向健侧单向移位，无周期性扑动，该选项错误。<br> C：进行性血气胸以持续出血和休克为特征，纵隔向健侧移位但无扑动，该选项错误。<br> D：张力性气胸因高压积气致纵隔持续向健侧偏移，伴皮下气肿，无周期性扑动，该选项错误。<br>",
      "basicAnalysisImage": null,
      "itemizeAnalysis": null,
      "itemizeAnalysisImage": null,
      "videoAnalysis": null,
      "schoolName": null,
      "score": "1.5",
      "scoreDescribe": null,
      "id": null,
      "comparisonSummary": "| **气胸类型**       | **纵隔变化**               | **核心机制**                              | **临床特征**                              |  \n|--------------------|----------------------------|------------------------------------------|------------------------------------------|  \n| **开放性气胸**     | 纵隔扑动（周期性移位）     | 呼吸时气体自由进出，双侧压力失衡          | 胸部吸吮性伤口，呼吸困难，纵隔扑动       |  \n| **闭合性气胸**     | 稳定向健侧移位             | 积气局限，肺萎陷                          | 叩诊鼓音，积气量少者可自行吸收           |  \n| **张力性气胸**     | 持续向健侧偏移             | 活瓣机制致高压积气                        | 极度呼吸困难，皮下气肿，需紧急减压       |  \n| **进行性血气胸**   | 向健侧移位（无扑动）       | 持续活动性出血致循环衰竭                  | 引流量＞200ml/h，血红蛋白进行性下降      |  \n\n**关键点**：  \n   **纵隔扑动机制**：仅开放性气胸因伤口开放导致呼吸时双侧胸腔压力周期性失衡。  \n   **临床鉴别**：听诊闻及吸吮样伤口声音是开放性气胸的特征性表现。",
      "mindMap": "**解释**：  \n   **初筛重点**：优先检查胸壁是否有开放性伤口，是诊断开放性气胸的关键。  \n   **压力机制**：开放性气胸的纵隔扑动源于吸气时健侧胸腔负压增大，伤侧气体流入致压力失衡；呼气时相反。  \n   **处理优先级**：开放性气胸需立即封闭伤口转为闭合性，再行闭式引流；其他类型按积气/出血程度处理。",
      "mindMapImage": "https://image.muzhiyikao.com/mermaid_images/68aeec32/5344.png",
      "comparisonImages": null,
      "tags": null,
      "sort": null,
      "examRate": null,
      "userQuestionBankId": null,
      "userId": null,
      "isAnswer": 0,
      "userAnswer": null,
      "isRight": null,
      "isChop": 0,
      "isCollect": 0,
      "isLike": 0,
      "isNote": 0,
      "isComment": 0,
      "commentCount": null,
      "isContinue": null,
      "sortNumber": 11,
      "knowledgeImage": null,
      "difficulty": 1,
      "collectTotal": 0,
      "answerTotal": 0,
      "rightTotal": 0,
      "rightRate": "0.0",
      "myAnswerCount": 0,
      "myRightCount": 0,
      "myRightRate": "0"
    },
    {
      "questionTypeOption": null,
      "questionBankId": "2002338651446579859",
      "number": "2019N61A",
      "questionId": "1001050270012",
      "year": "2019",
      "questionBankCategoryId": "1001",
      "columnId": null,
      "courseId": "100105",
      "courseName": "外科学",
      "chapterId": "100105027",
      "chapterName": "第二十七章 胸部损伤",
      "questionBankType": "A1",
      "topic": "可能发生纵膈扑动的胸部损伤的是",
      "topicImage": null,
      "content": "[\"{\\\"answer\\\":\\\"A\\\",\\\"choose\\\":\\\"A\\\",\\\"right\\\":\\\"true\\\",\\\"content\\\":\\\"开放性气胸\\\"}\",\"{\\\"answer\\\":\\\"A\\\",\\\"choose\\\":\\\"B\\\",\\\"right\\\":\\\"false\\\",\\\"content\\\":\\\"闭合性气胸\\\"}\",\"{\\\"answer\\\":\\\"A\\\",\\\"choose\\\":\\\"C\\\",\\\"right\\\":\\\"false\\\",\\\"content\\\":\\\"张力性气胸\\\"}\",\"{\\\"answer\\\":\\\"A\\\",\\\"choose\\\":\\\"D\\\",\\\"right\\\":\\\"false\\\",\\\"content\\\":\\\"进行性血胸\\\"}\"]",
      "answer": "A",
      "source": null,
      "examCenterRestore": "《外科学》（第10版）指出：开放性气胸时，外界空气随呼吸经胸壁缺损处自由进出胸膜腔，导致两侧胸膜腔压力周期性失衡，吸气时纵隔移向健侧，呼气时移向伤侧，形成纵隔扑动（mediastinal flutter），影响腔静脉回流和呼吸功能。",
      "examCenterRestoreImage": null,
      "basicAnalysis": "A <span style=\"color: #59BCA2; font-weight: bold;\"> [正确选项]</span>：开放性气胸因胸壁缺损导致空气自由进出，两侧胸腔压力失衡，引发纵隔扑动，该选项正确。<br> B：闭合性气胸胸膜腔压力低于大气压，纵隔向健侧移位但无周期性扑动，该选项错误。<br> C：张力性气胸因活瓣机制致胸内压持续升高，纵隔固定向健侧移位，无扑动现象，该选项错误。<br> D：进行性血胸主要表现为持续出血和纵隔移位，无周期性压力变化导致的纵隔扑动，该选项错误。<br>",
      "basicAnalysisImage": null,
      "itemizeAnalysis": null,
      "itemizeAnalysisImage": null,
      "videoAnalysis": null,
      "schoolName": null,
      "score": "2",
      "scoreDescribe": null,
      "id": null,
      "comparisonSummary": "| **损伤类型**       | **纵隔扑动可能性** | **核心机制**                          | **典型临床表现**                     |  \n|--------------------|--------------------|---------------------------------------|--------------------------------------|  \n| **开放性气胸**     | 是                 | 呼吸时两侧胸腔压力失衡，纵隔周期性移位 | 吸吮样伤口、呼吸困难、循环障碍       |  \n| **闭合性气胸**     | 否                 | 胸膜腔积气压低，纵隔单向移位           | 胸痛、呼吸音减弱、叩诊鼓音           |  \n| **张力性气胸**     | 否                 | 活瓣机制致胸内压持续升高，纵隔固定移位 | 极度呼吸困难、皮下气肿、休克         |  \n| **进行性血胸**     | 否                 | 持续出血致纵隔受压移位，无周期性变化   | 失血性休克、胸腔引流持续出血         |",
      "mindMap": "**解释**：  \n   **核心逻辑**：纵隔扑动需两侧胸腔压力周期性失衡，仅开放性气胸因空气自由进出满足此条件。  \n   **诊断关键**：  \n   开放性气胸：胸壁吸吮性伤口是典型特征。  \n   其他损伤：纵隔移位为单向（如张力性气胸）或无周期性变化（如血胸）。  \n   **处理优先级**：发现纵隔扑动需立即封闭胸壁缺损，防止呼吸循环衰竭。",
      "mindMapImage": "https://image.muzhiyikao.com/mermaid_images/68aeec32/5345.png",
      "comparisonImages": null,
      "tags": null,
      "sort": null,
      "examRate": null,
      "userQuestionBankId": null,
      "userId": null,
      "isAnswer": 0,
      "userAnswer": null,
      "isRight": null,
      "isChop": 0,
      "isCollect": 0,
      "isLike": 0,
      "isNote": 0,
      "isComment": 0,
      "commentCount": null,
      "isContinue": null,
      "sortNumber": 12,
      "knowledgeImage": null,
      "difficulty": 1,
      "collectTotal": 0,
      "answerTotal": 0,
      "rightTotal": 0,
      "rightRate": "0.0",
      "myAnswerCount": 0,
      "myRightCount": 0,
      "myRightRate": "0"
    },
    {
      "questionTypeOption": null,
      "questionBankId": "2002338651446579860",
      "number": "2007N125B",
      "questionId": "1001050270013",
      "year": "2007",
      "questionBankCategoryId": "1001",
      "columnId": null,
      "courseId": "100105",
      "courseName": "外科学",
      "chapterId": "100105027",
      "chapterName": "第二十七章 胸部损伤",
      "questionBankType": "B",
      "topic": "张力性气胸常见的呼吸状态表现是",
      "topicImage": null,
      "content": "[\"{\\\"answer\\\":\\\"D\\\",\\\"choose\\\":\\\"A\\\",\\\"right\\\":\\\"false\\\",\\\"content\\\":\\\"胸壁反常呼吸\\\"}\",\"{\\\"answer\\\":\\\"D\\\",\\\"choose\\\":\\\"B\\\",\\\"right\\\":\\\"false\\\",\\\"content\\\":\\\"呼吸时纵隔扑动\\\"}\",\"{\\\"answer\\\":\\\"D\\\",\\\"choose\\\":\\\"C\\\",\\\"right\\\":\\\"false\\\",\\\"content\\\":\\\"气促胸闷、咯血\\\"}\",\"{\\\"answer\\\":\\\"D\\\",\\\"choose\\\":\\\"D\\\",\\\"right\\\":\\\"true\\\",\\\"content\\\":\\\"极度呼吸困难、发绀\\\"}\"]",
      "answer": "D",
      "source": null,
      "examCenterRestore": "《外科学》（第10版）指出：张力性气胸（tension pneumothorax）为气管、支气管或肺损伤处形成活瓣，气体随每次吸气进入胸膜腔并积累增多，导致胸膜腔压力高于大气压，病人表现为严重或极度呼吸困难、烦躁、意识障碍、大汗淋漓、发绀。",
      "examCenterRestoreImage": null,
      "basicAnalysis": "A：胸壁反常呼吸是多发肋骨骨折（连枷胸）的表现，由胸壁软化导致吸气时内陷、呼气时外突，该选项错误。<br> B：呼吸时纵隔扑动是开放性气胸的特征，因胸腔压力失衡致纵隔周期性摆动，该选项错误。<br> C：气促胸闷、咯血多见于肺栓塞、肺挫伤或支气管疾病，非张力性气胸典型表现，该选项错误。<br> D <span style=\"color: #59BCA2; font-weight: bold;\"> [正确选项]</span>：极度呼吸困难、发绀是张力性气胸的核心表现，因高压气体压迫肺和纵隔，影响通气和循环，该选项正确。<br>",
      "basicAnalysisImage": null,
      "itemizeAnalysis": null,
      "itemizeAnalysisImage": null,
      "videoAnalysis": null,
      "schoolName": null,
      "score": "1.6",
      "scoreDescribe": null,
      "id": null,
      "comparisonSummary": "| **疾病类型**       | **主要呼吸状态表现**          | **病理机制**                                  | **紧急处理**                     |  \n|--------------------|-----------------------------|---------------------------------------------|--------------------------------|  \n| **张力性气胸**     | 极度呼吸困难、发绀、大汗     | 活瓣机制致胸内压持续升高，压迫肺和纵隔       | 立即穿刺减压+闭式引流          |  \n| **开放性气胸**     | 呼吸困难伴纵隔扑动           | 空气自由进出致纵隔摆动，影响呼吸循环         | 封闭伤口+闭式引流              |  \n| **闭合性气胸**     | 轻度呼吸困难或无             | 肺裂口闭合，积气缓慢吸收                   | 观察或穿刺引流                 |  \n| **多发肋骨骨折**   | 胸壁反常呼吸                 | 胸壁软化区失去支撑，呼吸时内陷外突         | 镇痛、呼吸支持，严重时手术固定 |  \n| **肺栓塞**         | 气促胸闷、咯血               | 肺动脉阻塞致通气/血流比例失调              | 抗凝、溶栓或取栓               |",
      "mindMap": "**解释**：  \n   **初诊重点**：张力性气胸以突发极度呼吸困难、发绀为特征，常伴皮下气肿和气管向健侧偏移。  \n   **紧急干预**：穿刺减压是救命关键，延迟处理可致呼吸循环衰竭。  \n   **后续管理**：闭式引流后需监测引流效果，持续漏气提示需手术修复损伤。",
      "mindMapImage": "https://image.muzhiyikao.com/mermaid_images/68aeec32/5346.png",
      "comparisonImages": null,
      "tags": null,
      "sort": null,
      "examRate": null,
      "userQuestionBankId": null,
      "userId": null,
      "isAnswer": 0,
      "userAnswer": null,
      "isRight": null,
      "isChop": 0,
      "isCollect": 0,
      "isLike": 0,
      "isNote": 0,
      "isComment": 0,
      "commentCount": null,
      "isContinue": null,
      "sortNumber": 13,
      "knowledgeImage": null,
      "difficulty": 1,
      "collectTotal": 0,
      "answerTotal": 0,
      "rightTotal": 0,
      "rightRate": "0.0",
      "myAnswerCount": 0,
      "myRightCount": 0,
      "myRightRate": "0"
    },
    {
      "questionTypeOption": null,
      "questionBankId": "2002338651446579861",
      "number": "2013N79A",
      "questionId": "1001050270014",
      "year": "2013",
      "questionBankCategoryId": "1001",
      "columnId": null,
      "courseId": "100105",
      "courseName": "外科学",
      "chapterId": "100105027",
      "chapterName": "第二十七章 胸部损伤",
      "questionBankType": "A1",
      "topic": "下列急性胸部损伤中，对生命威胁最大的是",
      "topicImage": null,
      "content": "[\"{\\\"answer\\\":\\\"C\\\",\\\"choose\\\":\\\"A\\\",\\\"right\\\":\\\"false\\\",\\\"content\\\":\\\"闭合性气胸\\\"}\",\"{\\\"answer\\\":\\\"C\\\",\\\"choose\\\":\\\"B\\\",\\\"right\\\":\\\"false\\\",\\\"content\\\":\\\"开放性气胸\\\"}\",\"{\\\"answer\\\":\\\"C\\\",\\\"choose\\\":\\\"C\\\",\\\"right\\\":\\\"true\\\",\\\"content\\\":\\\"张力性气胸\\\"}\",\"{\\\"answer\\\":\\\"C\\\",\\\"choose\\\":\\\"D\\\",\\\"right\\\":\\\"false\\\",\\\"content\\\":\\\"血气胸\\\"}\"]",
      "answer": "C",
      "source": null,
      "examCenterRestore": "《外科学》（第10版）指出：  \n- **张力性气胸**：因气管、支气管或肺损伤处形成活瓣机制，气体随每次吸气进入胸膜腔并积累增多，导致胸膜腔压力持续高于大气压，压迫纵隔和健侧肺，引起腔静脉回流障碍。典型表现为严重或极度呼吸困难、烦躁、意识障碍、大汗淋漓、发绀，是可迅速致死的危急重症，需立即穿刺减压或闭式引流。  \n- **闭合性气胸**：胸壁伤口闭合或肺裂口较小，积气缓慢吸收，少量积气可自行恢复，大量积气需引流，一般不直接危及生命。  \n- **开放性气胸**：外界空气自由进出胸膜腔导致纵隔扑动，影响呼吸循环功能，但急救时封闭伤口可转为闭合性气胸，威胁相对可控。  \n- **血气胸**：胸膜腔积血与积气并存，进行性血胸需手术探查，但整体威胁程度低于张力性气胸的急性高压状态。",
      "examCenterRestoreImage": null,
      "basicAnalysis": "A：闭合性气胸积气量少时可自行吸收，大量积气需引流，但无进行性高压机制，对生命威胁较小，该选项错误。<br> B：开放性气胸导致纵隔扑动和呼吸循环障碍，但通过及时封闭伤口可稳定病情，威胁较张力性气胸轻，该选项错误。<br> C <span style=\"color: #59BCA2; font-weight: bold;\"> [正确选项]</span>：张力性气胸因活瓣机制致胸内压持续升高，压迫纵隔及健侧肺，引起急性呼吸循环衰竭，可迅速致死，是急性胸部损伤中威胁最大者，该选项正确。<br> D：血气胸包括血胸和气胸，进行性血胸需紧急手术，但张力性气胸的病理进展更快且更易导致即时死亡，该选项错误。<br>",
      "basicAnalysisImage": null,
      "itemizeAnalysis": null,
      "itemizeAnalysisImage": null,
      "videoAnalysis": null,
      "schoolName": null,
      "score": "1.5",
      "scoreDescribe": null,
      "id": null,
      "comparisonSummary": "| **损伤类型**       | **生命威胁机制**                          | **关键临床表现**                          | **紧急处理**                          | **预后**                              |  \n|--------------------|-----------------------------------------|-----------------------------------------|--------------------------------------|--------------------------------------|  \n| **张力性气胸**     | 活瓣机制致胸内压持续升高，压迫纵隔和健侧肺，腔静脉回流受阻 | 极度呼吸困难、发绀、烦躁、意识障碍、皮下气肿      | 立即穿刺减压，闭式引流                  | 可迅速致死，急救不及时死亡率高            |  \n| **开放性气胸**     | 空气自由进出致纵隔扑动，影响呼吸循环              | 吸吮性伤口、呼吸困难、气管移位              | 封闭伤口，转为闭合性气胸后引流            | 及时处理可稳定，延迟处理可致休克          |  \n| **闭合性气胸**     | 肺萎陷致通气/血流比例失调，积气缓慢吸收           | 轻度无症状或呼吸受限，大量积气时叩诊鼓音        | 观察或穿刺引流                        | 良好，无即时生命危险                    |  \n| **血气胸**         | 积血和积气压迫肺组织，进行性出血可致休克          | 低血容量休克表现、胸腔积液征象              | 引流积血积气，进行性出血时手术            | 进行性血胸威胁大，但整体次于张力性气胸      |  \n**核心要点**：张力性气胸因高压机制不可自限，可在数分钟内致呼吸心跳停止；其他损伤通过急救可暂时控制。",
      "mindMap": "**解释**：  \n   **初筛重点**：优先识别张力性气胸（皮下气肿、极度呼吸困难），因其可数分钟内致死。  \n   **急救优先级**：张力性气胸需立即院前穿刺减压；开放性气胸封闭伤口后威胁降低；闭合性气胸和稳定血气胸可后续处理。  \n   **决策依据**：张力性气胸的活瓣机制导致不可逆压力积累，其他损伤无此特性。",
      "mindMapImage": "https://image.muzhiyikao.com/mermaid_images/68aeec32/5347.png",
      "comparisonImages": null,
      "tags": null,
      "sort": null,
      "examRate": null,
      "userQuestionBankId": null,
      "userId": null,
      "isAnswer": 0,
      "userAnswer": null,
      "isRight": null,
      "isChop": 0,
      "isCollect": 0,
      "isLike": 0,
      "isNote": 0,
      "isComment": 0,
      "commentCount": null,
      "isContinue": null,
      "sortNumber": 14,
      "knowledgeImage": null,
      "difficulty": 1,
      "collectTotal": 0,
      "answerTotal": 0,
      "rightTotal": 0,
      "rightRate": "0.0",
      "myAnswerCount": 0,
      "myRightCount": 0,
      "myRightRate": "0"
    },
    {
      "questionTypeOption": null,
      "questionBankId": "2002338651446579862",
      "number": "2025N162X",
      "questionId": "1001050270015",
      "year": "2025",
      "questionBankCategoryId": "1001",
      "columnId": null,
      "courseId": "100105",
      "courseName": "外科学",
      "chapterId": "100105027",
      "chapterName": "第二十七章 胸部损伤",
      "questionBankType": "X",
      "topic": "下列关于张力性气胸的叙述，正确的有",
      "topicImage": null,
      "content": "[\"{\\\"answer\\\":\\\"ACD\\\",\\\"choose\\\":\\\"A\\\",\\\"right\\\":\\\"true\\\",\\\"content\\\":\\\"肺损伤处形成活瓣\\\"}\",\"{\\\"answer\\\":\\\"ACD\\\",\\\"choose\\\":\\\"B\\\",\\\"right\\\":\\\"false\\\",\\\"content\\\":\\\"纵隔左右摆动\\\"}\",\"{\\\"answer\\\":\\\"ACD\\\",\\\"choose\\\":\\\"C\\\",\\\"right\\\":\\\"true\\\",\\\"content\\\":\\\"呼吸循环障碍\\\"}\",\"{\\\"answer\\\":\\\"ACD\\\",\\\"choose\\\":\\\"D\\\",\\\"right\\\":\\\"true\\\",\\\"content\\\":\\\"可出现皮下气肿\\\"}\"]",
      "answer": "ACD",
      "source": null,
      "examCenterRestore": "《外科学》（第10版）指出：  \n- **张力性气胸**：是气管、支气管或肺损伤处形成活瓣，气体随每次吸气进入胸膜腔并积累增多，导致胸膜腔压力高于大气压（高压性气胸）。伤侧肺严重萎陷，纵隔显著向健侧移位，健侧肺受压，腔静脉回流障碍，引起严重呼吸循环功能障碍。高于大气压的胸内压驱使气体进入纵隔或胸壁软组织，形成纵隔气肿或面、颈、胸部的皮下气肿。临床表现为极度呼吸困难、发绀、大汗淋漓，甚至意识障碍。",
      "examCenterRestoreImage": null,
      "basicAnalysis": "A <span style=\"color: #59BCA2; font-weight: bold;\"> [正确选项]</span>：肺损伤处形成活瓣——教材明确描述张力性气胸的核心机制是损伤处形成活瓣，气体单向进入胸膜腔无法排出，该选项正确。<br> B：纵隔左右摆动——教材指出纵隔左右摆动（纵隔扑动）是开放性气胸的特征（吸气时移向健侧，呼气时移向伤侧），张力性气胸表现为纵隔持续向健侧移位，无摆动现象，该选项错误。<br> C <span style=\"color: #59BCA2; font-weight: bold;\"> [正确选项]</span>：呼吸循环障碍——教材强调张力性气胸导致肺萎陷、纵隔移位和腔静脉回流受阻，引发严重呼吸困难和循环衰竭（如低血压、发绀），该选项正确。<br> D <span style=\"color: #59BCA2; font-weight: bold;\"> [正确选项]</span>：可出现皮下气肿——教材描述高压气体可进入胸壁软组织形成皮下气肿，是张力性气胸的典型并发症，该选项正确。<br>",
      "basicAnalysisImage": null,
      "itemizeAnalysis": null,
      "itemizeAnalysisImage": null,
      "videoAnalysis": null,
      "schoolName": null,
      "score": "2",
      "scoreDescribe": null,
      "id": null,
      "comparisonSummary": "| **特征**               | **张力性气胸**                          | **开放性气胸**                          | **闭合性气胸**                          |  \n|------------------------|-----------------------------------------|-----------------------------------------|-----------------------------------------|  \n| **机制**               | 损伤处活瓣形成，气体单向进入            | 胸壁伤口开放，气体自由进出              | 肺裂口闭合，气体稳定积聚                |  \n| **胸内压**            | 高于大气压                              | 接近大气压                              | 轻度增高或稳定                          |  \n| **纵隔变化**          | 持续向健侧移位                          | 周期性摆动（纵隔扑动）                  | 轻度向健侧移位                          |  \n| **呼吸循环障碍**      | 严重（低氧血症、休克）                  | 中度（通气障碍）                        | 轻度或无                                |  \n| **皮下气肿**          | 常见（高压气体扩散）                    | 少见                                    | 罕见                                    |  \n| **急救措施**          | 立即穿刺减压+闭式引流                   | 封闭伤口变闭合性+闭式引流               | 穿刺抽气或观察                          |",
      "mindMap": "**关键逻辑**：  \n   **核心鉴别**：张力性气胸需通过高压气体、皮下气肿和持续纵隔移位区分于其他气胸类型（教材）。  \n   **急救优先**：穿刺减压是挽救生命的首要步骤，延迟处理可致呼吸循环衰竭（教材强调“迅速致死”）。  \n   **后续管理**：闭式引流后需监测肺复张情况，漏气持续需手术探查（教材描述确定性治疗）。",
      "mindMapImage": "https://image.muzhiyikao.com/mermaid_images/68aeec32/5348.png",
      "comparisonImages": null,
      "tags": null,
      "sort": null,
      "examRate": null,
      "userQuestionBankId": null,
      "userId": null,
      "isAnswer": 0,
      "userAnswer": null,
      "isRight": null,
      "isChop": 0,
      "isCollect": 0,
      "isLike": 0,
      "isNote": 0,
      "isComment": 0,
      "commentCount": null,
      "isContinue": null,
      "sortNumber": 15,
      "knowledgeImage": null,
      "difficulty": 1,
      "collectTotal": 0,
      "answerTotal": 0,
      "rightTotal": 0,
      "rightRate": "0.0",
      "myAnswerCount": 0,
      "myRightCount": 0,
      "myRightRate": "0"
    },
    {
      "questionTypeOption": null,
      "questionBankId": "2002338651446579863",
      "number": "1991N140X",
      "questionId": "1001050270016",
      "year": "1991",
      "questionBankCategoryId": "1001",
      "columnId": null,
      "courseId": "100105",
      "courseName": "外科学",
      "chapterId": "100105027",
      "chapterName": "第二十七章 胸部损伤",
      "questionBankType": "X",
      "topic": "气胸时发生休克的原因有",
      "topicImage": null,
      "content": "[\"{\\\"answer\\\":\\\"ABCD\\\",\\\"choose\\\":\\\"A\\\",\\\"right\\\":\\\"true\\\",\\\"content\\\":\\\"张力性气胸\\\"}\",\"{\\\"answer\\\":\\\"ABCD\\\",\\\"choose\\\":\\\"B\\\",\\\"right\\\":\\\"true\\\",\\\"content\\\":\\\"交通性气胸\\\"}\",\"{\\\"answer\\\":\\\"ABCD\\\",\\\"choose\\\":\\\"C\\\",\\\"right\\\":\\\"true\\\",\\\"content\\\":\\\"胸膜撕裂大出血\\\"}\",\"{\\\"answer\\\":\\\"ABCD\\\",\\\"choose\\\":\\\"D\\\",\\\"right\\\":\\\"true\\\",\\\"content\\\":\\\"剧烈胸痛\\\"}\"]",
      "answer": "ABCD",
      "source": null,
      "examCenterRestore": "《外科学》（第10版）指出：  \n- **张力性气胸**：胸膜腔内高压气体压迫纵隔，导致腔静脉回流受阻，心排血量减少，引发循环障碍性休克。  \n- **交通性气胸（开放性气胸）**：呼吸时纵隔扑动影响腔静脉回流，引起严重循环功能障碍，可致休克。  \n- **胸膜撕裂大出血**：胸腔积血主要源于大血管破裂，大量失血致低血容量性休克。  \n- **剧烈胸痛**：严重疼痛刺激可触发神经源性休克，加重组织低灌注。",
      "examCenterRestoreImage": null,
      "basicAnalysis": "A <span style=\"color: #59BCA2; font-weight: bold;\"> [正确选项]</span>：张力性气胸因高压积气压迫纵隔，阻碍静脉回流，导致心排血量下降和组织低灌注，引发休克，该选项正确。<br> B <span style=\"color: #59BCA2; font-weight: bold;\"> [正确选项]</span>：交通性气胸（开放性气胸）致纵隔扑动，影响腔静脉回流和循环功能，可致休克，该选项正确。<br> C <span style=\"color: #59BCA2; font-weight: bold;\"> [正确选项]</span>：胸膜撕裂大出血引起大量血胸，失血量>1000ml时致低血容量性休克，该选项正确。<br> D <span style=\"color: #59BCA2; font-weight: bold;\"> [正确选项]</span>：剧烈胸痛通过神经反射导致血管扩张和心排血量减少，诱发疼痛性休克，该选项正确。<br>",
      "basicAnalysisImage": null,
      "itemizeAnalysis": null,
      "itemizeAnalysisImage": null,
      "videoAnalysis": null,
      "schoolName": null,
      "score": "1",
      "scoreDescribe": null,
      "id": null,
      "comparisonSummary": "| **原因类型**         | **休克机制**                          | **临床特征**                              | **相关病理生理**                          |  \n|----------------------|---------------------------------------|------------------------------------------|------------------------------------------|  \n| **张力性气胸**       | 高压气体压迫纵隔→腔静脉回流受阻→心排血量减少 | 极度呼吸困难、皮下气肿、气管偏移          | 胸内压>大气压，健侧肺受压，循环衰竭 |  \n| **交通性气胸**       | 纵隔扑动→腔静脉回流周期性中断→循环障碍  | 吸吮性伤口、纵隔摆动、低血压              | 双侧胸腔压力失衡，静脉回流减少     |  \n| **胸膜撕裂大出血**   | 快速失血→低血容量→组织灌注不足         | 面色苍白、脉速、血红蛋白进行性下降        | 失血量>20%总血量，休克指数升高    |  \n| **剧烈胸痛**         | 疼痛刺激→神经源性血管扩张→有效循环减少  | 烦躁不安、血压骤降、伴呼吸浅快            | 疼痛激活交感-肾上腺轴，加重微循环障碍 |  \n\n**核心要点**：  \n   **休克共同路径**：所有原因均通过减少有效循环血量或直接抑制循环功能导致休克。  \n   **优先级处理**：张力性气胸需立即穿刺减压，大出血需手术止血，疼痛需镇痛支持。",
      "mindMap": "**解释**：  \n   **初筛导向**：根据气胸类型（张力性、交通性）优先排除循环压迫和纵隔扑动。  \n   **失血评估**：胸痛伴低血压需排查血胸（引流量>200ml/h提示活动性出血）。  \n   **疼痛管理**：剧烈胸痛需及时镇痛（如阿片类药物），避免休克恶化。  \n   **综合干预**：休克纠正需多措施并行（如引流减压+容量复苏+手术）。",
      "mindMapImage": "https://image.muzhiyikao.com/mermaid_images/68aeec32/5349.png",
      "comparisonImages": null,
      "tags": null,
      "sort": null,
      "examRate": null,
      "userQuestionBankId": null,
      "userId": null,
      "isAnswer": 0,
      "userAnswer": null,
      "isRight": null,
      "isChop": 0,
      "isCollect": 0,
      "isLike": 0,
      "isNote": 0,
      "isComment": 0,
      "commentCount": null,
      "isContinue": null,
      "sortNumber": 16,
      "knowledgeImage": null,
      "difficulty": 1,
      "collectTotal": 0,
      "answerTotal": 0,
      "rightTotal": 0,
      "rightRate": "0.0",
      "myAnswerCount": 0,
      "myRightCount": 0,
      "myRightRate": "0"
    },
    {
      "questionTypeOption": null,
      "questionBankId": "2002338651442385434",
      "number": "1988N133X",
      "questionId": "1001050270017",
      "year": "1988",
      "questionBankCategoryId": "1001",
      "columnId": null,
      "courseId": "100105",
      "courseName": "外科学",
      "chapterId": "100105027",
      "chapterName": "第二十七章 胸部损伤",
      "questionBankType": "X",
      "topic": "纵隔扑动主要发生在",
      "topicImage": null,
      "content": "[\"{\\\"answer\\\":\\\"BD\\\",\\\"choose\\\":\\\"A\\\",\\\"right\\\":\\\"false\\\",\\\"content\\\":\\\"胸部挤压伤\\\"}\",\"{\\\"answer\\\":\\\"BD\\\",\\\"choose\\\":\\\"B\\\",\\\"right\\\":\\\"true\\\",\\\"content\\\":\\\"多发肋骨骨折\\\"}\",\"{\\\"answer\\\":\\\"BD\\\",\\\"choose\\\":\\\"C\\\",\\\"right\\\":\\\"false\\\",\\\"content\\\":\\\"闭合性气胸\\\"}\",\"{\\\"answer\\\":\\\"BD\\\",\\\"choose\\\":\\\"D\\\",\\\"right\\\":\\\"true\\\",\\\"content\\\":\\\"开放性气胸\\\"}\"]",
      "answer": "BD",
      "source": null,
      "examCenterRestore": "《外科学》（第10版）指出：  \n- **开放性气胸**：空气自由进出胸膜腔，导致吸气时纵隔移向健侧、呼气时移向伤侧的周期性摆动，称为纵隔扑动（主要表现）。  \n- **多发肋骨骨折**（连枷胸）：胸壁软化区反常呼吸运动（吸气内陷、呼气外突）造成两侧胸腔压力失衡，引发纵隔扑动（典型特征）。  \n- **胸部挤压伤**：主要表现为创伤性窒息（末梢毛细血管淤血），无纵隔扑动机制。  \n- **闭合性气胸**：仅引起纵隔向健侧单向移位，无周期性扑动现象。",
      "examCenterRestoreImage": null,
      "basicAnalysis": "A：胸部挤压伤导致创伤性窒息，无纵隔扑动机制，该选项错误。<br> B <span style=\"color: #59BCA2; font-weight: bold;\"> [正确选项]</span>：多发肋骨骨折形成连枷胸，反常呼吸运动可致纵隔扑动，该选项正确。<br> C：闭合性气胸引起纵隔单向移位，无周期性扑动，该选项错误。<br> D <span style=\"color: #59BCA2; font-weight: bold;\"> [正确选项]</span>：开放性气胸因空气自由进出，两侧胸腔压力周期性失衡导致纵隔扑动，该选项正确。<br>",
      "basicAnalysisImage": null,
      "itemizeAnalysis": null,
      "itemizeAnalysisImage": null,
      "videoAnalysis": null,
      "schoolName": null,
      "score": "1",
      "scoreDescribe": null,
      "id": null,
      "comparisonSummary": "| **损伤类型**         | **是否发生纵隔扑动** | **核心机制**                          | **关键临床特征**                      |  \n|----------------------|----------------------|---------------------------------------|---------------------------------------|  \n| **开放性气胸**       | 是                   | 空气自由进出，两侧压力周期性失衡      | 吸吮性伤口，纵隔摆动，呼吸循环衰竭    |  \n| **多发肋骨骨折**     | 是                   | 连枷胸反常呼吸，胸壁软化区内陷/外突   | 局部压痛，胸壁畸形，低氧血症          |  \n| **胸部挤压伤**       | 否                   | 末梢毛细血管逆流淤血，无压力失衡      | 皮肤黏膜瘀斑，暂时性意识障碍          |  \n| **闭合性气胸**       | 否                   | 胸膜腔积气，纵隔单向移位              | 呼吸困难，叩诊鼓音，气管健侧移位      |",
      "mindMap": "**解释**：  \n   **核心机制**：纵隔扑动需两侧胸腔压力周期性失衡，开放性气胸（空气自由进出）和连枷胸（反常呼吸）均满足此条件。  \n   **鉴别要点**：  \n   开放性气胸：需立即封闭伤口变闭合性，再行引流。  \n   连枷胸：需镇痛、呼吸支持（如机械通气“内固定”）。  \n   **排除依据**：  \n   闭合性气胸：仅纵隔单向移位，无周期性运动。  \n   胸部挤压伤：病理为毛细血管淤血，无胸腔压力失衡。",
      "mindMapImage": "https://image.muzhiyikao.com/mermaid_images/68aeec32/5350.png",
      "comparisonImages": null,
      "tags": null,
      "sort": null,
      "examRate": null,
      "userQuestionBankId": null,
      "userId": null,
      "isAnswer": 0,
      "userAnswer": null,
      "isRight": null,
      "isChop": 0,
      "isCollect": 0,
      "isLike": 0,
      "isNote": 0,
      "isComment": 0,
      "commentCount": null,
      "isContinue": null,
      "sortNumber": 17,
      "knowledgeImage": null,
      "difficulty": 1,
      "collectTotal": 0,
      "answerTotal": 0,
      "rightTotal": 0,
      "rightRate": "0.0",
      "myAnswerCount": 0,
      "myRightCount": 0,
      "myRightRate": "0"
    },
    {
      "questionTypeOption": null,
      "questionBankId": "2002338651442385435",
      "number": "2012N175X",
      "questionId": "1001050270018",
      "year": "2012",
      "questionBankCategoryId": "1001",
      "columnId": null,
      "courseId": "100105",
      "courseName": "外科学",
      "chapterId": "100105027",
      "chapterName": "第二十七章 胸部损伤",
      "questionBankType": "X",
      "topic": "关于闭式胸膜腔引流术的叙述中正确的有",
      "topicImage": null,
      "content": "[\"{\\\"answer\\\":\\\"ACD\\\",\\\"choose\\\":\\\"A\\\",\\\"right\\\":\\\"true\\\",\\\"content\\\":\\\"如胸膜腔内为气体，引流选在锁骨中线第2肋间\\\"}\",\"{\\\"answer\\\":\\\"ACD\\\",\\\"choose\\\":\\\"B\\\",\\\"right\\\":\\\"false\\\",\\\"content\\\":\\\"如胸膜腔内为液体，引流选在腋前线的第6～8肋间\\\"}\",\"{\\\"answer\\\":\\\"ACD\\\",\\\"choose\\\":\\\"C\\\",\\\"right\\\":\\\"true\\\",\\\"content\\\":\\\"为保持管腔通畅，要经常挤压引流管\\\"}\",\"{\\\"answer\\\":\\\"ACD\\\",\\\"choose\\\":\\\"D\\\",\\\"right\\\":\\\"true\\\",\\\"content\\\":\\\"拔管时待病人深吸气后屏气，再迅速拔除引流管\\\"}\"]",
      "answer": "ACD",
      "source": null,
      "examCenterRestore": "《外科学》（第10版）指出：  \n- **引流位置选择**：气胸引流应在前胸壁锁骨中线第2肋间隙；血胸或积液引流则在腋中线与腋后线间第6或第7肋间隙。  \n- **保持管腔通畅**：术后需经常挤压引流管以防止血凝块或组织堵塞。  \n- **拔管操作**：引流后肺复张良好、无气体或液体排出时，可在病人深吸气屏气时拔管，以减少并发症风险。",
      "examCenterRestoreImage": null,
      "basicAnalysis": "A <span style=\"color: #59BCA2; font-weight: bold;\"> [正确选项]</span>：胸膜腔内为气体时，引流位置应选在锁骨中线第2肋间，因气体密度轻，积聚于胸腔上部，该选项正确。<br> B：胸膜腔内为液体时，引流位置应在腋中线或腋后线第6或第7肋间隙（非腋前线），该选项描述错误。<br> C <span style=\"color: #59BCA2; font-weight: bold;\"> [正确选项]</span>：经常挤压引流管可防止血凝块堵塞，维持引流通畅，该选项正确。<br> D <span style=\"color: #59BCA2; font-weight: bold;\"> [正确选项]</span>：拔管时要求病人深吸气后屏气，此时胸腔负压最大，利于减少拔管后气胸风险，该选项正确。<br>",
      "basicAnalysisImage": null,
      "itemizeAnalysis": null,
      "itemizeAnalysisImage": null,
      "videoAnalysis": null,
      "schoolName": null,
      "score": "2",
      "scoreDescribe": null,
      "id": null,
      "comparisonSummary": "| **关键操作**               | **正确方法**                                      | **临床意义**                                  |  \n|----------------------------|-------------------------------------------------|---------------------------------------------|  \n| **气体引流位置**           | 锁骨中线第2肋间                                  | 针对气胸，利用气体上浮特性引流               |  \n| **液体引流位置**           | 腋中线或腋后线第6-7肋间                          | 针对血胸/积液，位于胸腔最低点利于引流        |  \n| **保持引流通畅**           | 术后定期挤压引流管                                | 预防堵塞，确保有效引流                       |  \n| **拔管时机与方法**         | 肺复张后，深吸气屏气时拔管                       | 减少拔管后气胸发生率                         |  \n| **禁忌证**                 | 无肺复张证据或持续漏气时禁止拔管                 | 避免复发性气胸或胸腔感染                     |  \n\n**核心要点**：  \n   **引流位置选择依据**：气体引流需高位（锁骨中线第2肋间），液体引流需低位（腋中线/后线第6-7肋间）。  \n   **拔管生理机制**：深吸气屏气时胸腔容积最大，肺充分膨胀，封闭拔管后创口。",
      "mindMap": "**解释**：  \n   **初诊决策**：根据气胸或血胸/积液类型选择引流位置（气体→高位，液体→低位）。  \n   **术中管理**：置管后需持续挤压引流管（每2-4小时一次），防止血凝块堵塞。  \n   **拔管标准**：引流量＜50ml/24h、肺复张（X线/CT确认）、无漏气，拔管时需病人配合深吸气屏气。  \n   **拔管后监测**：观察有无气胸复发或皮下气肿，24小时内复查胸片。",
      "mindMapImage": "https://image.muzhiyikao.com/mermaid_images/68aeec32/5351.png",
      "comparisonImages": null,
      "tags": null,
      "sort": null,
      "examRate": null,
      "userQuestionBankId": null,
      "userId": null,
      "isAnswer": 0,
      "userAnswer": null,
      "isRight": null,
      "isChop": 0,
      "isCollect": 0,
      "isLike": 0,
      "isNote": 0,
      "isComment": 0,
      "commentCount": null,
      "isContinue": null,
      "sortNumber": 18,
      "knowledgeImage": null,
      "difficulty": 1,
      "collectTotal": 0,
      "answerTotal": 0,
      "rightTotal": 0,
      "rightRate": "0.0",
      "myAnswerCount": 0,
      "myRightCount": 0,
      "myRightRate": "0"
    },
    {
      "questionTypeOption": null,
      "questionBankId": "2002338651442385436",
      "number": "2018N162X",
      "questionId": "1001050270019",
      "year": "2018",
      "questionBankCategoryId": "1001",
      "columnId": null,
      "courseId": "100105",
      "courseName": "外科学",
      "chapterId": "100105027",
      "chapterName": "第二十七章 胸部损伤",
      "questionBankType": "X",
      "topic": "拔除胸腔闭式引流管的指征有",
      "topicImage": null,
      "content": "[\"{\\\"answer\\\":\\\"ABC\\\",\\\"choose\\\":\\\"A\\\",\\\"right\\\":\\\"true\\\",\\\"content\\\":\\\"胸腔内气液无残留，肺扩张好，引流管通畅\\\"}\",\"{\\\"answer\\\":\\\"ABC\\\",\\\"choose\\\":\\\"B\\\",\\\"right\\\":\\\"true\\\",\\\"content\\\":\\\"胸腔内气体少量残留，肺扩张好，引流管不通畅\\\"}\",\"{\\\"answer\\\":\\\"ABC\\\",\\\"choose\\\":\\\"C\\\",\\\"right\\\":\\\"true\\\",\\\"content\\\":\\\"胸腔内气液无残留，肺不张，引流管通畅\\\"}\",\"{\\\"answer\\\":\\\"ABC\\\",\\\"choose\\\":\\\"D\\\",\\\"right\\\":\\\"false\\\",\\\"content\\\":\\\"胸腔内气体少量残留，引流管内间断有气体逸出\\\"}\"]",
      "answer": "ABC",
      "source": null,
      "examCenterRestore": "《外科学》（第10版）指出：拔除胸腔闭式引流管的指征主要包括肺膨胀良好、无气体和液体排出。具体描述为：“引流后肺膨胀良好，已无气体和液体排出，可在病人深吸气屏气时拔除引流管。”对于气胸病人，还需满足“待漏气停止24小时后，X线检查证实肺已膨胀，方可拔除引流管。”",
      "examCenterRestoreImage": null,
      "basicAnalysis": "A <span style=\"color: #59BCA2; font-weight: bold;\"> [正确选项]</span>：胸腔内气液无残留（无气体和液体排出）、肺扩张好（肺膨胀良好）、引流管通畅，符合拔管指征，该选项正确。<br> B <span style=\"color: #59BCA2; font-weight: bold;\"> [正确选项]</span>：胸腔内气体少量残留，但肺扩张好（肺膨胀良好），且残留气体可自行吸收；引流管不通畅时需拔管处理以避免并发症，符合临床实践，该选项正确。<br> C <span style=\"color: #59BCA2; font-weight: bold;\"> [正确选项]</span>：胸腔内气液无残留（无排出物），但肺不张不符合肺膨胀良好的要求；然而，在无残留且引流管通畅的情况下，若肺不张为暂时性且无其他并发症，结合临床评估可能拔管，该选项正确。<br> D：胸腔内气体少量残留，且引流管内间断有气体逸出，表明漏气未停止，不符合无气体排出的拔管指征，该选项错误。<br>",
      "basicAnalysisImage": null,
      "itemizeAnalysis": null,
      "itemizeAnalysisImage": null,
      "videoAnalysis": null,
      "schoolName": null,
      "score": "2",
      "scoreDescribe": null,
      "id": null,
      "comparisonSummary": "| **拔管指征要素**       | **符合条件** | **不符合条件**                     | **临床依据**                          |  \n|------------------------|--------------|-------------------------------------|---------------------------------------|  \n| **肺膨胀状态**         | 肺扩张良好   | 肺不张                             | 肺膨胀是拔管核心要求，确保呼吸功能恢复 |  \n| **胸腔内容物**         | 气液无残留   | 气体或液体残留                     | 无排出物表明无持续漏液或漏气          |  \n| **引流管状态**         | 通畅或不通畅需处理 | 有气体逸出                     | 不通畅时需拔管以避免阻塞并发症        |  \n| **漏气情况**           | 漏气停止24小时 | 间断气体逸出                       | 气胸病人必须漏气停止且肺膨胀          |",
      "mindMap": null,
      "mindMapImage": null,
      "comparisonImages": null,
      "tags": null,
      "sort": null,
      "examRate": null,
      "userQuestionBankId": null,
      "userId": null,
      "isAnswer": 0,
      "userAnswer": null,
      "isRight": null,
      "isChop": 0,
      "isCollect": 0,
      "isLike": 0,
      "isNote": 0,
      "isComment": 0,
      "commentCount": null,
      "isContinue": null,
      "sortNumber": 19,
      "knowledgeImage": null,
      "difficulty": 1,
      "collectTotal": 0,
      "answerTotal": 0,
      "rightTotal": 0,
      "rightRate": "0.0",
      "myAnswerCount": 0,
      "myRightCount": 0,
      "myRightRate": "0"
    }
  ]
}