{
  "courseId": "100103",
  "courseName": "病理学",
  "chapterId": "100103002",
  "chapterName": "第二章 损伤的修复",
  "questionCount": 28,
  "expectedCount": 28,
  "questions": [
    {
      "questionTypeOption": null,
      "questionBankId": "2002338651450773655",
      "number": "1993N91B",
      "questionId": "1001030020001",
      "year": "1993",
      "questionBankCategoryId": "1001",
      "columnId": null,
      "courseId": "100103",
      "courseName": "病理学",
      "chapterId": "100103002",
      "chapterName": "第二章 损伤的修复",
      "questionBankType": "B",
      "topic": "创伤神经纤维瘤",
      "topicImage": null,
      "content": "[\"{\\\"answer\\\":\\\"C\\\",\\\"choose\\\":\\\"A\\\",\\\"right\\\":\\\"false\\\",\\\"content\\\":\\\"肥大\\\"}\",\"{\\\"answer\\\":\\\"C\\\",\\\"choose\\\":\\\"B\\\",\\\"right\\\":\\\"false\\\",\\\"content\\\":\\\"增生\\\"}\",\"{\\\"answer\\\":\\\"C\\\",\\\"choose\\\":\\\"C\\\",\\\"right\\\":\\\"true\\\",\\\"content\\\":\\\"再生\\\"}\",\"{\\\"answer\\\":\\\"C\\\",\\\"choose\\\":\\\"D\\\",\\\"right\\\":\\\"false\\\",\\\"content\\\":\\\"化生\\\"}\",\"{\\\"answer\\\":\\\"C\\\",\\\"choose\\\":\\\"E\\\",\\\"right\\\":\\\"false\\\",\\\"content\\\":\\\"机化\\\"}\"]",
      "answer": "C",
      "source": null,
      "examCenterRestore": "《病理学》（第10版）指出：  \n- **创伤性神经瘤**的形成机制为：神经纤维断离后，若再生轴突无法到达远端（如因距离过远或瘢痕阻隔），轴突与增生的结缔组织混杂卷曲成团，成为创伤性神经瘤。  \n- **神经再生过程**：施万细胞增生形成带，轴突以约1mm/d速度生长，最终包绕髓鞘；若再生失败则形成瘤状结构。",
      "examCenterRestoreImage": null,
      "basicAnalysis": "A：肥大指细胞体积增大（如心肌肥厚），与神经瘤形成无关（教材未提及关联）。<br>B：增生指细胞数量增多（如施万细胞增生仅为再生环节），非创伤性神经瘤的本质原因。<br>C <span style=\"color: #59BCA2; font-weight: bold;\"> [正确选项]</span>：创伤性神经瘤是神经纤维再生失败的结果（教材明确描述轴突再生受阻后形成瘤状结构）。<br>D：化生为细胞类型转换（如鳞状化生），与神经再生无关（教材未提及）。<br>E：机化指肉芽组织替代坏死物（如血栓机化），神经瘤为再生异常而非机化过程。<br>",
      "basicAnalysisImage": null,
      "itemizeAnalysis": null,
      "itemizeAnalysisImage": null,
      "videoAnalysis": null,
      "schoolName": null,
      "score": "1",
      "scoreDescribe": null,
      "id": null,
      "comparisonSummary": "| **概念**       | **定义**                                  | **与创伤性神经瘤关联**          |  \n| :------------- | :---------------------------------------- | :------------------------------ |  \n| **再生（C）**  | 损伤后细胞/组织修复原结构                | 轴突再生失败导致瘤状结构形成    |  \n| **肥大（A）**  | 细胞体积增大（无数量变化）               | 不适用（神经瘤为结构异常）      |  \n| **增生（B）**  | 细胞数量增多（如施万细胞增生）           | 仅为再生过程中的局部表现        |  \n| **化生（D）**  | 成熟细胞类型被另一种取代（如上皮化生）   | 无关联（神经组织无非同源转化）  |  \n| **机化（E）**  | 肉芽组织替代坏死物或异物                 | 不适用（神经瘤非坏死物替代）    |",
      "mindMap": null,
      "mindMapImage": "https://image.muzhiyikao.com/mermaid_images/68aeec32/2209.png",
      "comparisonImages": null,
      "tags": null,
      "sort": null,
      "examRate": null,
      "userQuestionBankId": null,
      "userId": null,
      "isAnswer": 0,
      "userAnswer": null,
      "isRight": null,
      "isChop": 0,
      "isCollect": 0,
      "isLike": 0,
      "isNote": 0,
      "isComment": 0,
      "commentCount": null,
      "isContinue": 1,
      "sortNumber": 1,
      "knowledgeImage": null,
      "difficulty": 1,
      "collectTotal": 0,
      "answerTotal": 0,
      "rightTotal": 0,
      "rightRate": "0.0",
      "myAnswerCount": 0,
      "myRightCount": 0,
      "myRightRate": "0"
    },
    {
      "questionTypeOption": null,
      "questionBankId": "2002338651450773656",
      "number": "2016N163X",
      "questionId": "1001030020002",
      "year": "2016",
      "questionBankCategoryId": "1001",
      "columnId": null,
      "courseId": "100103",
      "courseName": "病理学",
      "chapterId": "100103002",
      "chapterName": "第二章 损伤的修复",
      "questionBankType": "X",
      "topic": "发生机化时，组织中出现的特征性细胞有",
      "topicImage": null,
      "content": "[\"{\\\"answer\\\":\\\"BC\\\",\\\"choose\\\":\\\"A\\\",\\\"right\\\":\\\"false\\\",\\\"content\\\":\\\"类上皮细胞\\\"}\",\"{\\\"answer\\\":\\\"BC\\\",\\\"choose\\\":\\\"B\\\",\\\"right\\\":\\\"true\\\",\\\"content\\\":\\\"内皮细胞\\\"}\",\"{\\\"answer\\\":\\\"BC\\\",\\\"choose\\\":\\\"C\\\",\\\"right\\\":\\\"true\\\",\\\"content\\\":\\\"成纤维细胞\\\"}\",\"{\\\"answer\\\":\\\"BC\\\",\\\"choose\\\":\\\"D\\\",\\\"right\\\":\\\"false\\\",\\\"content\\\":\\\"多核巨细胞\\\"}\"]",
      "answer": "BC",
      "source": null,
      "examCenterRestore": "《病理学》（第10版）指出：  \n- **机化**是\"新生肉芽组织长入并取代坏死组织、血栓、脓液、异物等的过程\"。  \n- **肉芽组织构成**：\"由新生的毛细血管（内皮细胞增生形成）、成纤维细胞及炎性细胞（中性粒细胞、巨噬细胞等）组成\"。  \n- **鉴别要点**：类上皮细胞和多核巨细胞是肉芽肿性炎（如结核结节）的特征性细胞，而非机化过程的表现（图3-7）。",
      "examCenterRestoreImage": null,
      "basicAnalysis": "A. 类上皮细胞：是肉芽肿性炎（如结核病）的特征性细胞，由巨噬细胞转化形成，非机化过程成分，故错误。<br>B. <span style=\"color: #59BCA2; font-weight: bold;\"> [正确选项]</span>：内皮细胞是肉芽组织中新毛细血管的主要构成细胞，在机化过程中显著增生形成血管网络，该选项正确。<br>C. <span style=\"color: #59BCA2; font-weight: bold;\"> [正确选项]</span>：成纤维细胞是肉芽组织的核心细胞，负责胶原合成和组织修复，在机化中必不可少，该选项正确。<br>D. 多核巨细胞：由巨噬细胞融合形成，见于肉芽肿性炎（如异物巨细胞），非机化特征，故错误。<br>",
      "basicAnalysisImage": null,
      "itemizeAnalysis": null,
      "itemizeAnalysisImage": null,
      "videoAnalysis": null,
      "schoolName": null,
      "score": "2",
      "scoreDescribe": null,
      "id": null,
      "comparisonSummary": "| **过程**       | **特征性细胞**          | **形成机制**                          | **功能**                |  \n| :------------- | :---------------------- | :------------------------------------ | :---------------------- |  \n| **机化**       | **内皮细胞（B）**       | 毛细血管内皮增生形成新生血管          | 建立血运，输送营养      |  \n|                | **成纤维细胞（C）**     | 间叶细胞分化，合成胶原纤维            | 瘢痕组织形成，修复缺损  |  \n| **肉芽肿性炎** | 类上皮细胞（A）         | 巨噬细胞上皮样转化                    | 包裹病原体，形成结节    |  \n|                | 多核巨细胞（D）         | 巨噬细胞融合（如Langhans巨细胞）      | 吞噬大颗粒异物          |",
      "mindMap": null,
      "mindMapImage": "https://image.muzhiyikao.com/mermaid_images/68aeec32/2210.png",
      "comparisonImages": null,
      "tags": null,
      "sort": null,
      "examRate": null,
      "userQuestionBankId": null,
      "userId": null,
      "isAnswer": 0,
      "userAnswer": null,
      "isRight": null,
      "isChop": 0,
      "isCollect": 0,
      "isLike": 0,
      "isNote": 0,
      "isComment": 0,
      "commentCount": null,
      "isContinue": null,
      "sortNumber": 2,
      "knowledgeImage": null,
      "difficulty": 1,
      "collectTotal": 0,
      "answerTotal": 0,
      "rightTotal": 0,
      "rightRate": "0.0",
      "myAnswerCount": 0,
      "myRightCount": 0,
      "myRightRate": "0"
    },
    {
      "questionTypeOption": null,
      "questionBankId": "2002338651450773657",
      "number": "2019N153X",
      "questionId": "1001030020003",
      "year": "2019",
      "questionBankCategoryId": "1001",
      "columnId": null,
      "courseId": "100103",
      "courseName": "病理学",
      "chapterId": "100103002",
      "chapterName": "第二章 损伤的修复",
      "questionBankType": "X",
      "topic": "关于肉芽组织正确的描述有",
      "topicImage": null,
      "content": "[\"{\\\"answer\\\":\\\"ACD\\\",\\\"choose\\\":\\\"A\\\",\\\"right\\\":\\\"true\\\",\\\"content\\\":\\\"是不完全修复的必经之路\\\"}\",\"{\\\"answer\\\":\\\"ACD\\\",\\\"choose\\\":\\\"B\\\",\\\"right\\\":\\\"false\\\",\\\"content\\\":\\\"老化时血管和胶原纤维明显增加\\\"}\",\"{\\\"answer\\\":\\\"ACD\\\",\\\"choose\\\":\\\"C\\\",\\\"right\\\":\\\"true\\\",\\\"content\\\":\\\"有数量不等的炎症细胞\\\"}\",\"{\\\"answer\\\":\\\"ACD\\\",\\\"choose\\\":\\\"D\\\",\\\"right\\\":\\\"true\\\",\\\"content\\\":\\\"含有毛细血管和成纤维细胞\\\"}\"]",
      "answer": "ACD",
      "source": null,
      "examCenterRestore": "《病理学》（第10版）指出：  \n- **肉芽组织是纤维性修复的核心环节**，在组织损伤后通过增生填补缺损，最终转化为瘢痕组织完成不完全修复。  \n- **组成特征**：由新生毛细血管、增生的成纤维细胞及数量不等的炎症细胞（巨噬细胞、中性粒细胞等）构成。  \n- **老化过程**：随时间推移，毛细血管闭塞减少，胶原纤维增多，炎症细胞逐渐消失。",
      "examCenterRestoreImage": null,
      "basicAnalysis": "A <span style=\"color: #59BCA2; font-weight: bold;\"> [正确选项]</span>：肉芽组织是纤维性修复（不完全修复）的必经阶段，教材明确描述其通过增生填补缺损并转化为瘢痕组织。<br>B：老化时血管减少（部分闭塞），胶原纤维增加但选项错误描述\"血管明显增加\"。<br>C <span style=\"color: #59BCA2; font-weight: bold;\"> [正确选项]</span>：教材明确肉芽组织\"伴有炎症细胞浸润\"，包括巨噬细胞、中性粒细胞等。<br>D <span style=\"color: #59BCA2; font-weight: bold;\"> [正确选项]</span>：教材定义肉芽组织由\"新生毛细血管及增生的成纤维细胞构成\"。<br>",
      "basicAnalysisImage": null,
      "itemizeAnalysis": null,
      "itemizeAnalysisImage": null,
      "videoAnalysis": null,
      "schoolName": null,
      "score": "2",
      "scoreDescribe": null,
      "id": null,
      "comparisonSummary": "| **特征**               | **正确描述（ACD）**                | **错误选项（B）**                |  \n| :--------------------- | :--------------------------------- | :------------------------------- |  \n| **修复作用**           | 不完全修复必经之路（填补缺损）     | -                                |  \n| **组成成分**           | 含毛细血管+成纤维细胞+炎症细胞    | -                                |  \n| **老化变化**           | 血管↓、胶原↑、炎症细胞↓            | 错误描述\"血管明显增加\"           |  \n| **教材依据**           |                           | （与描述矛盾）          |",
      "mindMap": null,
      "mindMapImage": "https://image.muzhiyikao.com/mermaid_images/68aeec32/2211.png",
      "comparisonImages": null,
      "tags": null,
      "sort": null,
      "examRate": null,
      "userQuestionBankId": null,
      "userId": null,
      "isAnswer": 0,
      "userAnswer": null,
      "isRight": null,
      "isChop": 0,
      "isCollect": 0,
      "isLike": 0,
      "isNote": 0,
      "isComment": 0,
      "commentCount": null,
      "isContinue": null,
      "sortNumber": 3,
      "knowledgeImage": null,
      "difficulty": 1,
      "collectTotal": 0,
      "answerTotal": 0,
      "rightTotal": 0,
      "rightRate": "0.0",
      "myAnswerCount": 0,
      "myRightCount": 0,
      "myRightRate": "0"
    },
    {
      "questionTypeOption": null,
      "questionBankId": "2002338651450773658",
      "number": "2011N41A",
      "questionId": "1001030020004",
      "year": "2011",
      "questionBankCategoryId": "1001",
      "columnId": null,
      "courseId": "100103",
      "courseName": "病理学",
      "chapterId": "100103002",
      "chapterName": "第二章 损伤的修复",
      "questionBankType": "A2",
      "topic": "患者，20岁，骨折愈合良好，5年后骨折处骨组织病理变化表现为",
      "topicImage": null,
      "content": "[\"{\\\"answer\\\":\\\"C\\\",\\\"choose\\\":\\\"A\\\",\\\"right\\\":\\\"false\\\",\\\"content\\\":\\\"大量成纤维细胞\\\"}\",\"{\\\"answer\\\":\\\"C\\\",\\\"choose\\\":\\\"B\\\",\\\"right\\\":\\\"false\\\",\\\"content\\\":\\\"大量新生毛细血管\\\"}\",\"{\\\"answer\\\":\\\"C\\\",\\\"choose\\\":\\\"C\\\",\\\"right\\\":\\\"true\\\",\\\"content\\\":\\\"正常骨组织\\\"}\",\"{\\\"answer\\\":\\\"C\\\",\\\"choose\\\":\\\"D\\\",\\\"right\\\":\\\"false\\\",\\\"content\\\":\\\"大量多核巨细胞\\\"}\"]",
      "answer": "C",
      "source": null,
      "examCenterRestore": "《病理学》（第10版）指出：  \n- **骨组织再生能力**：\"骨组织再生能力强，骨折后可完全修复\" 。  \n- **愈合过程**：骨折后通过骨痂形成和改建，最终恢复\"正常骨结构\"，无持续病理成分残留 。",
      "examCenterRestoreImage": null,
      "basicAnalysis": "A：成纤维细胞是纤维性骨痂期的成分（伤后2-3周），5年后已完全吸收（教材未提及长期存在）。<br>B：新生毛细血管见于早期肉芽组织（1-2周），5年后血管网络已正常化（教材描述血管再生为短期过程）。<br>C <span style=\"color: #59BCA2; font-weight: bold;\"> [正确选项]</span>：骨再生能力强，愈合良好时完全恢复\"正常骨组织\"结构（教材明确\"骨折后可完全修复\"）。<br>D：多核巨细胞见于肉芽肿或异物反应，非骨折愈合表现（教材未提及与骨再生关联）。<br>",
      "basicAnalysisImage": null,
      "itemizeAnalysis": null,
      "itemizeAnalysisImage": null,
      "videoAnalysis": null,
      "schoolName": null,
      "score": "1.5",
      "scoreDescribe": null,
      "id": null,
      "comparisonSummary": "| **骨折愈合阶段** | **时间** | **主要病理成分** | **5年后状态** |  \n| :--------------- | :------- | :--------------- | :------------ |  \n| **血肿形成期** | 24小时内 | 血细胞、纤维蛋白 | 完全吸收 |  \n| **纤维性骨痂期** | 2-3周 | 成纤维细胞（A）、新生毛细血管（B） | 消失 |  \n| **骨性骨痂期** | 3-12周 | 骨样组织、编织骨 | 改建为板层骨 |  \n| **改建期** | 数月-数年 | 破骨/成骨细胞 | 正常骨结构（C） |  \n| **异常愈合** | - | 多核巨细胞（D）、慢性炎症细胞 | 仅见于感染或异物残留 |",
      "mindMap": null,
      "mindMapImage": "https://image.muzhiyikao.com/mermaid_images/68aeec32/2212.png",
      "comparisonImages": null,
      "tags": null,
      "sort": null,
      "examRate": null,
      "userQuestionBankId": null,
      "userId": null,
      "isAnswer": 0,
      "userAnswer": null,
      "isRight": null,
      "isChop": 0,
      "isCollect": 0,
      "isLike": 0,
      "isNote": 0,
      "isComment": 0,
      "commentCount": null,
      "isContinue": null,
      "sortNumber": 4,
      "knowledgeImage": null,
      "difficulty": 1,
      "collectTotal": 0,
      "answerTotal": 0,
      "rightTotal": 0,
      "rightRate": "0.0",
      "myAnswerCount": 0,
      "myRightCount": 0,
      "myRightRate": "0"
    },
    {
      "questionTypeOption": null,
      "questionBankId": "2002338651450773659",
      "number": "2015N41A",
      "questionId": "1001030020005",
      "year": "2015",
      "questionBankCategoryId": "1001",
      "columnId": null,
      "courseId": "100103",
      "courseName": "病理学",
      "chapterId": "100103002",
      "chapterName": "第二章 损伤的修复",
      "questionBankType": "A2",
      "topic": "男性，25岁。患急性糜烂性胃炎，经治疗痊愈后，原胃体黏膜糜烂处表现为",
      "topicImage": null,
      "content": "[\"{\\\"answer\\\":\\\"A\\\",\\\"choose\\\":\\\"A\\\",\\\"right\\\":\\\"true\\\",\\\"content\\\":\\\"正常胃黏膜\\\"}\",\"{\\\"answer\\\":\\\"A\\\",\\\"choose\\\":\\\"B\\\",\\\"right\\\":\\\"false\\\",\\\"content\\\":\\\"幽门腺化生\\\"}\",\"{\\\"answer\\\":\\\"A\\\",\\\"choose\\\":\\\"C\\\",\\\"right\\\":\\\"false\\\",\\\"content\\\":\\\"肠上皮化生\\\"}\",\"{\\\"answer\\\":\\\"A\\\",\\\"choose\\\":\\\"D\\\",\\\"right\\\":\\\"false\\\",\\\"content\\\":\\\"表面腺体增厚\\\"}\"]",
      "answer": "A",
      "source": null,
      "examCenterRestore": "《病理学》（第10版）指出：  \n- **急性糜烂性胃炎**（如急性出血性胃炎）由化学刺激（如NSAIDs、酒精）引起，病变表现为\"胃黏膜急性出血合并轻度糜烂\"，属可逆性损伤。  \n- **胃黏膜上皮再生机制**：胃黏膜上皮为不稳定细胞，再生能力极强，急性损伤后可通过细胞分裂增殖完全修复，恢复原有结构。  \n- **化生与腺体增厚**：幽门腺化生和肠上皮化生是慢性萎缩性胃炎的典型特征（\"常出现腺上皮化生\"），表面腺体增厚见于慢性肥厚性胃炎，均与急性过程无关。",
      "examCenterRestoreImage": null,
      "basicAnalysis": "A <span style=\"color: #59BCA2; font-weight: bold;\"> [正确选项]</span>：教材明确胃黏膜上皮再生能力强，急性糜烂性胃炎愈合后可通过完全再生恢复为正常结构（无化生或增厚）。<br>B：幽门腺化生是慢性萎缩性胃炎的病理标志（如\"假幽门腺化生\"），非急性损伤愈合结局。<br>C：肠上皮化生与慢性萎缩性胃炎相关（如\"肠上皮化生为常见\"），急性糜烂性胃炎无此过程。<br>D：表面腺体增厚是慢性肥厚性胃炎的特征，教材未提及急性胃炎愈合后出现腺体增厚。<br>",
      "basicAnalysisImage": null,
      "itemizeAnalysis": null,
      "itemizeAnalysisImage": null,
      "videoAnalysis": null,
      "schoolName": null,
      "score": "1.5",
      "scoreDescribe": null,
      "id": null,
      "comparisonSummary": "| **特征**               | **急性糜烂性胃炎（本题）**          | **慢性萎缩性胃炎（对比）**        |  \n| :--------------------- | :---------------------------------- | :-------------------------------- |  \n| **病因**               | 化学刺激（NSAIDs、酒精）            | 幽门螺杆菌感染/自身免疫           |  \n| **病变本质**           | 可逆性糜烂                          | 不可逆萎缩+化生                   |  \n| **愈合结局**           | 完全再生 → 正常黏膜（A正确）        | 化生（B/C错误）或纤维化           |  \n| **教材依据**           | 胃黏膜再生能力强           | \"常出现腺上皮化生\"       |",
      "mindMap": null,
      "mindMapImage": "https://image.muzhiyikao.com/mermaid_images/68aeec32/2213.png",
      "comparisonImages": null,
      "tags": null,
      "sort": null,
      "examRate": null,
      "userQuestionBankId": null,
      "userId": null,
      "isAnswer": 0,
      "userAnswer": null,
      "isRight": null,
      "isChop": 0,
      "isCollect": 0,
      "isLike": 0,
      "isNote": 0,
      "isComment": 0,
      "commentCount": null,
      "isContinue": null,
      "sortNumber": 5,
      "knowledgeImage": null,
      "difficulty": 1,
      "collectTotal": 0,
      "answerTotal": 0,
      "rightTotal": 0,
      "rightRate": "0.0",
      "myAnswerCount": 0,
      "myRightCount": 0,
      "myRightRate": "0"
    },
    {
      "questionTypeOption": null,
      "questionBankId": "2002338651450773660",
      "number": "2003N35A",
      "questionId": "1001030020006",
      "year": "2003",
      "questionBankCategoryId": "1001",
      "columnId": null,
      "courseId": "100103",
      "courseName": "病理学",
      "chapterId": "100103002",
      "chapterName": "第二章 损伤的修复",
      "questionBankType": "A1",
      "topic": "前臂断肢再植手术成功后，下列哪种愈合属于完全再生",
      "topicImage": null,
      "content": "[\"{\\\"answer\\\":\\\"C\\\",\\\"choose\\\":\\\"A\\\",\\\"right\\\":\\\"false\\\",\\\"content\\\":\\\"动脉吻合口愈合\\\"}\",\"{\\\"answer\\\":\\\"C\\\",\\\"choose\\\":\\\"B\\\",\\\"right\\\":\\\"false\\\",\\\"content\\\":\\\"皮肤伤口愈合\\\"}\",\"{\\\"answer\\\":\\\"C\\\",\\\"choose\\\":\\\"C\\\",\\\"right\\\":\\\"true\\\",\\\"content\\\":\\\"骨折愈合\\\"}\",\"{\\\"answer\\\":\\\"C\\\",\\\"choose\\\":\\\"D\\\",\\\"right\\\":\\\"false\\\",\\\"content\\\":\\\"肌肉断端愈合\\\"}\",\"{\\\"answer\\\":\\\"C\\\",\\\"choose\\\":\\\"E\\\",\\\"right\\\":\\\"false\\\",\\\"content\\\":\\\"肌腱断端愈合\\\"}\"]",
      "answer": "C",
      "source": null,
      "examCenterRestore": "《病理学》（第10版）指出：  \n- **完全再生**的定义：由损伤周围的同种细胞修复，完全恢复原组织的结构及功能。  \n- **骨组织再生**：\"骨组织再生能力强，骨折后可完全修复\"，通过骨痂形成和改建恢复正常结构。  \n- **血管修复**：大血管离断后，\"离断的肌层不易完全再生，而由结缔组织增生连接，形成瘢痕修复\"（非完全再生）。  \n- **肌肉再生**：横纹肌\"再生能力很弱\"，若肌纤维完全断开，\"靠纤维瘢痕愈合\"（非完全再生）。  \n- **皮肤再生**：被覆上皮可完全再生，但全层皮肤缺损涉及肉芽组织增生，形成瘢痕（非完全再生）。  \n- **肌腱再生**：教材未提供肌腱再生的具体描述（见纤维组织再生部分，成纤维细胞增生通常形成瘢痕）。",
      "examCenterRestoreImage": null,
      "basicAnalysis": "A. 动脉吻合口愈合：大血管修复依赖结缔组织瘢痕（肌层难再生），非完全再生。<br>B. 皮肤伤口愈合：全层缺损时肉芽组织填充，形成瘢痕，非完全再生。<br>C. <span style=\"color: #59BCA2; font-weight: bold;\"> [正确选项]</span>：骨组织再生能力强，骨折愈合可完全恢复结构和功能，属完全再生。<br>D. 肌肉断端愈合：横纹肌再生能力弱，完全断开时依赖瘢痕修复，非完全再生。<br>E. 肌腱断端愈合：教材未明确描述肌腱再生机制；纤维组织再生通常由成纤维细胞形成胶原纤维，最终瘢痕化，非完全再生。<br>",
      "basicAnalysisImage": null,
      "itemizeAnalysis": null,
      "itemizeAnalysisImage": null,
      "videoAnalysis": null,
      "schoolName": null,
      "score": "1",
      "scoreDescribe": null,
      "id": null,
      "comparisonSummary": "| **组织类型** | **再生能力** | **愈合性质** | **教材依据** |  \n| :----------- | :----------- | :----------- | :----------- |  \n| **骨组织（C）** | 强 | 完全再生（恢复原结构） | \"骨折后可完全修复\" |  \n| **血管（A）** | 弱（肌层） | 瘢痕修复 | \"肌层不易完全再生，形成瘢痕\" |  \n| **皮肤（B）** | 上皮可完全再生，全层缺损否 | 瘢痕修复（肉芽组织参与） | 全层缺损未提完全再生 |  \n| **肌肉（D）** | 极弱 | 瘢痕修复 | \"靠纤维瘢痕愈合\" |  \n| **肌腱（E）** | 未明确 | 教材未提完全再生 | 纤维再生通常瘢痕化 |",
      "mindMap": null,
      "mindMapImage": "https://image.muzhiyikao.com/mermaid_images/68aeec32/2214.png",
      "comparisonImages": null,
      "tags": null,
      "sort": null,
      "examRate": null,
      "userQuestionBankId": null,
      "userId": null,
      "isAnswer": 0,
      "userAnswer": null,
      "isRight": null,
      "isChop": 0,
      "isCollect": 0,
      "isLike": 0,
      "isNote": 0,
      "isComment": 0,
      "commentCount": null,
      "isContinue": null,
      "sortNumber": 6,
      "knowledgeImage": null,
      "difficulty": 1,
      "collectTotal": 0,
      "answerTotal": 0,
      "rightTotal": 0,
      "rightRate": "0.0",
      "myAnswerCount": 0,
      "myRightCount": 0,
      "myRightRate": "0"
    },
    {
      "questionTypeOption": null,
      "questionBankId": "2002338651450773661",
      "number": "2008N163X",
      "questionId": "1001030020007",
      "year": "2008",
      "questionBankCategoryId": "1001",
      "columnId": null,
      "courseId": "100103",
      "courseName": "病理学",
      "chapterId": "100103002",
      "chapterName": "第二章 损伤的修复",
      "questionBankType": "X",
      "topic": "人体内属于恒定细胞的有",
      "topicImage": null,
      "content": "[\"{\\\"answer\\\":\\\"AC\\\",\\\"choose\\\":\\\"A\\\",\\\"right\\\":\\\"true\\\",\\\"content\\\":\\\"神经细胞\\\"}\",\"{\\\"answer\\\":\\\"AC\\\",\\\"choose\\\":\\\"B\\\",\\\"right\\\":\\\"false\\\",\\\"content\\\":\\\"表皮细胞\\\"}\",\"{\\\"answer\\\":\\\"AC\\\",\\\"choose\\\":\\\"C\\\",\\\"right\\\":\\\"true\\\",\\\"content\\\":\\\"心肌细胞\\\"}\",\"{\\\"answer\\\":\\\"AC\\\",\\\"choose\\\":\\\"D\\\",\\\"right\\\":\\\"false\\\",\\\"content\\\":\\\"肠上皮细胞\\\"}\"]",
      "answer": "AC",
      "source": null,
      "examCenterRestore": "《病理学》（第10版）指出：  \n- **永久性细胞（恒定细胞）**：属于非分裂细胞，出生后不能分裂增生，一旦破坏则永久性缺失，包括神经细胞、骨骼肌细胞及心肌细胞。  \n- **对比分类**：  \n  - 不稳定细胞（持续分裂细胞）：如表皮细胞、肠上皮细胞，再生能力强；  \n  - 稳定细胞（静止细胞）：如肝细胞、肾小管上皮细胞，受刺激时可再生；  \n  - 永久性细胞：无再生能力。",
      "examCenterRestoreImage": null,
      "basicAnalysis": "A <span style=\"color: #59BCA2; font-weight: bold;\"> [正确选项]</span>：神经细胞（中枢及神经节细胞）属永久性细胞，无再生能力。<br>B：表皮细胞属不稳定细胞，再生能力强（基底细胞为干细胞），非恒定细胞。<br>C <span style=\"color: #59BCA2; font-weight: bold;\"> [正确选项]</span>：心肌细胞属永久性细胞，无再生能力。<br>D：肠上皮细胞属不稳定细胞（隐窝干细胞持续更新），再生能力强。<br>",
      "basicAnalysisImage": null,
      "itemizeAnalysis": null,
      "itemizeAnalysisImage": null,
      "videoAnalysis": null,
      "schoolName": null,
      "score": "2",
      "scoreDescribe": null,
      "id": null,
      "comparisonSummary": "| **细胞类型**       | **别称**          | **再生能力** | **代表细胞**                | **教材依据** |  \n| :----------------- | :---------------- | :----------- | :-------------------------- | :----------- |  \n| **永久性细胞**     | 恒定细胞/非分裂细胞 | 无再生能力   | 神经细胞（A）、心肌细胞（C） |     |  \n| **不稳定细胞**     | 持续分裂细胞      | 再生能力强   | 表皮细胞（B）、肠上皮细胞（D） |     |  \n| **稳定细胞**       | 静止细胞          | 受刺激后再生 | 肝细胞、肾小管上皮细胞      |     |",
      "mindMap": null,
      "mindMapImage": "https://image.muzhiyikao.com/mermaid_images/68aeec32/2215.png",
      "comparisonImages": null,
      "tags": null,
      "sort": null,
      "examRate": null,
      "userQuestionBankId": null,
      "userId": null,
      "isAnswer": 0,
      "userAnswer": null,
      "isRight": null,
      "isChop": 0,
      "isCollect": 0,
      "isLike": 0,
      "isNote": 0,
      "isComment": 0,
      "commentCount": null,
      "isContinue": null,
      "sortNumber": 7,
      "knowledgeImage": null,
      "difficulty": 1,
      "collectTotal": 0,
      "answerTotal": 0,
      "rightTotal": 0,
      "rightRate": "0.0",
      "myAnswerCount": 0,
      "myRightCount": 0,
      "myRightRate": "0"
    },
    {
      "questionTypeOption": null,
      "questionBankId": "2002338651450773662",
      "number": "2023N30A",
      "questionId": "1001030020008",
      "year": "2023",
      "questionBankCategoryId": "1001",
      "columnId": null,
      "courseId": "100103",
      "courseName": "病理学",
      "chapterId": "100103002",
      "chapterName": "第二章 损伤的修复",
      "questionBankType": "A1",
      "topic": "容易发生机化的病变是",
      "topicImage": null,
      "content": "[\"{\\\"answer\\\":\\\"A\\\",\\\"choose\\\":\\\"A\\\",\\\"right\\\":\\\"true\\\",\\\"content\\\":\\\"肺脓肿\\\"}\",\"{\\\"answer\\\":\\\"A\\\",\\\"choose\\\":\\\"B\\\",\\\"right\\\":\\\"false\\\",\\\"content\\\":\\\"脑梗死灶\\\"}\",\"{\\\"answer\\\":\\\"A\\\",\\\"choose\\\":\\\"C\\\",\\\"right\\\":\\\"false\\\",\\\"content\\\":\\\"Barrett食管\\\"}\",\"{\\\"answer\\\":\\\"A\\\",\\\"choose\\\":\\\"D\\\",\\\"right\\\":\\\"false\\\",\\\"content\\\":\\\"宫颈管鳞状上皮化生\\\"}\"]",
      "answer": "A",
      "source": null,
      "examCenterRestore": "《病理学》（第10版）指出：  \n- **机化**：指坏死组织、血栓、脓液或异物被肉芽组织取代并逐渐转化为纤维瘢痕的过程（P30）。  \n- **肺脓肿**：急性期以液化坏死为主，若治疗不彻底或引流不畅，脓腔壁成纤维细胞增生，肉芽组织长入脓腔并机化坏死组织，形成慢性肺脓肿（P282）。  \n- **其他病变对比**：  \n  - 脑梗死灶：液化性坏死→胶质瘢痕修复（星形胶质细胞增生），非肉芽组织机化（P30）。  \n  - Barrett食管：鳞状上皮被柱状上皮取代（化生），无坏死组织需机化（P194）。  \n  - 宫颈鳞化：腺上皮转化为鳞状上皮（化生），属适应性改变，非机化（P194）。",
      "examCenterRestoreImage": null,
      "basicAnalysis": "A<span style=\"color: #59BCA2; font-weight: bold;\"> [正确选项]</span>：肺脓肿的脓液和坏死组织可被肉芽组织取代（机化），形成慢性脓肿壁，符合机化定义。<br>B：脑梗死灶为液化性坏死，最终由胶质细胞填充形成胶质瘢痕，不经历肉芽组织机化过程。<br>C：Barrett食管是化生性改变（鳞状上皮→柱状上皮），无坏死物需机化。<br>D：宫颈鳞化是慢性炎症刺激下的化生，与机化无关。<br>",
      "basicAnalysisImage": null,
      "itemizeAnalysis": null,
      "itemizeAnalysisImage": null,
      "videoAnalysis": null,
      "schoolName": null,
      "score": "1.5",
      "scoreDescribe": null,
      "id": null,
      "comparisonSummary": "| 病变类型 | 修复机制 | 病理特征 | 与机化关系 |  \n| :------- | :------- | :------- | :--------- |  \n| **肺脓肿** | 肉芽组织机化 | 脓腔壁纤维化，肉芽组织取代坏死物 | 直接相关（典型机化） |  \n| **脑梗死灶** | 胶质瘢痕修复 | 液化坏死→胶质细胞增生→囊腔或胶质瘢痕 | 无关（非肉芽组织参与） |  \n| **Barrett食管** | 化生 | 食管下段鳞状上皮→柱状上皮 | 无关（无坏死组织） |  \n| **宫颈鳞化** | 化生 | 宫颈腺上皮→鳞状上皮 | 无关（适应性改变） |",
      "mindMap": null,
      "mindMapImage": "https://image.muzhiyikao.com/mermaid_images/68aeec32/2216.png",
      "comparisonImages": null,
      "tags": null,
      "sort": null,
      "examRate": null,
      "userQuestionBankId": null,
      "userId": null,
      "isAnswer": 0,
      "userAnswer": null,
      "isRight": null,
      "isChop": 0,
      "isCollect": 0,
      "isLike": 0,
      "isNote": 0,
      "isComment": 0,
      "commentCount": null,
      "isContinue": null,
      "sortNumber": 8,
      "knowledgeImage": null,
      "difficulty": 1,
      "collectTotal": 0,
      "answerTotal": 0,
      "rightTotal": 0,
      "rightRate": "0.0",
      "myAnswerCount": 0,
      "myRightCount": 0,
      "myRightRate": "0"
    },
    {
      "questionTypeOption": null,
      "questionBankId": "2002338651450773663",
      "number": "1990N158X",
      "questionId": "1001030020009",
      "year": "1990",
      "questionBankCategoryId": "1001",
      "columnId": null,
      "courseId": "100103",
      "courseName": "病理学",
      "chapterId": "100103002",
      "chapterName": "第二章 损伤的修复",
      "questionBankType": "X",
      "topic": "肉芽组织变为瘢痕组织所见到的变化是",
      "topicImage": null,
      "content": "[\"{\\\"answer\\\":\\\"ABCD\\\",\\\"choose\\\":\\\"A\\\",\\\"right\\\":\\\"true\\\",\\\"content\\\":\\\"胶原纤维数量增多\\\"}\",\"{\\\"answer\\\":\\\"ABCD\\\",\\\"choose\\\":\\\"B\\\",\\\"right\\\":\\\"true\\\",\\\"content\\\":\\\"组织内水分减少\\\"}\",\"{\\\"answer\\\":\\\"ABCD\\\",\\\"choose\\\":\\\"C\\\",\\\"right\\\":\\\"true\\\",\\\"content\\\":\\\"毛细血管床减少\\\"}\",\"{\\\"answer\\\":\\\"ABCD\\\",\\\"choose\\\":\\\"D\\\",\\\"right\\\":\\\"true\\\",\\\"content\\\":\\\"成纤维细胞减少\\\"}\"]",
      "answer": "ABCD",
      "source": null,
      "examCenterRestore": "《病理学》（第10版）指出：  \n- **肉芽组织成熟过程**：随时间推移（如1~2周），间质水分逐渐吸收减少，炎症细胞消失，毛细血管数目减少（部分闭塞），成纤维细胞产生更多胶原纤维且自身数量减少。  \n- **瘢痕组织形成**：最终胶原纤维显著增多并玻璃样变性，细胞和毛细血管成分更少，转化为以胶原纤维为主的瘢痕组织。",
      "examCenterRestoreImage": null,
      "basicAnalysis": "A <span style=\"color: #59BCA2; font-weight: bold;\"> [正确选项]</span>：教材明确\"胶原纤维量更多\"（图2-7），瘢痕组织以胶原纤维为主。<br>B <span style=\"color: #59BCA2; font-weight: bold;\"> [正确选项]</span>：教材描述\"间质的水分逐渐吸收减少\"，为成熟标志之一。<br>C <span style=\"color: #59BCA2; font-weight: bold;\"> [正确选项]</span>：教材指出\"毛细血管管腔闭塞、数目减少\"，瘢痕组织中血管退化。<br>D <span style=\"color: #59BCA2; font-weight: bold;\"> [正确选项]</span>：教材说明\"成纤维细胞数目逐渐减少\"，最终变为纤维细胞。<br>",
      "basicAnalysisImage": null,
      "itemizeAnalysis": null,
      "itemizeAnalysisImage": null,
      "videoAnalysis": null,
      "schoolName": null,
      "score": "1",
      "scoreDescribe": null,
      "id": null,
      "comparisonSummary": "| **变化特征**         | **肉芽组织（初始）**                | **瘢痕组织（成熟）**              | **教材依据** |  \n| :------------------- | :---------------------------------- | :-------------------------------- | :----------- |  \n| **胶原纤维**         | 少量，逐渐增多                      | 大量积聚，玻璃样变性（A正确）     |     |  \n| **水分含量**         | 富含水分                            | 显著减少（B正确）                 |     |  \n| **毛细血管**         | 丰富，新生网络                      | 数目减少，部分闭塞（C正确）       |     |  \n| **成纤维细胞**       | 大量增殖                            | 数量减少，转化为纤维细胞（D正确） |     |  \n| **炎症细胞**         | 大量浸润（巨噬细胞、中性粒细胞）    | 完全消失                          |     |",
      "mindMap": null,
      "mindMapImage": "https://image.muzhiyikao.com/mermaid_images/68aeec32/2217.png",
      "comparisonImages": null,
      "tags": null,
      "sort": null,
      "examRate": null,
      "userQuestionBankId": null,
      "userId": null,
      "isAnswer": 0,
      "userAnswer": null,
      "isRight": null,
      "isChop": 0,
      "isCollect": 0,
      "isLike": 0,
      "isNote": 0,
      "isComment": 0,
      "commentCount": null,
      "isContinue": null,
      "sortNumber": 9,
      "knowledgeImage": null,
      "difficulty": 1,
      "collectTotal": 0,
      "answerTotal": 0,
      "rightTotal": 0,
      "rightRate": "0.0",
      "myAnswerCount": 0,
      "myRightCount": 0,
      "myRightRate": "0"
    },
    {
      "questionTypeOption": null,
      "questionBankId": "2002338651450773664",
      "number": "1996N148X",
      "questionId": "1001030020010",
      "year": "1996",
      "questionBankCategoryId": "1001",
      "columnId": null,
      "courseId": "100103",
      "courseName": "病理学",
      "chapterId": "100103002",
      "chapterName": "第二章 损伤的修复",
      "questionBankType": "X",
      "topic": "肉芽组织具有如下功能",
      "topicImage": null,
      "content": "[\"{\\\"answer\\\":\\\"ABD\\\",\\\"choose\\\":\\\"A\\\",\\\"right\\\":\\\"true\\\",\\\"content\\\":\\\"机化\\\"}\",\"{\\\"answer\\\":\\\"ABD\\\",\\\"choose\\\":\\\"B\\\",\\\"right\\\":\\\"true\\\",\\\"content\\\":\\\"修复\\\"}\",\"{\\\"answer\\\":\\\"ABD\\\",\\\"choose\\\":\\\"C\\\",\\\"right\\\":\\\"false\\\",\\\"content\\\":\\\"吞噬搬运\\\"}\",\"{\\\"answer\\\":\\\"ABD\\\",\\\"choose\\\":\\\"D\\\",\\\"right\\\":\\\"true\\\",\\\"content\\\":\\\"抗感染\\\"}\"]",
      "answer": "ABD",
      "source": null,
      "examCenterRestore": "《病理学》（第10版）指出：  \n- **核心功能**：肉芽组织在组织损伤修复过程中具有以下作用：  \n  ① **抗感染保护创面**（对应D）；  \n  ② **填补创口及其他组织缺损**（修复功能，对应B）；  \n  ③ **机化或包裹坏死、血栓、炎性渗出物及其他异物**（对应A）。  \n- **吞噬搬运机制**：肉芽组织中\"巨噬细胞及中性粒细胞吞噬细菌及组织碎片，这些细胞破坏后释放蛋白水解酶分解坏死物质\"（对应C）。",
      "examCenterRestoreImage": null,
      "basicAnalysis": "A<span style=\"color: #59BCA2; font-weight: bold;\"> [正确选项]</span>：教材明确肉芽组织可\"机化坏死、血栓等异物\"。<br>B <span style=\"color: #59BCA2; font-weight: bold;\"> [正确选项]</span>：填补创口功能即修复组织缺损。<br>C ：炎症细胞（巨噬细胞、中性粒细胞）只有吞噬功能，没有搬运功能。<br>D <span style=\"color: #59BCA2; font-weight: bold;\"> [正确选项]</span>：直接列为\"抗感染保护创面\"的核心作用。<br>",
      "basicAnalysisImage": null,
      "itemizeAnalysis": null,
      "itemizeAnalysisImage": null,
      "videoAnalysis": null,
      "schoolName": null,
      "score": "1",
      "scoreDescribe": null,
      "id": null,
      "comparisonSummary": "| **功能**         | **作用机制**                                                                 | **教材依据**                     |  \n| :--------------- | :--------------------------------------------------------------------------- | :------------------------------- |  \n| **机化（A）**    | 肉芽组织取代坏死物/异物（如血栓、脓液）                                      | \"机化或包裹坏死、血栓等异物\"    |  \n| **修复（B）**    | 填补组织缺损，通过成纤维细胞增殖和胶原沉积                                   | \"填补创口及其他组织缺损\"        |  \n| **吞噬不搬运（C）**| 巨噬细胞、中性粒细胞吞噬细菌及碎片，释放蛋白酶分解坏死组织                   | \"吞噬细菌及组织碎片\"            |  \n| **抗感染（D）**  | 炎症细胞清除病原体，形成物理屏障                                             | \"抗感染保护创面\"                |",
      "mindMap": null,
      "mindMapImage": "https://image.muzhiyikao.com/mermaid_images/68aeec32/2218.png",
      "comparisonImages": null,
      "tags": null,
      "sort": null,
      "examRate": null,
      "userQuestionBankId": null,
      "userId": null,
      "isAnswer": 0,
      "userAnswer": null,
      "isRight": null,
      "isChop": 0,
      "isCollect": 0,
      "isLike": 0,
      "isNote": 0,
      "isComment": 0,
      "commentCount": null,
      "isContinue": null,
      "sortNumber": 10,
      "knowledgeImage": null,
      "difficulty": 1,
      "collectTotal": 0,
      "answerTotal": 0,
      "rightTotal": 0,
      "rightRate": "0.0",
      "myAnswerCount": 0,
      "myRightCount": 0,
      "myRightRate": "0"
    },
    {
      "questionTypeOption": null,
      "questionBankId": "2002338651450773665",
      "number": "1989N155X",
      "questionId": "1001030020011",
      "year": "1989",
      "questionBankCategoryId": "1001",
      "columnId": null,
      "courseId": "100103",
      "courseName": "病理学",
      "chapterId": "100103002",
      "chapterName": "第二章 损伤的修复",
      "questionBankType": "X",
      "topic": "肉芽组织中包括下列哪些成分",
      "topicImage": null,
      "content": "[\"{\\\"answer\\\":\\\"ABC\\\",\\\"choose\\\":\\\"A\\\",\\\"right\\\":\\\"true\\\",\\\"content\\\":\\\"纤维母细胞\\\"}\",\"{\\\"answer\\\":\\\"ABC\\\",\\\"choose\\\":\\\"B\\\",\\\"right\\\":\\\"true\\\",\\\"content\\\":\\\"肌纤维母细胞\\\"}\",\"{\\\"answer\\\":\\\"ABC\\\",\\\"choose\\\":\\\"C\\\",\\\"right\\\":\\\"true\\\",\\\"content\\\":\\\"血管内皮细胞\\\"}\",\"{\\\"answer\\\":\\\"ABC\\\",\\\"choose\\\":\\\"D\\\",\\\"right\\\":\\\"false\\\",\\\"content\\\":\\\"表皮细胞\\\"}\"]",
      "answer": "ABC",
      "source": null,
      "examCenterRestore": "《病理学》（第10版）指出：肉芽组织由新生的毛细血管、增生的成纤维细胞（纤维母细胞）及炎性细胞构成。其中：  \n1. **纤维母细胞（A）**：主要合成胶原纤维，参与组织修复。  \n2. **肌纤维母细胞（B）**：兼具成纤维细胞和平滑肌细胞特性，含肌细丝，促进伤口收缩。  \n3. **血管内皮细胞（C）**：形成新生毛细血管，提供营养和氧。  \n4. **表皮细胞（D）**：属上皮组织成分，存在于皮肤表层，不参与肉芽组织构成。",
      "examCenterRestoreImage": null,
      "basicAnalysis": "A <span style=\"color: #59BCA2; font-weight: bold;\"> [正确选项]</span>：纤维母细胞是肉芽组织的核心成分，负责合成胶原纤维，填补缺损。<br>B <span style=\"color: #59BCA2; font-weight: bold;\"> [正确选项]</span>：肌纤维母细胞具有收缩功能，加速创面愈合，是肉芽组织中的特殊细胞类型。<br>C <span style=\"color: #59BCA2; font-weight: bold;\"> [正确选项]</span>：血管内皮细胞增殖形成毛细血管网，为修复提供代谢支持。<br>D：表皮细胞位于皮肤表层，参与上皮再生，不属于深层肉芽组织的组成成分。<br>",
      "basicAnalysisImage": null,
      "itemizeAnalysis": null,
      "itemizeAnalysisImage": null,
      "videoAnalysis": null,
      "schoolName": null,
      "score": "1",
      "scoreDescribe": null,
      "id": null,
      "comparisonSummary": "| 成分 | 功能 | 存在位置 | 特征 |  \n| :--- | :--- | :--- | :--- |  \n| **纤维母细胞** | 合成胶原纤维，修复组织缺损 | 肉芽组织主体 | 核大、卵圆形，胞质丰富 |  \n| **肌纤维母细胞** | 收缩创口，促进愈合 | 肉芽组织（尤伤口边缘） | 含肌动蛋白丝，兼具收缩与合成功能 |  \n| **血管内皮细胞** | 形成毛细血管，运输营养 | 新生血管网 | 增殖活跃，管腔不成熟 |  \n| **炎细胞** | 清除坏死组织，抗感染 | 弥漫分布 | 巨噬细胞、中性粒细胞等 |  \n| **表皮细胞** | 覆盖创面，屏障作用 | 皮肤表层 | 不参与肉芽组织构成 |",
      "mindMap": null,
      "mindMapImage": "https://image.muzhiyikao.com/mermaid_images/68aeec32/2219.png",
      "comparisonImages": null,
      "tags": null,
      "sort": null,
      "examRate": null,
      "userQuestionBankId": null,
      "userId": null,
      "isAnswer": 0,
      "userAnswer": null,
      "isRight": null,
      "isChop": 0,
      "isCollect": 0,
      "isLike": 0,
      "isNote": 0,
      "isComment": 0,
      "commentCount": null,
      "isContinue": null,
      "sortNumber": 11,
      "knowledgeImage": null,
      "difficulty": 1,
      "collectTotal": 0,
      "answerTotal": 0,
      "rightTotal": 0,
      "rightRate": "0.0",
      "myAnswerCount": 0,
      "myRightCount": 0,
      "myRightRate": "0"
    },
    {
      "questionTypeOption": null,
      "questionBankId": "2002338651450773666",
      "number": "2009N164X",
      "questionId": "1001030020012",
      "year": "2009",
      "questionBankCategoryId": "1001",
      "columnId": null,
      "courseId": "100103",
      "courseName": "病理学",
      "chapterId": "100103002",
      "chapterName": "第二章 损伤的修复",
      "questionBankType": "X",
      "topic": "肉芽组织中常见的细胞有",
      "topicImage": null,
      "content": "[\"{\\\"answer\\\":\\\"BCD\\\",\\\"choose\\\":\\\"A\\\",\\\"right\\\":\\\"false\\\",\\\"content\\\":\\\"郎罕氏巨细胞\\\"}\",\"{\\\"answer\\\":\\\"BCD\\\",\\\"choose\\\":\\\"B\\\",\\\"right\\\":\\\"true\\\",\\\"content\\\":\\\"成纤维细胞\\\"}\",\"{\\\"answer\\\":\\\"BCD\\\",\\\"choose\\\":\\\"C\\\",\\\"right\\\":\\\"true\\\",\\\"content\\\":\\\"新生内皮细胞\\\"}\",\"{\\\"answer\\\":\\\"BCD\\\",\\\"choose\\\":\\\"D\\\",\\\"right\\\":\\\"true\\\",\\\"content\\\":\\\"浆细胞\\\"}\"]",
      "answer": "BCD",
      "source": null,
      "examCenterRestore": "《病理学》（第10版）指出：肉芽组织由新生薄壁的毛细血管以及增生的成纤维细胞构成，并伴有炎症细胞浸润，炎症细胞中常以巨噬细胞为主，也有多少不等的中性粒细胞及淋巴细胞 。",
      "examCenterRestoreImage": null,
      "basicAnalysis": "A. 郎罕氏巨细胞：教材中未提及此细胞类型，且其为肉芽肿（如结核结节）的特征性细胞，非肉芽组织常见成分 。<br>B. <span style=\"color: #59BCA2; font-weight: bold;\"> [正确选项]</span>：成纤维细胞是肉芽组织的核心成分，负责胶原纤维合成和基质产生，教材明确描述为\"增生的成纤维细胞\" 。<br>C. <span style=\"color: #59BCA2; font-weight: bold;\"> [正确选项]</span>：新生内皮细胞通过毛细血管增生参与肉芽组织形成，教材指出\"由内皮细胞增生形成的实性细胞索及扩张的毛细血管\" 。<br>D. <span style=\"color: #59BCA2; font-weight: bold;\"> [正确选项]</span>：浆细胞属于淋巴细胞分化形式，教材提到炎症细胞包括\"淋巴细胞\"，在慢性炎症背景下可涵盖浆细胞 。<br>",
      "basicAnalysisImage": null,
      "itemizeAnalysis": null,
      "itemizeAnalysisImage": null,
      "videoAnalysis": null,
      "schoolName": null,
      "score": "2",
      "scoreDescribe": null,
      "id": null,
      "comparisonSummary": "| **细胞类型**       | **在肉芽组织中的角色** | **教材依据** |  \n| :----------------- | :--------------------- | :----------- |  \n| **成纤维细胞（B）** | 主要细胞，合成胶原纤维和基质 | \"增生的成纤维细胞\"  |  \n| **新生内皮细胞（C）** | 形成新生毛细血管网络 | \"内皮细胞增生形成的实性细胞索\"  |  \n| **浆细胞（D）**     | 炎症细胞成分（淋巴细胞亚型） | \"炎症细胞包括淋巴细胞\"  |  \n| **郎罕氏巨细胞（A）** | 非肉芽组织成分，见于肉芽肿 | 教材未提及 |  \n| **巨噬细胞/中性粒细胞** | 常见炎症细胞 | \"以巨噬细胞为主，中性粒细胞及淋巴细胞\"  |",
      "mindMap": null,
      "mindMapImage": "https://image.muzhiyikao.com/mermaid_images/68aeec32/2220.png",
      "comparisonImages": null,
      "tags": null,
      "sort": null,
      "examRate": null,
      "userQuestionBankId": null,
      "userId": null,
      "isAnswer": 0,
      "userAnswer": null,
      "isRight": null,
      "isChop": 0,
      "isCollect": 0,
      "isLike": 0,
      "isNote": 0,
      "isComment": 0,
      "commentCount": null,
      "isContinue": null,
      "sortNumber": 12,
      "knowledgeImage": null,
      "difficulty": 1,
      "collectTotal": 0,
      "answerTotal": 0,
      "rightTotal": 0,
      "rightRate": "0.0",
      "myAnswerCount": 0,
      "myRightCount": 0,
      "myRightRate": "0"
    },
    {
      "questionTypeOption": null,
      "questionBankId": "2002338651450773667",
      "number": "2009N133B",
      "questionId": "1001030020013",
      "year": "2009",
      "questionBankCategoryId": "1001",
      "columnId": null,
      "courseId": "100103",
      "courseName": "病理学",
      "chapterId": "100103002",
      "chapterName": "第二章 损伤的修复",
      "questionBankType": "B",
      "topic": "属于不稳定细胞的是",
      "topicImage": null,
      "content": "[\"{\\\"answer\\\":\\\"A\\\",\\\"choose\\\":\\\"A\\\",\\\"right\\\":\\\"true\\\",\\\"content\\\":\\\"小肠黏膜被覆上皮细胞\\\"}\",\"{\\\"answer\\\":\\\"A\\\",\\\"choose\\\":\\\"B\\\",\\\"right\\\":\\\"false\\\",\\\"content\\\":\\\"肝细胞\\\"}\",\"{\\\"answer\\\":\\\"A\\\",\\\"choose\\\":\\\"C\\\",\\\"right\\\":\\\"false\\\",\\\"content\\\":\\\"神经细胞\\\"}\",\"{\\\"answer\\\":\\\"A\\\",\\\"choose\\\":\\\"D\\\",\\\"right\\\":\\\"false\\\",\\\"content\\\":\\\"心肌细胞\\\"}\"]",
      "answer": "A",
      "source": null,
      "examCenterRestore": "《病理学》（第10版）指出：  \n- **不稳定细胞（持续分裂细胞）**：再生能力最强，生理状态下持续分裂更新，损伤后可快速再生修复，代表细胞包括表皮细胞、呼吸道/消化道黏膜被覆上皮细胞（如小肠黏膜上皮）。  \n- **对比分类**：  \n  - 稳定细胞（静止细胞）：如肝细胞、肾小管上皮细胞，生理状态下增殖慢，损伤后再生能力强；  \n  - 永久性细胞（恒定细胞）：如神经细胞、心肌细胞、骨骼肌细胞，无再生能力。",
      "examCenterRestoreImage": null,
      "basicAnalysis": "A<span style=\"color: #59BCA2; font-weight: bold;\"> [正确选项]</span>：小肠黏膜被覆上皮细胞（隐窝干细胞持续分裂更新）属不稳定细胞，再生能力极强。<br>B：肝细胞属稳定细胞，生理状态下极少分裂，但肝损伤后可显著再生（如肝部分切除后）。<br>C：神经细胞（神经元）属永久性细胞，无再生能力，损伤后由胶质细胞修复。<br>D：心肌细胞属永久性细胞，无再生能力，损伤后由纤维瘢痕替代。<br>",
      "basicAnalysisImage": null,
      "itemizeAnalysis": null,
      "itemizeAnalysisImage": null,
      "videoAnalysis": null,
      "schoolName": null,
      "score": "1.5",
      "scoreDescribe": null,
      "id": null,
      "comparisonSummary": "| **细胞类型**       | **再生能力**       | **代表细胞**                     | **损伤后修复方式**         |  \n| :----------------- | :----------------- | :------------------------------- | :------------------------- |  \n| **不稳定细胞**     | 极强（持续更新）   | 小肠黏膜上皮（A）、表皮细胞      | 原位再生，恢复原有结构     |  \n| **稳定细胞**       | 较强（受刺激后）   | 肝细胞（B）、肾小管上皮细胞      | 再生修复，可恢复功能       |  \n| **永久性细胞**     | 无再生能力         | 神经细胞（C）、心肌细胞（D）     | 瘢痕修复（胶质/纤维组织）  |",
      "mindMap": null,
      "mindMapImage": "https://image.muzhiyikao.com/mermaid_images/68aeec32/2221.png",
      "comparisonImages": null,
      "tags": null,
      "sort": null,
      "examRate": null,
      "userQuestionBankId": null,
      "userId": null,
      "isAnswer": 0,
      "userAnswer": null,
      "isRight": null,
      "isChop": 0,
      "isCollect": 0,
      "isLike": 0,
      "isNote": 0,
      "isComment": 0,
      "commentCount": null,
      "isContinue": null,
      "sortNumber": 13,
      "knowledgeImage": null,
      "difficulty": 1,
      "collectTotal": 0,
      "answerTotal": 0,
      "rightTotal": 0,
      "rightRate": "0.0",
      "myAnswerCount": 0,
      "myRightCount": 0,
      "myRightRate": "0"
    },
    {
      "questionTypeOption": null,
      "questionBankId": "2002338651450773668",
      "number": "2009N134B",
      "questionId": "1001030020014",
      "year": "2009",
      "questionBankCategoryId": "1001",
      "columnId": null,
      "courseId": "100103",
      "courseName": "病理学",
      "chapterId": "100103002",
      "chapterName": "第二章 损伤的修复",
      "questionBankType": "B",
      "topic": "属于稳定细胞的是",
      "topicImage": null,
      "content": "[\"{\\\"answer\\\":\\\"B\\\",\\\"choose\\\":\\\"A\\\",\\\"right\\\":\\\"false\\\",\\\"content\\\":\\\"小肠黏膜被覆上皮细胞\\\"}\",\"{\\\"answer\\\":\\\"B\\\",\\\"choose\\\":\\\"B\\\",\\\"right\\\":\\\"true\\\",\\\"content\\\":\\\"肝细胞\\\"}\",\"{\\\"answer\\\":\\\"B\\\",\\\"choose\\\":\\\"C\\\",\\\"right\\\":\\\"false\\\",\\\"content\\\":\\\"神经细胞\\\"}\",\"{\\\"answer\\\":\\\"B\\\",\\\"choose\\\":\\\"D\\\",\\\"right\\\":\\\"false\\\",\\\"content\\\":\\\"心肌细胞\\\"}\"]",
      "answer": "B",
      "source": null,
      "examCenterRestore": "《病理学》（第10版）指出：  \n- **稳定细胞**：在生理状态下增殖不明显，但受损伤刺激时表现出较强再生能力，如肝细胞、肾小管上皮细胞、成纤维细胞等。  \n- **不稳定细胞**：持续分裂以替代衰亡细胞，再生能力强，如皮肤表皮细胞、呼吸道和消化道被覆上皮（小肠黏膜上皮属此类）。  \n- **永久性细胞**：无再生能力，损伤后由瘢痕修复，如神经细胞、心肌细胞、骨骼肌细胞。",
      "examCenterRestoreImage": null,
      "basicAnalysis": "A：小肠黏膜被覆上皮细胞属不稳定细胞（持续分裂更新），不符合稳定细胞定义。<br>B <span style=\"color: #59BCA2; font-weight: bold;\"> [正确选项]</span>：肝细胞在生理状态下静息，但肝损伤后可显著再生（如肝部分切除后增生），属典型稳定细胞。<br>C：神经细胞无再生能力，属永久性细胞。<br>D：心肌细胞无再生能力，损伤后由纤维瘢痕替代，属永久性细胞。<br>",
      "basicAnalysisImage": null,
      "itemizeAnalysis": null,
      "itemizeAnalysisImage": null,
      "videoAnalysis": null,
      "schoolName": null,
      "score": "1.5",
      "scoreDescribe": null,
      "id": null,
      "comparisonSummary": "| **细胞类型**     | **再生能力**                     | **典型例子**                     | **损伤后修复方式**         |  \n| :--------------- | :------------------------------- | :------------------------------- | :------------------------- |  \n| **稳定细胞**     | 低增殖，损伤后强再生             | 肝细胞（B正确）、肾小管上皮细胞  | 完全再生（结构功能恢复）   |  \n| **不稳定细胞**   | 持续分裂，再生能力强             | 小肠黏膜上皮（A）、皮肤表皮细胞  | 完全再生                   |  \n| **永久性细胞**   | 无再生能力                       | 神经细胞（C）、心肌细胞（D）     | 瘢痕修复（无功能恢复）     |",
      "mindMap": null,
      "mindMapImage": "https://image.muzhiyikao.com/mermaid_images/68aeec32/2222.png",
      "comparisonImages": null,
      "tags": null,
      "sort": null,
      "examRate": null,
      "userQuestionBankId": null,
      "userId": null,
      "isAnswer": 0,
      "userAnswer": null,
      "isRight": null,
      "isChop": 0,
      "isCollect": 0,
      "isLike": 0,
      "isNote": 0,
      "isComment": 0,
      "commentCount": null,
      "isContinue": null,
      "sortNumber": 14,
      "knowledgeImage": null,
      "difficulty": 1,
      "collectTotal": 0,
      "answerTotal": 0,
      "rightTotal": 0,
      "rightRate": "0.0",
      "myAnswerCount": 0,
      "myRightCount": 0,
      "myRightRate": "0"
    },
    {
      "questionTypeOption": null,
      "questionBankId": "2002338651450773669",
      "number": "2025N150X",
      "questionId": "1001030020015",
      "year": "2025",
      "questionBankCategoryId": "1001",
      "columnId": null,
      "courseId": "100103",
      "courseName": "病理学",
      "chapterId": "100103002",
      "chapterName": "第二章 损伤的修复",
      "questionBankType": "X",
      "topic": "属于永久性细胞的有",
      "topicImage": null,
      "content": "[\"{\\\"answer\\\":\\\"AB\\\",\\\"choose\\\":\\\"A\\\",\\\"right\\\":\\\"true\\\",\\\"content\\\":\\\"神经元\\\"}\",\"{\\\"answer\\\":\\\"AB\\\",\\\"choose\\\":\\\"B\\\",\\\"right\\\":\\\"true\\\",\\\"content\\\":\\\"心肌细胞\\\"}\",\"{\\\"answer\\\":\\\"AB\\\",\\\"choose\\\":\\\"C\\\",\\\"right\\\":\\\"false\\\",\\\"content\\\":\\\"成骨细胞\\\"}\",\"{\\\"answer\\\":\\\"AB\\\",\\\"choose\\\":\\\"D\\\",\\\"right\\\":\\\"false\\\",\\\"content\\\":\\\"平滑肌细胞\\\"}\"]",
      "answer": "AB",
      "source": null,
      "examCenterRestore": "《病理学》（第10版）指出：永久性细胞（又称非分裂细胞）是指高度分化、失去再生分裂能力的细胞，一旦破坏则永久缺失，无法通过细胞分裂修复。典型例子包括神经元（高度分化后不再分裂）和心肌细胞（成年后无分裂能力）。成骨细胞和平滑肌细胞不属于此类，前者保留一定增殖能力（如骨修复时），后者在损伤后可增生。",
      "examCenterRestoreImage": null,
      "basicAnalysis": "A<span style=\"color: #59BCA2; font-weight: bold;\"> [正确选项]</span>：神经元是高度分化的永久性细胞，成熟后无分裂能力，损伤后不可再生，该选项正确。<br>B<span style=\"color: #59BCA2; font-weight: bold;\"> [正确选项]</span>：心肌细胞在成年后失去分裂能力，属永久性细胞，损伤后由瘢痕组织替代，该选项正确。<br>C：成骨细胞具有分裂增殖潜能（如参与骨形成和修复），不属永久性细胞，该选项错误。<br>D：平滑肌细胞在生理或病理条件下（如血管损伤）可增生，不属永久性细胞，该选项错误。<br>",
      "basicAnalysisImage": null,
      "itemizeAnalysis": null,
      "itemizeAnalysisImage": null,
      "videoAnalysis": null,
      "schoolName": null,
      "score": "2",
      "scoreDescribe": null,
      "id": null,
      "comparisonSummary": "| 细胞类型 | 定义 | 再生能力 | 典型例子 | 临床意义 |  \n| :------- | :--- | :------- | :------- | :------- |  \n| **永久性细胞** | 高度分化，无分裂能力 | 无再生能力，损伤后永久缺失 | 神经元、心肌细胞 | 中枢神经损伤、心肌梗死不可逆 |  \n| **稳定细胞** | 低度增殖，静止状态可分裂 | 较强再生能力（刺激下分裂） | 肝细胞、成骨细胞 | 肝再生、骨折愈合 |  \n| **不稳定细胞** | 持续分裂更新 | 高再生能力 | 表皮细胞、黏膜上皮 | 伤口愈合、黏膜修复 |",
      "mindMap": null,
      "mindMapImage": "https://image.muzhiyikao.com/mermaid_images/68aeec32/2223.png",
      "comparisonImages": null,
      "tags": null,
      "sort": null,
      "examRate": null,
      "userQuestionBankId": null,
      "userId": null,
      "isAnswer": 0,
      "userAnswer": null,
      "isRight": null,
      "isChop": 0,
      "isCollect": 0,
      "isLike": 0,
      "isNote": 0,
      "isComment": 0,
      "commentCount": null,
      "isContinue": null,
      "sortNumber": 15,
      "knowledgeImage": null,
      "difficulty": 1,
      "collectTotal": 0,
      "answerTotal": 0,
      "rightTotal": 0,
      "rightRate": "0.0",
      "myAnswerCount": 0,
      "myRightCount": 0,
      "myRightRate": "0"
    },
    {
      "questionTypeOption": null,
      "questionBankId": "2002338651450773670",
      "number": "2009N43A",
      "questionId": "1001030020016",
      "year": "2009",
      "questionBankCategoryId": "1001",
      "columnId": null,
      "courseId": "100103",
      "courseName": "病理学",
      "chapterId": "100103002",
      "chapterName": "第二章 损伤的修复",
      "questionBankType": "A1",
      "topic": "维生素C缺乏常导致创伤愈合不良的主要原因是",
      "topicImage": null,
      "content": "[\"{\\\"answer\\\":\\\"B\\\",\\\"choose\\\":\\\"A\\\",\\\"right\\\":\\\"false\\\",\\\"content\\\":\\\"表皮再生困难\\\"}\",\"{\\\"answer\\\":\\\"B\\\",\\\"choose\\\":\\\"B\\\",\\\"right\\\":\\\"true\\\",\\\"content\\\":\\\"难以形成前胶原分子\\\"}\",\"{\\\"answer\\\":\\\"B\\\",\\\"choose\\\":\\\"C\\\",\\\"right\\\":\\\"false\\\",\\\"content\\\":\\\"炎症难以控制\\\"}\",\"{\\\"answer\\\":\\\"B\\\",\\\"choose\\\":\\\"D\\\",\\\"right\\\":\\\"false\\\",\\\"content\\\":\\\"局部神经营养不良\\\"}\"]",
      "answer": "B",
      "source": null,
      "examCenterRestore": "《病理学》（第10版）指出：维生素C是催化羟化酶的关键辅助因子，负责脯氨酸和赖氨酸的羟化，以形成前胶原分子；缺乏维生素C时，前胶原分子难以形成，从而影响胶原纤维的合成。",
      "examCenterRestoreImage": null,
      "basicAnalysis": "A：表皮再生困难 – 教材未提及维生素C缺乏直接影响表皮再生；维生素C主要作用于胶原合成，而非表皮细胞迁移或增殖。<br>B <span style=\"color: #59BCA2; font-weight: bold;\"> [正确选项]</span>：难以形成前胶原分子 – 教材明确描述维生素C是羟化酶的必需辅助因子，缺乏时脯氨酸和赖氨酸无法羟化，导致前胶原分子合成障碍。<br>C：炎症难以控制 – 教材强调感染通过毒素和酶加重组织损伤，但维生素C缺乏未直接与炎症调控关联。<br>D：局部神经营养不良 – 教材提及神经支配影响再生（如麻风病），但维生素C缺乏未涉及神经营养机制。<br>",
      "basicAnalysisImage": null,
      "itemizeAnalysis": null,
      "itemizeAnalysisImage": null,
      "videoAnalysis": null,
      "schoolName": null,
      "score": "1.5",
      "scoreDescribe": null,
      "id": null,
      "comparisonSummary": "| **因素**               | **对创伤愈合的影响**                | **教材依据** |  \n| :--------------------- | :---------------------------------- | :----------- |  \n| **维生素C缺乏（B）**   | 抑制脯氨酸/赖氨酸羟化 → 前胶原分子形成障碍 → 胶原纤维合成减少 | \"维生素C是催化羟化酶的关键辅助因子\"  |  \n| **蛋白质缺乏**         | 肉芽组织及胶原形成不良              | \"含硫氨基酸缺乏时愈合延缓\"  |  \n| **感染（C相关）**      | 细菌毒素溶解胶原，增加伤口张力      | \"化脓菌产生毒素溶解基质或胶原\"  |  \n| **神经损伤（D相关）**  | 局部神经营养不良影响再生            | \"自主神经损伤改变局部血供\"  |",
      "mindMap": null,
      "mindMapImage": "https://image.muzhiyikao.com/mermaid_images/68aeec32/2224.png",
      "comparisonImages": null,
      "tags": null,
      "sort": null,
      "examRate": null,
      "userQuestionBankId": null,
      "userId": null,
      "isAnswer": 0,
      "userAnswer": null,
      "isRight": null,
      "isChop": 0,
      "isCollect": 0,
      "isLike": 0,
      "isNote": 0,
      "isComment": 0,
      "commentCount": null,
      "isContinue": null,
      "sortNumber": 16,
      "knowledgeImage": null,
      "difficulty": 1,
      "collectTotal": 0,
      "answerTotal": 0,
      "rightTotal": 0,
      "rightRate": "0.0",
      "myAnswerCount": 0,
      "myRightCount": 0,
      "myRightRate": "0"
    },
    {
      "questionTypeOption": null,
      "questionBankId": "2002338651450773671",
      "number": "2016N44A",
      "questionId": "1001030020017",
      "year": "2016",
      "questionBankCategoryId": "1001",
      "columnId": null,
      "courseId": "100103",
      "courseName": "病理学",
      "chapterId": "100103002",
      "chapterName": "第二章 损伤的修复",
      "questionBankType": "A1",
      "topic": "下列创伤中，能完全修复的是",
      "topicImage": null,
      "content": "[\"{\\\"answer\\\":\\\"A\\\",\\\"choose\\\":\\\"A\\\",\\\"right\\\":\\\"true\\\",\\\"content\\\":\\\"闭合性骨折\\\"}\",\"{\\\"answer\\\":\\\"A\\\",\\\"choose\\\":\\\"B\\\",\\\"right\\\":\\\"false\\\",\\\"content\\\":\\\"一期愈合的手术切口\\\"}\",\"{\\\"answer\\\":\\\"A\\\",\\\"choose\\\":\\\"C\\\",\\\"right\\\":\\\"false\\\",\\\"content\\\":\\\"二期愈合的手术切口\\\"}\",\"{\\\"answer\\\":\\\"A\\\",\\\"choose\\\":\\\"D\\\",\\\"right\\\":\\\"false\\\",\\\"content\\\":\\\"三度烧伤的创面\\\"}\"]",
      "answer": "A",
      "source": null,
      "examCenterRestore": "《病理学》（第10版）指出：  \n- **完全修复（完全再生）**：由同种细胞再生修复，恢复原组织的结构和功能，见于再生能力强的组织（如骨组织）。闭合性骨折通过骨再生可完全愈合，恢复骨的结构和功能。  \n- **瘢痕修复（纤维性修复）**：由纤维结缔组织修复，形成瘢痕，无法恢复原功能。一期愈合的手术切口（如清洁切口）、二期愈合的手术切口（如感染切口）及三度烧伤创面均属此类修复方式。",
      "examCenterRestoreImage": null,
      "basicAnalysis": "A <span style=\"color: #59BCA2; font-weight: bold;\"> [正确选项]</span>：闭合性骨折中，骨组织属稳定细胞，再生能力强，可通过骨再生完全恢复结构和功能（如骨痂形成后重塑为正常骨）。<br>B：一期愈合的手术切口虽愈合快，但本质为瘢痕修复（胶原纤维替代），表皮仅部分再生，深层组织由瘢痕连接。<br>C：二期愈合的手术切口伴感染或坏死，肉芽组织填充后形成更显著的瘢痕，无完全再生。<br>D：三度烧伤累及皮肤全层及附件，表皮干细胞被破坏，仅能通过肉芽组织和瘢痕修复。<br>",
      "basicAnalysisImage": null,
      "itemizeAnalysis": null,
      "itemizeAnalysisImage": null,
      "videoAnalysis": null,
      "schoolName": null,
      "score": "1.5",
      "scoreDescribe": null,
      "id": null,
      "comparisonSummary": "| **创伤类型**               | **修复方式**         | **再生能力来源**       | **是否完全修复** | **临床结局**         |  \n| :------------------------- | :------------------- | :--------------------- | :--------------- | :------------------- |  \n| **闭合性骨折（A）**        | 完全再生             | 骨细胞（稳定细胞）     | 是               | 恢复骨结构和功能     |  \n| **一期愈合手术切口（B）**  | 瘢痕修复             | 表皮部分再生，深层纤维化 | 否               | 线性瘢痕，功能部分恢复 |  \n| **二期愈合手术切口（C）**  | 瘢痕修复             | 肉芽组织填充后纤维化   | 否               | 不规则瘢痕，功能受限 |  \n| **三度烧伤创面（D）**      | 瘢痕修复             | 皮肤附件破坏，无干细胞   | 否               | 挛缩瘢痕，功能丧失   |",
      "mindMap": null,
      "mindMapImage": "https://image.muzhiyikao.com/mermaid_images/68aeec32/2225.png",
      "comparisonImages": null,
      "tags": null,
      "sort": null,
      "examRate": null,
      "userQuestionBankId": null,
      "userId": null,
      "isAnswer": 0,
      "userAnswer": null,
      "isRight": null,
      "isChop": 0,
      "isCollect": 0,
      "isLike": 0,
      "isNote": 0,
      "isComment": 0,
      "commentCount": null,
      "isContinue": null,
      "sortNumber": 17,
      "knowledgeImage": null,
      "difficulty": 1,
      "collectTotal": 0,
      "answerTotal": 0,
      "rightTotal": 0,
      "rightRate": "0.0",
      "myAnswerCount": 0,
      "myRightCount": 0,
      "myRightRate": "0"
    },
    {
      "questionTypeOption": null,
      "questionBankId": "2002338651450773672",
      "number": "2012N44A",
      "questionId": "1001030020018",
      "year": "2012",
      "questionBankCategoryId": "1001",
      "columnId": null,
      "courseId": "100103",
      "courseName": "病理学",
      "chapterId": "100103002",
      "chapterName": "第二章 损伤的修复",
      "questionBankType": "A1",
      "topic": "下列骨折愈合描述中，骨折处表现为肉芽组织和排列紊乱的骨小梁的是",
      "topicImage": null,
      "content": "[\"{\\\"answer\\\":\\\"B\\\",\\\"choose\\\":\\\"A\\\",\\\"right\\\":\\\"false\\\",\\\"content\\\":\\\"纤维性骨痂形成\\\"}\",\"{\\\"answer\\\":\\\"B\\\",\\\"choose\\\":\\\"B\\\",\\\"right\\\":\\\"true\\\",\\\"content\\\":\\\"骨性骨痂形成\\\"}\",\"{\\\"answer\\\":\\\"B\\\",\\\"choose\\\":\\\"C\\\",\\\"right\\\":\\\"false\\\",\\\"content\\\":\\\"骨不愈合\\\"}\",\"{\\\"answer\\\":\\\"B\\\",\\\"choose\\\":\\\"D\\\",\\\"right\\\":\\\"false\\\",\\\"content\\\":\\\"骨痂重塑完成\\\"}\"]",
      "answer": "B",
      "source": null,
      "examCenterRestore": "《病理学》（第10版）指出：  \n> - **骨性骨痂形成阶段**：纤维性骨痂逐渐分化出成骨细胞，形成 **类骨组织**，钙盐沉积后转变为 **编织骨（woven bone）**。编织骨的结构 **不够致密，骨小梁排列紊乱**，同时该阶段仍存在肉芽组织参与的转化过程。  \n> - **其他阶段对比**：  \n>   - **纤维性骨痂形成**：由肉芽组织取代血肿并纤维化， **无骨小梁形成**。  \n>   - **骨痂重塑完成**：编织骨改建为成熟板层骨， **肉芽组织消失，骨小梁排列有序**。  \n>   - **骨不愈合**：无有效骨痂形成， **肉芽组织和骨小梁均缺失**。",
      "examCenterRestoreImage": null,
      "basicAnalysis": "A. **纤维性骨痂形成**：   教材描述此阶段为肉芽组织机化血肿并纤维化， **无骨小梁结构**，仅含纤维组织或透明软骨（）。<br>B. **<span style=\"color: #59BCA2; font-weight: bold;\"> [正确选项]</span>：骨性骨痂形成**：   教材明确此阶段形成 **编织骨**，其特征为 **骨小梁排列紊乱**，同时肉芽组织参与向骨组织的转化过程（）。<br>C. **骨不愈合**：   教材未直接描述，但指出骨不愈合时骨痂形成障碍， **无肉芽组织或骨小梁的病理表现**（）。<br>D. **骨痂重塑完成**：   教材强调此阶段编织骨改建为板层骨， **肉芽组织退化消失，骨小梁排列恢复规则**（）。<br>",
      "basicAnalysisImage": null,
      "itemizeAnalysis": null,
      "itemizeAnalysisImage": null,
      "videoAnalysis": null,
      "schoolName": null,
      "score": "1.5",
      "scoreDescribe": null,
      "id": null,
      "comparisonSummary": "| **骨折愈合阶段**       | **病理特征**                          | **肉芽组织** | **骨小梁状态**         |  \n|-------------------------|----------------------------------------|--------------|------------------------|  \n| **纤维性骨痂形成 (A)** | 肉芽组织纤维化，无骨结构              | 存在         | **无**                 |  \n| **骨性骨痂形成 (B)**   | 编织骨形成（类骨组织钙化）            | 存在（转化中）| **排列紊乱**           |  \n| **骨不愈合 (C)**       | 无有效骨痂，纤维瘢痕或假关节          | **无**       | **无**                 |  \n| **骨痂重塑完成 (D)**   | 板层骨成熟，哈佛系统重建              | **无**       | 排列规则（有序）       |",
      "mindMap": null,
      "mindMapImage": "https://image.muzhiyikao.com/mermaid_images/68aeec32/2226.png",
      "comparisonImages": null,
      "tags": null,
      "sort": null,
      "examRate": null,
      "userQuestionBankId": null,
      "userId": null,
      "isAnswer": 0,
      "userAnswer": null,
      "isRight": null,
      "isChop": 0,
      "isCollect": 0,
      "isLike": 0,
      "isNote": 0,
      "isComment": 0,
      "commentCount": null,
      "isContinue": null,
      "sortNumber": 18,
      "knowledgeImage": null,
      "difficulty": 1,
      "collectTotal": 0,
      "answerTotal": 0,
      "rightTotal": 0,
      "rightRate": "0.0",
      "myAnswerCount": 0,
      "myRightCount": 0,
      "myRightRate": "0"
    },
    {
      "questionTypeOption": null,
      "questionBankId": "2002338651450773673",
      "number": "2005N39A",
      "questionId": "1001030020019",
      "year": "2005",
      "questionBankCategoryId": "1001",
      "columnId": null,
      "courseId": "100103",
      "courseName": "病理学",
      "chapterId": "100103002",
      "chapterName": "第二章 损伤的修复",
      "questionBankType": "A1",
      "topic": "下列哪种新生的细胞是机化时出现的特征性细胞",
      "topicImage": null,
      "content": "[\"{\\\"answer\\\":\\\"B\\\",\\\"choose\\\":\\\"A\\\",\\\"right\\\":\\\"false\\\",\\\"content\\\":\\\"平滑肌细胞\\\"}\",\"{\\\"answer\\\":\\\"B\\\",\\\"choose\\\":\\\"B\\\",\\\"right\\\":\\\"true\\\",\\\"content\\\":\\\"成纤维细胞\\\"}\",\"{\\\"answer\\\":\\\"B\\\",\\\"choose\\\":\\\"C\\\",\\\"right\\\":\\\"false\\\",\\\"content\\\":\\\"类上皮细胞\\\"}\",\"{\\\"answer\\\":\\\"B\\\",\\\"choose\\\":\\\"D\\\",\\\"right\\\":\\\"false\\\",\\\"content\\\":\\\"横纹肌细胞\\\"}\",\"{\\\"answer\\\":\\\"B\\\",\\\"choose\\\":\\\"E\\\",\\\"right\\\":\\\"false\\\",\\\"content\\\":\\\"上皮细胞\\\"}\"]",
      "answer": "B",
      "source": null,
      "examCenterRestore": "《病理学》（第10版）指出：在组织修复过程中，肉芽组织由新生毛细血管、成纤维细胞和炎症细胞构成；其中成纤维细胞是肉芽组织的特征性细胞，负责合成胶原纤维，填补缺损并机化坏死组织或血栓。",
      "examCenterRestoreImage": null,
      "basicAnalysis": "A.平滑肌细胞：主要存在于血管壁和内脏器官（如胃肠道、子宫），参与收缩功能，非机化过程中的特征性细胞。<br>B <span style=\"color: #59BCA2; font-weight: bold;\"> [正确选项]</span>：成纤维细胞是肉芽组织的核心成分，在机化过程中增殖并分泌胶原，促进瘢痕形成。<br>C.类上皮细胞：见于肉芽肿性炎（如结核结节），由巨噬细胞衍生形成，与机化无关。<br>D.横纹肌细胞：包括骨骼肌和心肌细胞，属永久性细胞，无再生能力，不参与机化。<br>E.上皮细胞：参与表皮或黏膜的再生（如皮肤创伤愈合），但非机化特征性细胞。<br>",
      "basicAnalysisImage": null,
      "itemizeAnalysis": null,
      "itemizeAnalysisImage": null,
      "videoAnalysis": null,
      "schoolName": null,
      "score": "1",
      "scoreDescribe": null,
      "id": null,
      "comparisonSummary": "| **细胞类型**       | **在修复中的作用**                | **是否机化特征性细胞** | **相关疾病或过程**       |  \n| :----------------- | :-------------------------------- | :--------------------- | :----------------------- |  \n| **成纤维细胞（B）** | 合成胶原纤维，形成肉芽组织        | 是                     | 血栓机化、坏死组织替代   |  \n| **平滑肌细胞（A）** | 维持血管张力，参与器官收缩        | 否                     | 高血压、动脉粥样硬化     |  \n| **类上皮细胞（C）** | 构成肉芽肿，参与慢性炎症          | 否                     | 结核病、结节病           |  \n| **横纹肌细胞（D）** | 无再生能力，损伤后由瘢痕修复      | 否                     | 心肌梗死、肌营养不良     |  \n| **上皮细胞（E）**   | 表皮或黏膜再生，覆盖创面          | 否                     | 皮肤溃疡、黏膜糜烂愈合   |",
      "mindMap": null,
      "mindMapImage": "https://image.muzhiyikao.com/mermaid_images/68aeec32/2227.png",
      "comparisonImages": null,
      "tags": null,
      "sort": null,
      "examRate": null,
      "userQuestionBankId": null,
      "userId": null,
      "isAnswer": 0,
      "userAnswer": null,
      "isRight": null,
      "isChop": 0,
      "isCollect": 0,
      "isLike": 0,
      "isNote": 0,
      "isComment": 0,
      "commentCount": null,
      "isContinue": null,
      "sortNumber": 19,
      "knowledgeImage": null,
      "difficulty": 1,
      "collectTotal": 0,
      "answerTotal": 0,
      "rightTotal": 0,
      "rightRate": "0.0",
      "myAnswerCount": 0,
      "myRightCount": 0,
      "myRightRate": "0"
    },
    {
      "questionTypeOption": null,
      "questionBankId": "2002338651450773674",
      "number": "2006N37A",
      "questionId": "1001030020020",
      "year": "2006",
      "questionBankCategoryId": "1001",
      "columnId": null,
      "courseId": "100103",
      "courseName": "病理学",
      "chapterId": "100103002",
      "chapterName": "第二章 损伤的修复",
      "questionBankType": "A1",
      "topic": "下列细胞中，再生能力最弱的是",
      "topicImage": null,
      "content": "[\"{\\\"answer\\\":\\\"A\\\",\\\"choose\\\":\\\"A\\\",\\\"right\\\":\\\"true\\\",\\\"content\\\":\\\"心肌细胞\\\"}\",\"{\\\"answer\\\":\\\"A\\\",\\\"choose\\\":\\\"B\\\",\\\"right\\\":\\\"false\\\",\\\"content\\\":\\\"骨细胞\\\"}\",\"{\\\"answer\\\":\\\"A\\\",\\\"choose\\\":\\\"C\\\",\\\"right\\\":\\\"false\\\",\\\"content\\\":\\\"纤维细胞\\\"}\",\"{\\\"answer\\\":\\\"A\\\",\\\"choose\\\":\\\"D\\\",\\\"right\\\":\\\"false\\\",\\\"content\\\":\\\"血管内皮细胞\\\"}\",\"{\\\"answer\\\":\\\"A\\\",\\\"choose\\\":\\\"E\\\",\\\"right\\\":\\\"false\\\",\\\"content\\\":\\\"平滑肌细胞\\\"}\"]",
      "answer": "A",
      "source": null,
      "examCenterRestore": "《病理学》（第10版）指出：  \n- **心肌细胞**：再生能力极弱，破坏后由瘢痕修复，无有效再生机制。  \n- **骨细胞**：骨组织再生能力强，骨折后可完全修复。  \n- **纤维细胞**：成纤维细胞在损伤刺激下可分裂增生，参与修复。  \n- **血管内皮细胞**：可通过出芽式或套叠式血管生成再生新毛细血管。  \n- **平滑肌细胞**：有一定分裂再生能力（如小动脉修复），但大血管损伤后主要依赖瘢痕连接。",
      "examCenterRestoreImage": null,
      "basicAnalysis": "A <span style=\"color: #59BCA2; font-weight: bold;\"> [正确选项]</span>：心肌细胞再生能力极弱，教材明确描述为\"心肌再生能力极弱，破坏后一般都是瘢痕修复\"，属永久性细胞。<br>B：骨细胞再生能力强，教材指出\"骨组织再生能力强，骨折后可完全修复\"，属稳定细胞。<br>C：纤维细胞（成纤维细胞）可分裂增生，教材描述\"受损处的成纤维细胞进行分裂、增生\"，再生能力中等。<br>D：血管内皮细胞再生能力显著，教材详述其通过\"出芽式血管生成\"形成新毛细血管。<br>E：平滑肌细胞有一定再生能力，教材提到\"小动脉的再生中就有平滑肌的再生\"，但大血管损伤后再生有限。<br>",
      "basicAnalysisImage": null,
      "itemizeAnalysis": null,
      "itemizeAnalysisImage": null,
      "videoAnalysis": null,
      "schoolName": null,
      "score": "1",
      "scoreDescribe": null,
      "id": null,
      "comparisonSummary": "| **细胞类型**       | **再生能力**                     | **教材依据**                     | **修复方式**               |  \n| :----------------- | :------------------------------- | :------------------------------- | :------------------------- |  \n| **心肌细胞（A）**  | 极弱（永久性细胞）               | \"心肌再生能力极弱\"      | 瘢痕修复                   |  \n| **骨细胞（B）**    | 强（稳定细胞）                   | \"骨组织再生能力强\"      | 完全再生（骨痂形成）       |  \n| **纤维细胞（C）**  | 中等（稳定细胞）                 | \"成纤维细胞分裂增生\"    | 肉芽组织填充               |  \n| **血管内皮细胞（D）** | 强（不稳定细胞）               | \"出芽式血管生成\"        | 新生毛细血管网             |  \n| **平滑肌细胞（E）** | 有限（稳定细胞）                | \"平滑肌有一定分裂再生能力\"  | 小血管可再生，大血管瘢痕修复 |",
      "mindMap": null,
      "mindMapImage": "https://image.muzhiyikao.com/mermaid_images/68aeec32/2228.png",
      "comparisonImages": null,
      "tags": null,
      "sort": null,
      "examRate": null,
      "userQuestionBankId": null,
      "userId": null,
      "isAnswer": 0,
      "userAnswer": null,
      "isRight": null,
      "isChop": 0,
      "isCollect": 0,
      "isLike": 0,
      "isNote": 0,
      "isComment": 0,
      "commentCount": null,
      "isContinue": null,
      "sortNumber": 20,
      "knowledgeImage": null,
      "difficulty": 1,
      "collectTotal": 0,
      "answerTotal": 0,
      "rightTotal": 0,
      "rightRate": "0.0",
      "myAnswerCount": 0,
      "myRightCount": 0,
      "myRightRate": "0"
    },
    {
      "questionTypeOption": null,
      "questionBankId": "2002338651450773675",
      "number": "2012N164X",
      "questionId": "1001030020021",
      "year": "2012",
      "questionBankCategoryId": "1001",
      "columnId": null,
      "courseId": "100103",
      "courseName": "病理学",
      "chapterId": "100103002",
      "chapterName": "第二章 损伤的修复",
      "questionBankType": "X",
      "topic": "下列选项中符合肉芽组织特征的有",
      "topicImage": null,
      "content": "[\"{\\\"answer\\\":\\\"BC\\\",\\\"choose\\\":\\\"A\\\",\\\"right\\\":\\\"false\\\",\\\"content\\\":\\\"较多的多核巨细胞\\\"}\",\"{\\\"answer\\\":\\\"BC\\\",\\\"choose\\\":\\\"B\\\",\\\"right\\\":\\\"true\\\",\\\"content\\\":\\\"较多的成纤维细胞\\\"}\",\"{\\\"answer\\\":\\\"BC\\\",\\\"choose\\\":\\\"C\\\",\\\"right\\\":\\\"true\\\",\\\"content\\\":\\\"较多的内皮细胞\\\"}\",\"{\\\"answer\\\":\\\"BC\\\",\\\"choose\\\":\\\"D\\\",\\\"right\\\":\\\"false\\\",\\\"content\\\":\\\"较多的类上皮细胞\\\"}\"]",
      "answer": "BC",
      "source": null,
      "examCenterRestore": "《病理学》（第10版）指出：肉芽组织由新生薄壁的毛细血管（由内皮细胞构成）以及增生的成纤维细胞构成，并伴有炎症细胞浸润（如巨噬细胞、中性粒细胞及淋巴细胞）。镜下可见大量由内皮细胞增生形成的实性细胞索及扩张的毛细血管，周围有许多新生的成纤维细胞（图2-5、图2-6）。",
      "examCenterRestoreImage": null,
      "basicAnalysis": "A：较多的多核巨细胞 – 教材未提及肉芽组织含多核巨细胞；该细胞为肉芽肿性炎（如结核结节）的特征成分，故错误。<br>B <span style=\"color: #59BCA2; font-weight: bold;\"> [正确选项]</span>：较多的成纤维细胞 – 教材明确描述肉芽组织含\"增生的成纤维细胞\"，是核心成分之一（图2-5、图2-6）。<br>C <span style=\"color: #59BCA2; font-weight: bold;\"> [正确选项]</span>：较多的内皮细胞 – 教材强调\"新生薄壁的毛细血管由内皮细胞增生形成\"，是肉芽组织的基础结构。<br>D：较多的类上皮细胞 – 教材未涉及此类细胞；类上皮细胞是肉芽肿性炎的标志（如结节病），与肉芽组织无关，故错误。<br>",
      "basicAnalysisImage": null,
      "itemizeAnalysis": null,
      "itemizeAnalysisImage": null,
      "videoAnalysis": null,
      "schoolName": null,
      "score": "2",
      "scoreDescribe": null,
      "id": null,
      "comparisonSummary": "| **特征**               | **肉芽组织**                          | **肉芽肿**（对比）              |  \n| :--------------------- | :------------------------------------ | :------------------------------ |  \n| **核心细胞**           | 内皮细胞（C）、成纤维细胞（B）         | 类上皮细胞（D）、多核巨细胞（A） |  \n| **炎症细胞**           | 巨噬细胞、中性粒细胞、淋巴细胞         | 淋巴细胞、浆细胞                 |  \n| **结构特点**           | 新生毛细血管网+疏松基质（图2-5）      | 上皮样细胞聚集+坏死核心          |  \n| **功能**               | 填补缺损、抗感染、机化异物（如血栓）   | 包裹难溶性病原体（如结核杆菌）   |  \n| **临床关联**           | 创伤愈合二期修复（瘢痕形成前）         | 慢性肉芽肿性炎（如结核、真菌感染） |",
      "mindMap": null,
      "mindMapImage": "https://image.muzhiyikao.com/mermaid_images/68aeec32/2229.png",
      "comparisonImages": null,
      "tags": null,
      "sort": null,
      "examRate": null,
      "userQuestionBankId": null,
      "userId": null,
      "isAnswer": 0,
      "userAnswer": null,
      "isRight": null,
      "isChop": 0,
      "isCollect": 0,
      "isLike": 0,
      "isNote": 0,
      "isComment": 0,
      "commentCount": null,
      "isContinue": null,
      "sortNumber": 21,
      "knowledgeImage": null,
      "difficulty": 1,
      "collectTotal": 0,
      "answerTotal": 0,
      "rightTotal": 0,
      "rightRate": "0.0",
      "myAnswerCount": 0,
      "myRightCount": 0,
      "myRightRate": "0"
    },
    {
      "questionTypeOption": null,
      "questionBankId": "2002338651450773676",
      "number": "2009N42A",
      "questionId": "1001030020022",
      "year": "2009",
      "questionBankCategoryId": "1001",
      "columnId": null,
      "courseId": "100103",
      "courseName": "病理学",
      "chapterId": "100103002",
      "chapterName": "第二章 损伤的修复",
      "questionBankType": "A1",
      "topic": "下列选项中属于稳定细胞的是",
      "topicImage": null,
      "content": "[\"{\\\"answer\\\":\\\"C\\\",\\\"choose\\\":\\\"A\\\",\\\"right\\\":\\\"false\\\",\\\"content\\\":\\\"表皮细胞\\\"}\",\"{\\\"answer\\\":\\\"C\\\",\\\"choose\\\":\\\"B\\\",\\\"right\\\":\\\"false\\\",\\\"content\\\":\\\"消化道黏膜被覆上皮细胞\\\"}\",\"{\\\"answer\\\":\\\"C\\\",\\\"choose\\\":\\\"C\\\",\\\"right\\\":\\\"true\\\",\\\"content\\\":\\\"肾小管上皮细胞\\\"}\",\"{\\\"answer\\\":\\\"C\\\",\\\"choose\\\":\\\"D\\\",\\\"right\\\":\\\"false\\\",\\\"content\\\":\\\"神经细胞\\\"}\"]",
      "answer": "C",
      "source": null,
      "examCenterRestore": "《病理学》（第10版）指出：  \n- **稳定细胞（静止细胞）**：在生理情况下处于静止期（G₀期），但受损伤刺激时可进入增殖状态，表现出较强再生能力。包括腺体或腺样器官的实质细胞（如胰腺、唾液腺、肾小管上皮细胞等）。  \n- **对比分类**：  \n  - 不稳定细胞（持续分裂细胞）：如表皮细胞、消化道黏膜被覆上皮细胞，生理状态下持续更新。  \n  - 永久性细胞（非分裂细胞）：如神经细胞、心肌细胞，无再生能力。",
      "examCenterRestoreImage": null,
      "basicAnalysis": "A.表皮细胞：属不稳定细胞（持续分裂细胞），基底细胞不断增殖补充表层脱落细胞。<br>B.消化道黏膜被覆上皮细胞：属不稳定细胞，更新周期短（约1-2天），再生能力强。<br>C <span style=\"color: #59BCA2; font-weight: bold;\"> [正确选项]</span>：肾小管上皮细胞：属稳定细胞，生理状态下静止，损伤后（如急性肾小管坏死）可激活再生。<br>D.神经细胞：属永久性细胞，无再生能力，损伤后由胶质瘢痕修复。<br>",
      "basicAnalysisImage": null,
      "itemizeAnalysis": null,
      "itemizeAnalysisImage": null,
      "videoAnalysis": null,
      "schoolName": null,
      "score": "1.5",
      "scoreDescribe": null,
      "id": null,
      "comparisonSummary": "| **细胞类型**         | **再生能力**               | **典型代表**                     | **损伤后反应**               |  \n| :------------------- | :------------------------- | :------------------------------- | :--------------------------- |  \n| **稳定细胞（C）**    | 静止期可激活再生           | 肾小管上皮细胞、肝细胞、腺细胞   | 进入增殖周期，修复缺损       |  \n| **不稳定细胞（A,B）** | 持续分裂，再生能力强       | 表皮细胞、黏膜上皮、造血细胞     | 快速增殖补充                 |  \n| **永久性细胞（D）**  | 无再生能力                 | 神经细胞、心肌细胞、骨骼肌细胞   | 瘢痕修复，功能不可逆丧失     |",
      "mindMap": null,
      "mindMapImage": "https://image.muzhiyikao.com/mermaid_images/68aeec32/2230.png",
      "comparisonImages": null,
      "tags": null,
      "sort": null,
      "examRate": null,
      "userQuestionBankId": null,
      "userId": null,
      "isAnswer": 0,
      "userAnswer": null,
      "isRight": null,
      "isChop": 0,
      "isCollect": 0,
      "isLike": 0,
      "isNote": 0,
      "isComment": 0,
      "commentCount": null,
      "isContinue": null,
      "sortNumber": 22,
      "knowledgeImage": null,
      "difficulty": 1,
      "collectTotal": 0,
      "answerTotal": 0,
      "rightTotal": 0,
      "rightRate": "0.0",
      "myAnswerCount": 0,
      "myRightCount": 0,
      "myRightRate": "0"
    },
    {
      "questionTypeOption": null,
      "questionBankId": "2002338651450773677",
      "number": "1991N62A",
      "questionId": "1001030020023",
      "year": "1991",
      "questionBankCategoryId": "1001",
      "columnId": null,
      "courseId": "100103",
      "courseName": "病理学",
      "chapterId": "100103002",
      "chapterName": "第二章 损伤的修复",
      "questionBankType": "A1",
      "topic": "下述各种细胞中，哪种再生能力最强",
      "topicImage": null,
      "content": "[\"{\\\"answer\\\":\\\"D\\\",\\\"choose\\\":\\\"A\\\",\\\"right\\\":\\\"false\\\",\\\"content\\\":\\\"神经细胞\\\"}\",\"{\\\"answer\\\":\\\"D\\\",\\\"choose\\\":\\\"B\\\",\\\"right\\\":\\\"false\\\",\\\"content\\\":\\\"心肌细胞\\\"}\",\"{\\\"answer\\\":\\\"D\\\",\\\"choose\\\":\\\"C\\\",\\\"right\\\":\\\"false\\\",\\\"content\\\":\\\"软骨细胞\\\"}\",\"{\\\"answer\\\":\\\"D\\\",\\\"choose\\\":\\\"D\\\",\\\"right\\\":\\\"true\\\",\\\"content\\\":\\\"神经胶质细胞\\\"}\",\"{\\\"answer\\\":\\\"D\\\",\\\"choose\\\":\\\"E\\\",\\\"right\\\":\\\"false\\\",\\\"content\\\":\\\"骨骼肌细胞\\\"}\"]",
      "answer": "D",
      "source": null,
      "examCenterRestore": "《病理学》（第10版）指出：  \n- **神经胶质细胞**（如施万细胞）在神经损伤后可显著增生，形成带状的合体细胞连接断端，支持轴突再生（约1mm/d），是神经修复的核心细胞。  \n- **神经细胞**（神经元）属永久性细胞，无再生能力，损伤后由胶质细胞修复。  \n- **心肌细胞**和**骨骼肌细胞**同为永久性细胞，无再生能力，损伤后由瘢痕修复（教材未直接提及，但符合分类共识）。  \n- **软骨细胞**属稳定细胞，再生能力有限，大缺损需纤维组织参与修补（教材未直接提及）。",
      "examCenterRestoreImage": null,
      "basicAnalysis": "A.神经细胞：属永久性细胞，无分裂再生能力，损伤后不可逆。<br>B.心肌细胞：属永久性细胞，无再生能力，梗死区域由瘢痕替代。<br>C.软骨细胞：属稳定细胞，有较弱再生能力，但不足以完全修复大范围缺损。<br>D <span style=\"color: #59BCA2; font-weight: bold;\"> [正确选项]</span>：神经胶质细胞（如施万细胞）属稳定细胞，损伤后可活跃增生（教材描述其\"增生形成带状的合体细胞\"），支持轴突再生，再生能力显著。<br>E.骨骼肌细胞：属永久性细胞，无再生能力，损伤后由纤维瘢痕修复。<br>",
      "basicAnalysisImage": null,
      "itemizeAnalysis": null,
      "itemizeAnalysisImage": null,
      "videoAnalysis": null,
      "schoolName": null,
      "score": "1",
      "scoreDescribe": null,
      "id": null,
      "comparisonSummary": "| **细胞类型**         | **再生能力分类** | **再生能力描述**                     | **教材依据**         |  \n| :------------------- | :--------------- | :----------------------------------- | :------------------- |  \n| **神经胶质细胞（D）** | 稳定细胞         | 损伤后显著增生（如施万细胞连接断端） | 明确描述    |  \n| **软骨细胞（C）**     | 稳定细胞         | 有限再生，大缺损需纤维组织参与       | 未直接提及           |  \n| **神经细胞（A）**     | 永久性细胞       | 无再生能力                           | 教材暗示无再生 |  \n| **心肌细胞（B）**     | 永久性细胞       | 无再生能力                           | 未直接提及           |  \n| **骨骼肌细胞（E）**   | 永久性细胞       | 无再生能力                           | 未直接提及           |",
      "mindMap": null,
      "mindMapImage": "https://image.muzhiyikao.com/mermaid_images/68aeec32/2231.png",
      "comparisonImages": null,
      "tags": null,
      "sort": null,
      "examRate": null,
      "userQuestionBankId": null,
      "userId": null,
      "isAnswer": 0,
      "userAnswer": null,
      "isRight": null,
      "isChop": 0,
      "isCollect": 0,
      "isLike": 0,
      "isNote": 0,
      "isComment": 0,
      "commentCount": null,
      "isContinue": null,
      "sortNumber": 23,
      "knowledgeImage": null,
      "difficulty": 1,
      "collectTotal": 0,
      "answerTotal": 0,
      "rightTotal": 0,
      "rightRate": "0.0",
      "myAnswerCount": 0,
      "myRightCount": 0,
      "myRightRate": "0"
    },
    {
      "questionTypeOption": null,
      "questionBankId": "2002338651450773678",
      "number": "1996N37A",
      "questionId": "1001030020024",
      "year": "1996",
      "questionBankCategoryId": "1001",
      "columnId": null,
      "courseId": "100103",
      "courseName": "病理学",
      "chapterId": "100103002",
      "chapterName": "第二章 损伤的修复",
      "questionBankType": "A1",
      "topic": "下述描述中，哪种属于完全再生",
      "topicImage": null,
      "content": "[\"{\\\"answer\\\":\\\"B\\\",\\\"choose\\\":\\\"A\\\",\\\"right\\\":\\\"false\\\",\\\"content\\\":\\\"动脉吻合口愈合\\\"}\",\"{\\\"answer\\\":\\\"B\\\",\\\"choose\\\":\\\"B\\\",\\\"right\\\":\\\"true\\\",\\\"content\\\":\\\"骨折愈合再建\\\"}\",\"{\\\"answer\\\":\\\"B\\\",\\\"choose\\\":\\\"C\\\",\\\"right\\\":\\\"false\\\",\\\"content\\\":\\\"剖腹手术切口愈合\\\"}\",\"{\\\"answer\\\":\\\"B\\\",\\\"choose\\\":\\\"D\\\",\\\"right\\\":\\\"false\\\",\\\"content\\\":\\\"肠吻合口愈合\\\"}\",\"{\\\"answer\\\":\\\"B\\\",\\\"choose\\\":\\\"E\\\",\\\"right\\\":\\\"false\\\",\\\"content\\\":\\\"胃溃疡愈合\\\"}\"]",
      "answer": "B",
      "source": null,
      "examCenterRestore": "《病理学》（第10版）指出：  \n- **骨组织再生**：再生能力强，骨折后可完全修复，恢复原有结构和功能。  \n- **肌组织再生**：平滑肌再生能力有限，大血管或肠管吻合后主要依赖纤维瘢痕修复，非完全再生。  \n- **皮肤及黏膜修复**：手术切口或溃疡愈合常伴肉芽组织增生，最终形成瘢痕，属不完全再生。",
      "examCenterRestoreImage": null,
      "basicAnalysis": "A.动脉吻合口愈合：大血管离断后肌层不易完全再生，由结缔组织瘢痕连接（教材：\"断处的平滑肌主要通过纤维瘢痕连接\"），非完全再生。<br>B <span style=\"color: #59BCA2; font-weight: bold;\"> [正确选项]</span>：骨折愈合可完全恢复骨组织结构和功能（教材：\"骨组织的再生能力强，骨折后可完全修复\"），属完全再生。<br>C.剖腹手术切口愈合：涉及皮肤及深层组织，修复过程伴肉芽组织增生和瘢痕形成（教材：\"创缘基底层细胞分裂增生，但深层损伤由纤维组织参与修补\"），非完全再生。<br>D.肠吻合口愈合：肠管断开后平滑肌再生受限，主要依赖纤维瘢痕连接（教材：\"断开的肠管平滑肌通过纤维瘢痕连接\"），非完全再生。<br>E.胃溃疡愈合：胃黏膜损伤后若基底膜破坏，腺体结构难以完全再生（教材：\"腺体构造完全破坏则难以再生\"），常形成瘢痕修复。<br>",
      "basicAnalysisImage": null,
      "itemizeAnalysis": null,
      "itemizeAnalysisImage": null,
      "videoAnalysis": null,
      "schoolName": null,
      "score": "1",
      "scoreDescribe": null,
      "id": null,
      "comparisonSummary": "| **组织/损伤类型**       | **再生能力**               | **修复方式**         | **教材依据**                     |  \n| :---------------------- | :------------------------- | :------------------- | :------------------------------- |  \n| **骨组织（B）**         | 强（完全再生）             | 骨痂重塑恢复原结构   | \"骨折后可完全修复\"      |  \n| **平滑肌（A、D）**      | 弱（瘢痕修复）             | 纤维结缔组织连接     | \"平滑肌主要通过纤维瘢痕连接\"  |  \n| **皮肤手术切口（C）**   | 中等（不完全再生）         | 肉芽组织+瘢痕形成   | \"基底层细胞分裂，深层纤维修补\"  |  \n| **腺上皮溃疡（E）**     | 依赖基底膜完整性           | 瘢痕或不完全再生     | \"基底膜破坏则难以再生\"  |",
      "mindMap": null,
      "mindMapImage": "https://image.muzhiyikao.com/mermaid_images/68aeec32/2232.png",
      "comparisonImages": null,
      "tags": null,
      "sort": null,
      "examRate": null,
      "userQuestionBankId": null,
      "userId": null,
      "isAnswer": 0,
      "userAnswer": null,
      "isRight": null,
      "isChop": 0,
      "isCollect": 0,
      "isLike": 0,
      "isNote": 0,
      "isComment": 0,
      "commentCount": null,
      "isContinue": null,
      "sortNumber": 24,
      "knowledgeImage": null,
      "difficulty": 1,
      "collectTotal": 0,
      "answerTotal": 0,
      "rightTotal": 0,
      "rightRate": "0.0",
      "myAnswerCount": 0,
      "myRightCount": 0,
      "myRightRate": "0"
    },
    {
      "questionTypeOption": null,
      "questionBankId": "2002338651450773679",
      "number": "1994N34A",
      "questionId": "1001030020025",
      "year": "1994",
      "questionBankCategoryId": "1001",
      "columnId": null,
      "courseId": "100103",
      "courseName": "病理学",
      "chapterId": "100103002",
      "chapterName": "第二章 损伤的修复",
      "questionBankType": "A1",
      "topic": "下述哪种细胞属于永久性细胞",
      "topicImage": null,
      "content": "[\"{\\\"answer\\\":\\\"D\\\",\\\"choose\\\":\\\"A\\\",\\\"right\\\":\\\"false\\\",\\\"content\\\":\\\"造血细胞\\\"}\",\"{\\\"answer\\\":\\\"D\\\",\\\"choose\\\":\\\"B\\\",\\\"right\\\":\\\"false\\\",\\\"content\\\":\\\"表皮细胞\\\"}\",\"{\\\"answer\\\":\\\"D\\\",\\\"choose\\\":\\\"C\\\",\\\"right\\\":\\\"false\\\",\\\"content\\\":\\\"肝细胞\\\"}\",\"{\\\"answer\\\":\\\"D\\\",\\\"choose\\\":\\\"D\\\",\\\"right\\\":\\\"true\\\",\\\"content\\\":\\\"心肌细胞\\\"}\",\"{\\\"answer\\\":\\\"D\\\",\\\"choose\\\":\\\"E\\\",\\\"right\\\":\\\"false\\\",\\\"content\\\":\\\"肾小管细胞\\\"}\"]",
      "answer": "D",
      "source": null,
      "examCenterRestore": "《病理学》（第10版）指出：  \n- **永久性细胞（非分裂细胞）**：再生能力极弱，无论在生理状态或损伤刺激下均无再生能力，包括神经细胞、骨骼肌细胞及心肌细胞。  \n- **对比分类**：  \n  - 不稳定细胞（持续分裂细胞）：如造血细胞（A）、表皮细胞（B），生理状态下持续更新。  \n  - 稳定细胞（静止细胞）：如肝细胞（C）、肾小管细胞（E），损伤后可激活再生。",
      "examCenterRestoreImage": null,
      "basicAnalysis": "A.造血细胞：属不稳定细胞，教材描述为\"总在不断地增殖\"（如骨髓造血），再生能力强。<br>B.表皮细胞：属不稳定细胞，教材明确为\"表皮基底细胞不断增生分化\"。<br>C.肝细胞：属稳定细胞，教材指出\"肝脏在切除70%后仍可快速再生\"。<br>D <span style=\"color: #59BCA2; font-weight: bold;\"> [正确选项]</span>：心肌细胞：属永久性细胞，教材强调\"一旦遭受破坏则成为永久性缺失\"。<br>E.肾小管细胞：属稳定细胞，教材提及\"肾小管上皮细胞在损伤后进入增殖周期\"。<br>",
      "basicAnalysisImage": null,
      "itemizeAnalysis": null,
      "itemizeAnalysisImage": null,
      "videoAnalysis": null,
      "schoolName": null,
      "score": "1",
      "scoreDescribe": null,
      "id": null,
      "comparisonSummary": "| **细胞类型**         | **再生能力**               | **教材依据**                     | **临床意义**                 |  \n| :------------------- | :------------------------- | :------------------------------- | :--------------------------- |  \n| **永久性细胞（D）**  | 无再生能力                 | \"遭受破坏后永久性缺失\"  | 心肌梗死→瘢痕修复（室壁瘤） |  \n| **不稳定细胞（A,B）** | 持续分裂，再生能力强       | \"总在不断地增殖\"       | 创伤后快速修复（如表皮更新）|  \n| **稳定细胞（C,E）**  | 静止期可激活再生           | \"损伤后进入增殖周期\"   | 肝切除后再生、肾小管坏死修复 |",
      "mindMap": null,
      "mindMapImage": "https://image.muzhiyikao.com/mermaid_images/68aeec32/2233.png",
      "comparisonImages": null,
      "tags": null,
      "sort": null,
      "examRate": null,
      "userQuestionBankId": null,
      "userId": null,
      "isAnswer": 0,
      "userAnswer": null,
      "isRight": null,
      "isChop": 0,
      "isCollect": 0,
      "isLike": 0,
      "isNote": 0,
      "isComment": 0,
      "commentCount": null,
      "isContinue": null,
      "sortNumber": 25,
      "knowledgeImage": null,
      "difficulty": 1,
      "collectTotal": 0,
      "answerTotal": 0,
      "rightTotal": 0,
      "rightRate": "0.0",
      "myAnswerCount": 0,
      "myRightCount": 0,
      "myRightRate": "0"
    },
    {
      "questionTypeOption": null,
      "questionBankId": "2002338651450773680",
      "number": "2013N45A",
      "questionId": "1001030020026",
      "year": "2013",
      "questionBankCategoryId": "1001",
      "columnId": null,
      "courseId": "100103",
      "courseName": "病理学",
      "chapterId": "100103002",
      "chapterName": "第二章 损伤的修复",
      "questionBankType": "A1",
      "topic": "在伤口愈合时，对增加伤口愈合强度起主要作用的是",
      "topicImage": null,
      "content": "[\"{\\\"answer\\\":\\\"C\\\",\\\"choose\\\":\\\"A\\\",\\\"right\\\":\\\"false\\\",\\\"content\\\":\\\"成纤维细胞\\\"}\",\"{\\\"answer\\\":\\\"C\\\",\\\"choose\\\":\\\"B\\\",\\\"right\\\":\\\"false\\\",\\\"content\\\":\\\"毛细血管\\\"}\",\"{\\\"answer\\\":\\\"C\\\",\\\"choose\\\":\\\"C\\\",\\\"right\\\":\\\"true\\\",\\\"content\\\":\\\"细胞外基质\\\"}\",\"{\\\"answer\\\":\\\"C\\\",\\\"choose\\\":\\\"D\\\",\\\"right\\\":\\\"false\\\",\\\"content\\\":\\\"良好的血供\\\"}\"]",
      "answer": "C",
      "source": null,
      "examCenterRestore": "《病理学》（第10版）指出：  \n- **细胞外基质**：胶原的积聚是增加伤口愈合强度的核心因素，不仅与胶原合成增加有关，还与胶原降解抑制有关。肉芽组织最终转变为含致密胶原的瘢痕，显著提升机械强度。  \n- **对比其他因素**：  \n  - 成纤维细胞：虽产生胶原，但后期数量减少，非直接强度来源（图2-9）。  \n  - 毛细血管：提供营养，但在瘢痕成熟过程中逐渐退化，演变为\"血管稀少\"状态（图2-8）。  \n  - 良好血供：仅支持愈合过程，不直接决定强度（局部血液循环影响修复速度）。",
      "examCenterRestoreImage": null,
      "basicAnalysis": "A.成纤维细胞：教材描述其\"产生胶原纤维\"，但强调胶原积累后成纤维细胞作用减弱，非强度主因。<br>B.毛细血管：教材明确\"血管逐渐退化\"，瘢痕最终\"苍白、血管稀少\"，说明其营养作用非强度核心。<br>C <span style=\"color: #59BCA2; font-weight: bold;\"> [正确选项]</span>：细胞外基质：教材多次强调\"胶原纤维越来越多\"直接导致瘢痕形成，是强度增加的直接物质基础（图2-8、图2-9）。<br>D.良好的血供：教材指出其促进\"再生修复\"，但未关联强度提升，属支持性因素。<br>",
      "basicAnalysisImage": null,
      "itemizeAnalysis": null,
      "itemizeAnalysisImage": null,
      "videoAnalysis": null,
      "schoolName": null,
      "score": "1.5",
      "scoreDescribe": null,
      "id": null,
      "comparisonSummary": "| **因素**           | **在伤口愈合中的作用**          | **教材依据**                     | **与强度的关联**           |  \n| :----------------- | :------------------------------ | :------------------------------- | :------------------------- |  \n| **细胞外基质（C）** | 胶原积累形成致密瘢痕            | \"胶原纤维越来越多，出现瘢痕形成\" | 直接增加机械强度（核心）   |  \n| **成纤维细胞（A）** | 合成胶原，但后期减少            | \"第5~6天起成纤维细胞产生胶原纤维\" | 间接作用（合成者）         |  \n| **毛细血管（B）**   | 提供营养，瘢痕成熟后退化        | \"血管逐渐退化→血管稀少的瘢痕\"    | 无直接关联（仅支持代谢）   |  \n| **良好血供（D）**   | 加速修复，防止感染              | \"局部血液供应良好时再生修复理想\" | 间接支持（非强度决定因素） |",
      "mindMap": null,
      "mindMapImage": "https://image.muzhiyikao.com/mermaid_images/68aeec32/2234.png",
      "comparisonImages": null,
      "tags": null,
      "sort": null,
      "examRate": null,
      "userQuestionBankId": null,
      "userId": null,
      "isAnswer": 0,
      "userAnswer": null,
      "isRight": null,
      "isChop": 0,
      "isCollect": 0,
      "isLike": 0,
      "isNote": 0,
      "isComment": 0,
      "commentCount": null,
      "isContinue": null,
      "sortNumber": 26,
      "knowledgeImage": null,
      "difficulty": 1,
      "collectTotal": 0,
      "answerTotal": 0,
      "rightTotal": 0,
      "rightRate": "0.0",
      "myAnswerCount": 0,
      "myRightCount": 0,
      "myRightRate": "0"
    },
    {
      "questionTypeOption": null,
      "questionBankId": "2002338651450773681",
      "number": "2022N34A",
      "questionId": "1001030020027",
      "year": "2022",
      "questionBankCategoryId": "1001",
      "columnId": null,
      "courseId": "100103",
      "courseName": "病理学",
      "chapterId": "100103002",
      "chapterName": "第二章 损伤的修复",
      "questionBankType": "A1",
      "topic": "组织损伤时，完成纤维性修复的最重要细胞是",
      "topicImage": null,
      "content": "[\"{\\\"answer\\\":\\\"C\\\",\\\"choose\\\":\\\"A\\\",\\\"right\\\":\\\"false\\\",\\\"content\\\":\\\"纤维细胞\\\"}\",\"{\\\"answer\\\":\\\"C\\\",\\\"choose\\\":\\\"B\\\",\\\"right\\\":\\\"false\\\",\\\"content\\\":\\\"血管内皮细胞\\\"}\",\"{\\\"answer\\\":\\\"C\\\",\\\"choose\\\":\\\"C\\\",\\\"right\\\":\\\"true\\\",\\\"content\\\":\\\"成纤维细胞\\\"}\",\"{\\\"answer\\\":\\\"C\\\",\\\"choose\\\":\\\"D\\\",\\\"right\\\":\\\"false\\\",\\\"content\\\":\\\"巨噬细胞\\\"}\"]",
      "answer": "C",
      "source": null,
      "examCenterRestore": "《病理学》（第10版）指出：  \n> - **成纤维细胞**是纤维性修复的核心细胞，通过产生胶原和细胞外基质（ECM），直接参与肉芽组织形成和瘢痕修复。  \n> - **其他细胞作用**：  \n>   - 血管内皮细胞受FGF调控参与毛细血管新生，提供营养支持。  \n>   - 巨噬细胞分泌TGF-β等生长因子，间接刺激成纤维细胞增殖。  \n>   - 纤维细胞在教材中未明确区分于成纤维细胞，但非修复主力。",
      "examCenterRestoreImage": null,
      "basicAnalysis": "A. **纤维细胞**：   教材未明确其与成纤维细胞的区别，但强调成纤维细胞为活跃状态，负责基质合成；纤维细胞可能指静止状态，修复作用次要。<br>B. **血管内皮细胞**：   受FGF调控参与血管新生，为修复提供微环境，但非胶原沉积的直接执行者。<br>C. **<span style=\"color: #59BCA2; font-weight: bold;\"> [正确选项]</span>：成纤维细胞**：   教材明确其为纤维性修复的\"关键细胞\"：   - 产生胶原（如Ⅰ、Ⅲ型）和ECM成分（纤维粘连蛋白）。<br>   - TGF-β直接促进其趋化、胶原合成及纤维化。<br>   - 肉芽组织转变为瘢痕的核心驱动者。<br>D. **巨噬细胞**：   分泌TGF-β等因子间接刺激成纤维细胞，但自身不产生胶原，非直接修复细胞。<br>",
      "basicAnalysisImage": null,
      "itemizeAnalysis": null,
      "itemizeAnalysisImage": null,
      "videoAnalysis": null,
      "schoolName": null,
      "score": "1.5",
      "scoreDescribe": null,
      "id": null,
      "comparisonSummary": "| **细胞类型**       | **在纤维性修复中的作用**                | **调控机制**                          | **教材依据**                     |  \n|---------------------|-----------------------------------------|---------------------------------------|----------------------------------|  \n| **成纤维细胞 (C)**  | **核心作用**：合成胶原/ECM，驱动瘢痕形成 | TGF-β促进趋化与胶原生成               | 明确描述（ECM沉积与纤维化关键） |  \n| **血管内皮细胞 (B)** | 辅助作用：形成新生毛细血管，提供营养     | FGF诱导内皮细胞分裂和迁移             | FGF作用于内皮细胞       |  \n| **巨噬细胞 (D)**    | 间接作用：分泌TGF-β等因子刺激成纤维细胞  | 炎症反应中释放生长因子                | 巨噬细胞产生TGF-β       |  \n| **纤维细胞 (A)**    | 未明确：可能为成纤维细胞的静止状态       | 无主动合成胶原能力                   | 未直接提及                       |",
      "mindMap": null,
      "mindMapImage": "https://image.muzhiyikao.com/mermaid_images/68aeec32/2235.png",
      "comparisonImages": null,
      "tags": null,
      "sort": null,
      "examRate": null,
      "userQuestionBankId": null,
      "userId": null,
      "isAnswer": 0,
      "userAnswer": null,
      "isRight": null,
      "isChop": 0,
      "isCollect": 0,
      "isLike": 0,
      "isNote": 0,
      "isComment": 0,
      "commentCount": null,
      "isContinue": null,
      "sortNumber": 27,
      "knowledgeImage": null,
      "difficulty": 1,
      "collectTotal": 0,
      "answerTotal": 0,
      "rightTotal": 0,
      "rightRate": "0.0",
      "myAnswerCount": 0,
      "myRightCount": 0,
      "myRightRate": "0"
    },
    {
      "questionTypeOption": null,
      "questionBankId": "2002338651450773682",
      "number": "2005N40A",
      "questionId": "1001030020028",
      "year": "2005",
      "questionBankCategoryId": "1001",
      "columnId": null,
      "courseId": "100103",
      "courseName": "病理学",
      "chapterId": "100103002",
      "chapterName": "第二章 损伤的修复",
      "questionBankType": "A1",
      "topic": "组织修复过程中，再生能力弱的组织是",
      "topicImage": null,
      "content": "[\"{\\\"answer\\\":\\\"C\\\",\\\"choose\\\":\\\"A\\\",\\\"right\\\":\\\"false\\\",\\\"content\\\":\\\"上皮组织\\\"}\",\"{\\\"answer\\\":\\\"C\\\",\\\"choose\\\":\\\"B\\\",\\\"right\\\":\\\"false\\\",\\\"content\\\":\\\"纤维组织\\\"}\",\"{\\\"answer\\\":\\\"C\\\",\\\"choose\\\":\\\"C\\\",\\\"right\\\":\\\"true\\\",\\\"content\\\":\\\"软骨细胞\\\"}\",\"{\\\"answer\\\":\\\"C\\\",\\\"choose\\\":\\\"D\\\",\\\"right\\\":\\\"false\\\",\\\"content\\\":\\\"骨组织\\\"}\",\"{\\\"answer\\\":\\\"C\\\",\\\"choose\\\":\\\"E\\\",\\\"right\\\":\\\"false\\\",\\\"content\\\":\\\"毛细血管\\\"}\"]",
      "answer": "C",
      "source": null,
      "examCenterRestore": "《病理学》（第10版）指出：  \n- **软骨组织再生能力弱**：软骨组织缺损较大时需由纤维组织参与修补，无法完全再生。  \n- **对比其他组织**：  \n  - 骨组织再生能力强，骨折后可完全修复。  \n  - 上皮组织（如皮肤、黏膜）再生能力强，基底层细胞可快速分裂补充。  \n  - 纤维组织再生能力强，成纤维细胞可活跃增生。  \n  - 毛细血管再生能力强，可通过出芽或套叠方式新生。",
      "examCenterRestoreImage": null,
      "basicAnalysis": "A.上皮组织：再生能力强，教材描述\"基底层细胞分裂增生，向缺损中心迁移\"，如皮肤或黏膜缺损可完全修复。<br>B.纤维组织：再生能力强，教材明确\"成纤维细胞分裂、增生，分泌胶原形成新纤维\"。<br>C <span style=\"color: #59BCA2; font-weight: bold;\"> [正确选项]</span>：软骨细胞：再生能力弱，教材强调\"软骨再生能力弱，缺损较大时由纤维组织参与修补\"。<br>D.骨组织：再生能力强，教材指出\"骨组织再生能力强，骨折后可完全修复\"。<br>E.毛细血管：再生能力强，教材描述\"出芽式或套叠式血管生成，可形成新生毛细血管网\"。<br>",
      "basicAnalysisImage": null,
      "itemizeAnalysis": null,
      "itemizeAnalysisImage": null,
      "videoAnalysis": null,
      "schoolName": null,
      "score": "1",
      "scoreDescribe": null,
      "id": null,
      "comparisonSummary": "| **组织类型**       | **再生能力** | **修复机制**                     | **教材依据**               |  \n| :----------------- | :----------- | :------------------------------- | :------------------------- |  \n| **软骨组织（C）**   | 弱           | 大缺损需纤维组织参与修补         | \"软骨再生能力弱\"  |  \n| **骨组织（D）**     | 强           | 完全再生恢复原结构               | \"骨折后可完全修复\"|  \n| **上皮组织（A）**   | 强           | 基底层细胞分裂迁移修复           | \"基底层细胞分裂增生\"|  \n| **纤维组织（B）**   | 强           | 成纤维细胞增生分泌胶原           | \"成纤维细胞分裂增生\"|  \n| **毛细血管（E）**   | 强           | 出芽式/套叠式生成新血管          | \"形成毛细血管网\" |",
      "mindMap": null,
      "mindMapImage": "https://image.muzhiyikao.com/mermaid_images/68aeec32/2236.png",
      "comparisonImages": null,
      "tags": null,
      "sort": null,
      "examRate": null,
      "userQuestionBankId": null,
      "userId": null,
      "isAnswer": 0,
      "userAnswer": null,
      "isRight": null,
      "isChop": 0,
      "isCollect": 0,
      "isLike": 0,
      "isNote": 0,
      "isComment": 0,
      "commentCount": null,
      "isContinue": null,
      "sortNumber": 28,
      "knowledgeImage": null,
      "difficulty": 1,
      "collectTotal": 1,
      "answerTotal": 1,
      "rightTotal": 0,
      "rightRate": "0.0",
      "myAnswerCount": 0,
      "myRightCount": 0,
      "myRightRate": "0"
    }
  ]
}